Workbook
Name _Toc464338185: 'TABLA RetFte'!$A$16

Sheet Grupos Familiares
A1: GERMÁN TULIO FERNÁNDEZ FERNÁNDEZ
A2: GRUPOS FAMILIARES | I2: ENVIADO | L2: RETENCIÓN EN LA FUENTE
A3: PRESUPUESTO DE COBROS | I3: SIN ENVIAR
A4: AÑO GRAVABLE 2024 | O4: RETENCIÓN FUENTE -Honorarios- | P4: UVT 2025
B5: =+A583 -> GRAN TOTAL | C5: =+C583 -> 121229000 | D5: =+D583 -> 23033510 | E5: =+E583 -> -12447490 | F5: =+F583 -> 144262510 | G5: =+G583 -> 131815020 | H5: =+H583 -> 96430000 | I5: =+I583 -> 228245020 | O5: 0.11 | P5: 49799
A6: No. | B6: APELLIDOS Y NOMBRES o RAZÓN SOCIAL | C6: VALOR FACTURA | D6: I V A | E6: RETENCIÓN EN LA FUENTE | F6: VALOR FACTURA antes de RTE FTE | G6: VALOR TOTAL NETO DE LA FACTURA | H6: VALOR CUENTA DE COBRO | I6: VALOR NETO TOTAL FRAS + C DE C | J6: OBSERVACIONES | L6: SEGURIDAD SOCIAL | M6: Ingreso Base RetFte | N6: AGENTE RETENEDOR | O6: RETENCIÓN EN LA FUENTE | P6: Vr Ingreso Base RetFte EN UVT
L7: =12.5%+16% -> 0.285
A8: FAMILIA RESTREPO POSADA
B10: Luís Emilio
A11: 1 | B11: ÁLVAREZ LONDOÑO OLGA STELLA | C11: =SUMIF('Consolidado Cobros'!$B$10:$B$314,B11,'Consolidado Cobros'!$F$10:$F$314) -> 0 | D11: =SUMIF('Consolidado Cobros'!$B$10:$B$314,B11,'Consolidado Cobros'!$G$10:$G$314) -> 0 | E11: =SUMIF('Consolidado Cobros'!$B$10:$B$314,B11,'Consolidado Cobros'!$H$10:$H$314) -> 0 | F11: =SUMIF('Consolidado Cobros'!$B$10:$B$314,B11,'Consolidado Cobros'!$I$10:$I$314) -> 0 | G11: =SUMIF('Consolidado Cobros'!$B$10:$B$314,B11,'Consolidado Cobros'!$J$10:$J$314) -> 0 | H11: =SUMIF('Consolidado Cobros'!$B$10:$B$314,B11,'Consolidado Cobros'!$L$10:$L$314) -> 1010000 | I11: =+G11+H11 -> 1010000
A12: SUB TOTAL | C12: =SUM(C9:C11) -> 0 | D12: =SUM(D9:D11) -> 0 | E12: =IF(O12="NO RETENCIÓN",0,-O12) -> 0 | F12: =SUM(F9:F11) -> 0 | G12: =SUM(G9:G11) -> 0 | H12: =SUM(H9:H11) -> 1010000 | I12: =SUM(I9:I11) -> 1010000 | L12: =+C12*$L$7 -> 0 | M12: =+C12-L12*0 -> 0 | N12: N | O12: =IF(N12="S",M12*$O$5,"NO RETENCIÓN") -> NO RETENCIÓN | P12: =+M12/$P$5 -> 0
B14: INVERSIONES LUÍS EMILIO RESTREPO ÁLVAREZ LIMITADA | J14: Luís Emilio
A15: 1 | B15: RESTREPO ÁLVAREZ LUÍS EMILIO | C15: =SUMIF('Consolidado Cobros'!$B$10:$B$314,B15,'Consolidado Cobros'!$F$10:$F$314) -> 800000 | D15: =SUMIF('Consolidado Cobros'!$B$10:$B$314,B15,'Consolidado Cobros'!$G$10:$G$314) -> 152000 | E15: =SUMIF('Consolidado Cobros'!$B$10:$B$314,B15,'Consolidado Cobros'!$H$10:$H$314) -> -88000 | F15: =SUMIF('Consolidado Cobros'!$B$10:$B$314,B15,'Consolidado Cobros'!$I$10:$I$314) -> 952000 | G15: =SUMIF('Consolidado Cobros'!$B$10:$B$314,B15,'Consolidado Cobros'!$J$10:$J$314) -> 864000 | H15: =SUMIF('Consolidado Cobros'!$B$10:$B$314,B15,'Consolidado Cobros'!$L$10:$L$314) -> 0 | I15: =+G15+H15 -> 864000 | J15: GTFF-172
A16: =A15+1 -> 2 | B16: INVERSIONES LUÍS EMILIO RESTREPO ÁLVAREZ LIMITADA | C16: =SUMIF('Consolidado Cobros'!$B$10:$B$314,B16,'Consolidado Cobros'!$F$10:$F$314) -> 3876000 | D16: =SUMIF('Consolidado Cobros'!$B$10:$B$314,B16,'Consolidado Cobros'!$G$10:$G$314) -> 736440 | E16: =SUMIF('Consolidado Cobros'!$B$10:$B$314,B16,'Consolidado Cobros'!$H$10:$H$314) -> -426360 | F16: =SUMIF('Consolidado Cobros'!$B$10:$B$314,B16,'Consolidado Cobros'!$I$10:$I$314) -> 4612440 | G16: =SUMIF('Consolidado Cobros'!$B$10:$B$314,B16,'Consolidado Cobros'!$J$10:$J$314) -> 4186080 | H16: =SUMIF('Consolidado Cobros'!$B$10:$B$314,B16,'Consolidado Cobros'!$L$10:$L$314) -> 0 | I16: =+G16+H16 -> 4186080 | J16: GTFF-172
A17: SUB TOTAL | B17: INVERSIONES LUÍS EMILIO RESTREPO ÁLVAREZ LIMITADA | C17: =SUM(C14:C16) -> 4676000 | D17: =SUM(D14:D16) -> 888440 | E17: =SUM(E15:E16) -> -514360 | F17: =SUM(F14:F16) -> 5564440 | G17: =SUM(G14:G16) -> 5050080 | H17: =SUM(H14:H16) -> 0 | I17: =SUM(I14:I16) -> 5050080 | L17: =+C17*$L$7 -> 1332660 | M17: =+C17-L17*0 -> 4676000 | N17: S | O17: =IF(N17="S",M17*$O$5,"NO RETENCIÓN") -> 514360 | P17: =+M17/$P$5 -> 93.897468
B19: Doña Silvia | V19: -0.06302521
B20: RESTREPO POSADA SILVIA ELENA | J20: Doña Silvia
A21: 1 | B21: RESTREPO POSADA SILVIA ELENA | C21: =SUMIF('Consolidado Cobros'!$B$10:$B$314,B21,'Consolidado Cobros'!$F$10:$F$314) -> 2530000 | D21: =SUMIF('Consolidado Cobros'!$B$10:$B$314,B21,'Consolidado Cobros'!$G$10:$G$314) -> 480700 | E21: =SUMIF('Consolidado Cobros'!$B$10:$B$314,B21,'Consolidado Cobros'!$H$10:$H$314) -> 0 | F21: =SUMIF('Consolidado Cobros'!$B$10:$B$314,B21,'Consolidado Cobros'!$I$10:$I$314) -> 3010700 | G21: =SUMIF('Consolidado Cobros'!$B$10:$B$314,B21,'Consolidado Cobros'!$J$10:$J$314) -> 3010700 | H21: =SUMIF('Consolidado Cobros'!$B$10:$B$314,B21,'Consolidado Cobros'!$L$10:$L$314) -> 0 | I21: =+G21+H21 -> 3010700 | J21: GTFF-171 | Q21: =+'Facturas año anterior'!F25 -> 2380000 | R21: =+Q21*5.2% -> 123760 | S21: =+Q21+R21 -> 2503760 | T21: =+C21 -> 2530000 | U21: =+Q21-T21 -> -150000 | V21: =+U21/Q21 -> -0.06302521
A22: SUB TOTAL | C22: =SUM(C18:C21) -> 2530000 | D22: =SUM(D18:D21) -> 480700 | E22: =SUM(E21) -> 0 | F22: =SUM(F18:F21) -> 3010700 | G22: =SUM(G18:G21) -> 3010700 | H22: =SUM(H18:H21) -> 0 | I22: =SUM(I18:I21) -> 3010700 | L22: =+C22*$L$7 -> 721050 | M22: =+C22-L22*0 -> 2530000 | N22: N | O22: =IF(N22="S",M22*$O$5,"NO RETENCIÓN") -> NO RETENCIÓN | P22: =+M22/$P$5 -> 50.804233
B24: BETANCUR RESTREPO SARA LUISA
A25: =A21+1 -> 2 | B25: BETANCUR RESTREPO SARA LUISA | C25: =SUMIF('Consolidado Cobros'!$B$10:$B$314,B25,'Consolidado Cobros'!$F$10:$F$314) -> 1950000 | D25: =SUMIF('Consolidado Cobros'!$B$10:$B$314,B25,'Consolidado Cobros'!$G$10:$G$314) -> 370500 | E25: =SUMIF('Consolidado Cobros'!$B$10:$B$314,B25,'Consolidado Cobros'!$H$10:$H$314) -> 0 | F25: =SUMIF('Consolidado Cobros'!$B$10:$B$314,B25,'Consolidado Cobros'!$I$10:$I$314) -> 2320500 | G25: =SUMIF('Consolidado Cobros'!$B$10:$B$314,B25,'Consolidado Cobros'!$J$10:$J$314) -> 2320500 | H25: =SUMIF('Consolidado Cobros'!$B$10:$B$314,B25,'Consolidado Cobros'!$L$10:$L$314) -> 0 | I25: =+G25+H25 -> 2320500 | J25: GTFF-168 | Q25: =+'Facturas año anterior'!F10 -> 1830000 | R25: =+Q25*5.2% -> 95160 | S25: =+Q25+R25 -> 1925160 | T25: =+C25 -> 1950000 | U25: =+Q25-T25 -> -120000 | V25: =+U25/Q25 -> -0.06557377
A26: SUB TOTAL | C26: =SUM(C23:C25) -> 1950000 | D26: =SUM(D23:D25) -> 370500 | E26: =SUM(E25) -> 0 | F26: =SUM(F23:F25) -> 2320500 | G26: =SUM(G23:G25) -> 2320500 | H26: =SUM(H23:H25) -> 0 | I26: =SUM(I23:I25) -> 2320500 | L26: =+C26*$L$7 -> 555750 | M26: =+C26-L26*0 -> 1950000 | N26: N | O26: =IF(N26="S",M26*$O$5,"NO RETENCIÓN") -> NO RETENCIÓN | P26: =+M26/$P$5 -> 39.157413
B28: SOCIEDAD BETANCUR RESTREPO SAS
A29: =A25+1 -> 3 | B29: RESTREPO POSADA Y CÍA S EN C EN LIQUIDACIÓN | C29: =SUMIF('Consolidado Cobros'!$B$10:$B$314,B29,'Consolidado Cobros'!$F$10:$F$314) -> 3391000 | D29: =SUMIF('Consolidado Cobros'!$B$10:$B$314,B29,'Consolidado Cobros'!$G$10:$G$314) -> 644290 | E29: =SUMIF('Consolidado Cobros'!$B$10:$B$314,B29,'Consolidado Cobros'!$H$10:$H$314) -> -373010 | F29: =SUMIF('Consolidado Cobros'!$B$10:$B$314,B29,'Consolidado Cobros'!$I$10:$I$314) -> 4035290 | G29: =SUMIF('Consolidado Cobros'!$B$10:$B$314,B29,'Consolidado Cobros'!$J$10:$J$314) -> 3662280 | H29: =SUMIF('Consolidado Cobros'!$B$10:$B$314,B29,'Consolidado Cobros'!$L$10:$L$314) -> 0 | I29: =+G29+H29 -> 3662280 | J29: GTFF-173
A30: =A29+1 -> 4 | B30: SOCIEDAD BETANCUR RESTREPO S A S | C30: =SUMIF('Consolidado Cobros'!$B$10:$B$314,B30,'Consolidado Cobros'!$F$10:$F$314) -> 3873000 | D30: =SUMIF('Consolidado Cobros'!$B$10:$B$314,B30,'Consolidado Cobros'!$G$10:$G$314) -> 735870 | E30: =SUMIF('Consolidado Cobros'!$B$10:$B$314,B30,'Consolidado Cobros'!$H$10:$H$314) -> -426030 | F30: =SUMIF('Consolidado Cobros'!$B$10:$B$314,B30,'Consolidado Cobros'!$I$10:$I$314) -> 4608870 | G30: =SUMIF('Consolidado Cobros'!$B$10:$B$314,B30,'Consolidado Cobros'!$J$10:$J$314) -> 4182840 | H30: =SUMIF('Consolidado Cobros'!$B$10:$B$314,B30,'Consolidado Cobros'!$L$10:$L$314) -> 0 | I30: =+G30+H30 -> 4182840 | J30: GTFF-173
A31: SUB TOTAL | B31: SOCIEDAD BETANCUR RESTREPO SAS | C31: =SUM(C28:C30) -> 7264000 | D31: =SUM(D28:D30) -> 1380160 | E31: =SUM(E29:E30) -> -799040 | F31: =SUM(F28:F30) -> 8644160 | G31: =SUM(G28:G30) -> 7845120 | H31: =SUM(H28:H30) -> 0 | I31: =SUM(I28:I30) -> 7845120 | L31: =+C31*$L$7 -> 2070240 | M31: =+C31-L31*0 -> 7264000 | N31: S | O31: =IF(N31="S",M31*$O$5,"NO RETENCIÓN") -> 799040 | P31: =+M31/$P$5 -> 145.86638
A33: TOTAL DOÑA SILVIA ELENA | C33: =+C22+C26+C31 -> 11744000 | D33: =+D22+D26+D31 -> 2231360 | E33: =+E22+E26+E31 -> -799040 | F33: =+F22+F26+F31 -> 13975360 | G33: =+G22+G26+G31 -> 13176320 | H33: =+H22+H26+H31 -> 0 | I33: =+I22+I26+I31 -> 13176320
B36: INVERSIONES CIRPUL SAS | J36: Doña Clara
A37: 1 | B37: RESTREPO POSADA CLARA INÉS | C37: =SUMIF('Consolidado Cobros'!$B$10:$B$314,B37,'Consolidado Cobros'!$F$10:$F$314) -> 1830000 | D37: =SUMIF('Consolidado Cobros'!$B$10:$B$314,B37,'Consolidado Cobros'!$G$10:$G$314) -> 347700 | E37: =SUMIF('Consolidado Cobros'!$B$10:$B$314,B37,'Consolidado Cobros'!$H$10:$H$314) -> -201300 | F37: =SUMIF('Consolidado Cobros'!$B$10:$B$314,B37,'Consolidado Cobros'!$I$10:$I$314) -> 2177700 | G37: =SUMIF('Consolidado Cobros'!$B$10:$B$314,B37,'Consolidado Cobros'!$J$10:$J$314) -> 1976400 | H37: =SUMIF('Consolidado Cobros'!$B$10:$B$314,B37,'Consolidado Cobros'!$L$10:$L$314) -> 0 | I37: =+G37+H37 -> 1976400 | J37: GTFF-174
A38: =A37+1 -> 2 | B38: INVERSIONES CIRPUL S A S | C38: =SUMIF('Consolidado Cobros'!$B$10:$B$314,B38,'Consolidado Cobros'!$F$10:$F$314) -> 3876000 | D38: =SUMIF('Consolidado Cobros'!$B$10:$B$314,B38,'Consolidado Cobros'!$G$10:$G$314) -> 736440 | E38: =SUMIF('Consolidado Cobros'!$B$10:$B$314,B38,'Consolidado Cobros'!$H$10:$H$314) -> -426360 | F38: =SUMIF('Consolidado Cobros'!$B$10:$B$314,B38,'Consolidado Cobros'!$I$10:$I$314) -> 4612440 | G38: =SUMIF('Consolidado Cobros'!$B$10:$B$314,B38,'Consolidado Cobros'!$J$10:$J$314) -> 4186080 | H38: =SUMIF('Consolidado Cobros'!$B$10:$B$314,B38,'Consolidado Cobros'!$L$10:$L$314) -> 0 | I38: =+G38+H38 -> 4186080 | J38: GTFF-174
A39: SUB TOTAL | C39: =SUM(C37:C38) -> 5706000 | D39: =SUM(D37:D38) -> 1084140 | E39: =SUM(E37:E38) -> -627660 | F39: =SUM(F37:F38) -> 6790140 | G39: =SUM(G37:G38) -> 6162480 | H39: =SUM(H37:H38) -> 0 | I39: =SUM(I37:I38) -> 6162480 | L39: =+C39*$L$7 -> 1626210 | M39: =+C39-L39*0 -> 5706000 | N39: S | O39: =IF(N39="S",M39*$O$5,"NO RETENCIÓN") -> 627660 | P39: =+M39/$P$5 -> 114.58061
B41: Doña María Isabel
A42: 1 | B42: RESTREPO DE SÁNCHEZ MARÍA ISABEL | C42: =SUMIF('Consolidado Cobros'!$B$10:$B$314,B42,'Consolidado Cobros'!$F$10:$F$314) -> 1790000 | D42: =SUMIF('Consolidado Cobros'!$B$10:$B$314,B42,'Consolidado Cobros'!$G$10:$G$314) -> 340100 | E42: =SUMIF('Consolidado Cobros'!$B$10:$B$314,B42,'Consolidado Cobros'!$H$10:$H$314) -> 0 | F42: =SUMIF('Consolidado Cobros'!$B$10:$B$314,B42,'Consolidado Cobros'!$I$10:$I$314) -> 2130100 | G42: =SUMIF('Consolidado Cobros'!$B$10:$B$314,B42,'Consolidado Cobros'!$J$10:$J$314) -> 2130100 | H42: =SUMIF('Consolidado Cobros'!$B$10:$B$314,B42,'Consolidado Cobros'!$L$10:$L$314) -> 0 | I42: =+G42+H42 -> 2130100 | J42: GTFF-169 | L42: =+'Facturas año anterior'!F19 -> 1710000
A43: =A42+1 -> 2 | B43: SÁNCHEZ RESTREPO JUAN DAVID | C43: =SUMIF('Consolidado Cobros'!$B$10:$B$314,B43,'Consolidado Cobros'!$F$10:$F$314) -> 800000 | D43: =SUMIF('Consolidado Cobros'!$B$10:$B$314,B43,'Consolidado Cobros'!$G$10:$G$314) -> 152000 | E43: =SUMIF('Consolidado Cobros'!$B$10:$B$314,B43,'Consolidado Cobros'!$H$10:$H$314) -> 0 | F43: =SUMIF('Consolidado Cobros'!$B$10:$B$314,B43,'Consolidado Cobros'!$I$10:$I$314) -> 952000 | G43: =SUMIF('Consolidado Cobros'!$B$10:$B$314,B43,'Consolidado Cobros'!$J$10:$J$314) -> 952000 | H43: =SUMIF('Consolidado Cobros'!$B$10:$B$314,B43,'Consolidado Cobros'!$L$10:$L$314) -> 0 | I43: =+G43+H43 -> 952000 | J43: GTFF-169 | L43: =+'Facturas año anterior'!F30 -> 760000
A44: =+A43+1 -> 3 | B44: SÁNCHEZ RUBIO JOSÉ MARDOQUEO | C44: =SUMIF('Consolidado Cobros'!$B$10:$B$314,B44,'Consolidado Cobros'!$F$10:$F$314) -> 0 | D44: =SUMIF('Consolidado Cobros'!$B$10:$B$314,B44,'Consolidado Cobros'!$G$10:$G$314) -> 0 | E44: =SUMIF('Consolidado Cobros'!$B$10:$B$314,B44,'Consolidado Cobros'!$H$10:$H$314) -> 0 | F44: =SUMIF('Consolidado Cobros'!$B$10:$B$314,B44,'Consolidado Cobros'!$I$10:$I$314) -> 0 | G44: =SUMIF('Consolidado Cobros'!$B$10:$B$314,B44,'Consolidado Cobros'!$J$10:$J$314) -> 0 | H44: =SUMIF('Consolidado Cobros'!$B$10:$B$314,B44,'Consolidado Cobros'!$L$10:$L$314) -> 0 | I44: =+G44+H44 -> 0
A45: SUB TOTAL | C45: =SUM(C42:C44) -> 2590000 | D45: =SUM(D42:D44) -> 492100 | E45: =SUM(E42:E44) -> 0 | F45: =SUM(F42:F44) -> 3082100 | G45: =SUM(G42:G44) -> 3082100 | H45: =SUM(H42:H44) -> 0 | I45: =SUM(I42:I44) -> 3082100 | L45: =+C45*$L$7 -> 738150 | M45: =+C45-L45*0 -> 2590000 | N45: N | O45: =IF(N45="S",M45*$O$5,"NO RETENCIÓN") -> NO RETENCIÓN | P45: =+M45/$P$5 -> 52.009076
A48: =+A44+1 -> 4 | B48: SÁNCHEZ RESTREPO MARGARITA ROSA | C48: =SUMIF('Consolidado Cobros'!$B$10:$B$314,B48,'Consolidado Cobros'!$F$10:$F$314) -> 1000000 | D48: =SUMIF('Consolidado Cobros'!$B$10:$B$314,B48,'Consolidado Cobros'!$G$10:$G$314) -> 190000 | E48: =SUMIF('Consolidado Cobros'!$B$10:$B$314,B48,'Consolidado Cobros'!$H$10:$H$314) -> 0 | F48: =SUMIF('Consolidado Cobros'!$B$10:$B$314,B48,'Consolidado Cobros'!$I$10:$I$314) -> 1190000 | G48: =SUMIF('Consolidado Cobros'!$B$10:$B$314,B48,'Consolidado Cobros'!$J$10:$J$314) -> 1190000 | H48: =SUMIF('Consolidado Cobros'!$B$10:$B$314,B48,'Consolidado Cobros'!$L$10:$L$314) -> 0 | I48: =+G48+H48 -> 1190000 | J48: GTFF-170
A49: SUB TOTAL | C49: =SUM(C46:C48) -> 1000000 | D49: =SUM(D46:D48) -> 190000 | E49: =SUM(E48) -> 0 | F49: =SUM(F46:F48) -> 1190000 | G49: =SUM(G46:G48) -> 1190000 | H49: =SUM(H46:H48) -> 0 | I49: =SUM(I46:I48) -> 1190000 | L49: =+C49*$L$7 -> 285000 | M49: =+C49-L49*0 -> 1000000 | N49: N | O49: =IF(N49="S",M49*$O$5,"NO RETENCIÓN") -> NO RETENCIÓN | P49: =+M49/$P$5 -> 20.080725
B52: Don Juan José
A53: 1 | B53: RESTREPO POSADA JUAN JOSÉ | C53: =SUMIF('Consolidado Cobros'!$B$10:$B$314,B53,'Consolidado Cobros'!$F$10:$F$314) -> 1410000 | D53: =SUMIF('Consolidado Cobros'!$B$10:$B$314,B53,'Consolidado Cobros'!$G$10:$G$314) -> 267900 | E53: =SUMIF('Consolidado Cobros'!$B$10:$B$314,B53,'Consolidado Cobros'!$H$10:$H$314) -> -155100 | F53: =SUMIF('Consolidado Cobros'!$B$10:$B$314,B53,'Consolidado Cobros'!$I$10:$I$314) -> 1677900 | G53: =SUMIF('Consolidado Cobros'!$B$10:$B$314,B53,'Consolidado Cobros'!$J$10:$J$314) -> 1522800 | H53: =SUMIF('Consolidado Cobros'!$B$10:$B$314,B53,'Consolidado Cobros'!$L$10:$L$314) -> 0 | I53: =+G53+H53 -> 1522800 | J53: GTFF-166
A54: =+A53+1 -> 2 | B54: RESTREPO MEJÍA MARÍA LUISA | C54: =SUMIF('Consolidado Cobros'!$B$10:$B$314,B54,'Consolidado Cobros'!$F$10:$F$314) -> 610000 | D54: =SUMIF('Consolidado Cobros'!$B$10:$B$314,B54,'Consolidado Cobros'!$G$10:$G$314) -> 115900 | E54: =SUMIF('Consolidado Cobros'!$B$10:$B$314,B54,'Consolidado Cobros'!$H$10:$H$314) -> -67100 | F54: =SUMIF('Consolidado Cobros'!$B$10:$B$314,B54,'Consolidado Cobros'!$I$10:$I$314) -> 725900 | G54: =SUMIF('Consolidado Cobros'!$B$10:$B$314,B54,'Consolidado Cobros'!$J$10:$J$314) -> 658800 | H54: =SUMIF('Consolidado Cobros'!$B$10:$B$314,B54,'Consolidado Cobros'!$L$10:$L$314) -> 0 | I54: =+G54+H54 -> 658800 | J54: GTFF-166
A55: =A54+1 -> 3 | B55: RESTREPO MEJÍA SEBASTIAN | C55: =SUMIF('Consolidado Cobros'!$B$10:$B$314,B55,'Consolidado Cobros'!$F$10:$F$314) -> 1280000 | D55: =SUMIF('Consolidado Cobros'!$B$10:$B$314,B55,'Consolidado Cobros'!$G$10:$G$314) -> 243200 | E55: =SUMIF('Consolidado Cobros'!$B$10:$B$314,B55,'Consolidado Cobros'!$H$10:$H$314) -> -140800 | F55: =SUMIF('Consolidado Cobros'!$B$10:$B$314,B55,'Consolidado Cobros'!$I$10:$I$314) -> 1523200 | G55: =SUMIF('Consolidado Cobros'!$B$10:$B$314,B55,'Consolidado Cobros'!$J$10:$J$314) -> 1382400 | H55: =SUMIF('Consolidado Cobros'!$B$10:$B$314,B55,'Consolidado Cobros'!$L$10:$L$314) -> 0 | I55: =+G55+H55 -> 1382400 | J55: GTFF-166
A56: =+A55+1 -> 4 | B56: CORTIJO DE RESTREPO S A S | C56: =SUMIF('Consolidado Cobros'!$B$10:$B$314,B56,'Consolidado Cobros'!$F$10:$F$314) -> 5146000 | D56: =SUMIF('Consolidado Cobros'!$B$10:$B$314,B56,'Consolidado Cobros'!$G$10:$G$314) -> 977740 | E56: =SUMIF('Consolidado Cobros'!$B$10:$B$314,B56,'Consolidado Cobros'!$H$10:$H$314) -> -566060 | F56: =SUMIF('Consolidado Cobros'!$B$10:$B$314,B56,'Consolidado Cobros'!$I$10:$I$314) -> 6123740 | G56: =SUMIF('Consolidado Cobros'!$B$10:$B$314,B56,'Consolidado Cobros'!$J$10:$J$314) -> 5557680 | H56: =SUMIF('Consolidado Cobros'!$B$10:$B$314,B56,'Consolidado Cobros'!$L$10:$L$314) -> 0 | I56: =+G56+H56 -> 5557680 | J56: GTFF-166
A57: SUB TOTAL | B57: CORTIJO DE RESTREPO S A S | C57: =SUM(C53:C56) -> 8446000 | D57: =SUM(D53:D56) -> 1604740 | E57: =SUM(E53:E56) -> -929060 | F57: =SUM(F53:F56) -> 10050740 | G57: =SUM(G53:G56) -> 9121680 | H57: =SUM(H53:H56) -> 0 | I57: =SUM(I53:I56) -> 9121680 | L57: =+C57*$L$7 -> 2407110 | M57: =+C57-L57*0 -> 8446000 | N57: S | O57: =IF(N57="S",M57*$O$5,"NO RETENCIÓN") -> 929060 | P57: =+M57/$P$5 -> 169.6018
B59: SAN ANTONIO DE LA ALMERÍA SAS | J59: Don Emilio
A60: =A58+1 -> 1 | B60: RESTREPO POSADA EMILIO ANTONIO | C60: =SUMIF('Consolidado Cobros'!$B$10:$B$314,B60,'Consolidado Cobros'!$F$10:$F$314) -> 2430000 | D60: =SUMIF('Consolidado Cobros'!$B$10:$B$314,B60,'Consolidado Cobros'!$G$10:$G$314) -> 461700 | E60: =SUMIF('Consolidado Cobros'!$B$10:$B$314,B60,'Consolidado Cobros'!$H$10:$H$314) -> -267300 | F60: =SUMIF('Consolidado Cobros'!$B$10:$B$314,B60,'Consolidado Cobros'!$I$10:$I$314) -> 2891700 | G60: =SUMIF('Consolidado Cobros'!$B$10:$B$314,B60,'Consolidado Cobros'!$J$10:$J$314) -> 2624400 | H60: =SUMIF('Consolidado Cobros'!$B$10:$B$314,B60,'Consolidado Cobros'!$L$10:$L$314) -> 0 | I60: =+G60+H60 -> 2624400 | J60: GTFF-175 | Q60: CADAVID GALLEGO JULIA CRISTINA | R60: 580000 | S60: =+SUMIF($B$60:$B$64,Q60,$C$60:$C$64) -> 610000 | T60: =+R60-S60 -> -30000
A61: =+A60+1 -> 2 | B61: GALLEGO ARIAS GLORIA CRISTINA | C61: =SUMIF('Consolidado Cobros'!$B$10:$B$314,B61,'Consolidado Cobros'!$F$10:$F$314) -> 610000 | D61: =SUMIF('Consolidado Cobros'!$B$10:$B$314,B61,'Consolidado Cobros'!$G$10:$G$314) -> 115900 | E61: =SUMIF('Consolidado Cobros'!$B$10:$B$314,B61,'Consolidado Cobros'!$H$10:$H$314) -> -67100 | F61: =SUMIF('Consolidado Cobros'!$B$10:$B$314,B61,'Consolidado Cobros'!$I$10:$I$314) -> 725900 | G61: =SUMIF('Consolidado Cobros'!$B$10:$B$314,B61,'Consolidado Cobros'!$J$10:$J$314) -> 658800 | H61: =SUMIF('Consolidado Cobros'!$B$10:$B$314,B61,'Consolidado Cobros'!$L$10:$L$314) -> 0 | I61: =+G61+H61 -> 658800 | J61: GTFF-175 | Q61: GALLEGO ARIAS GLORIA CRISTINA | R61: 580000 | S61: =+SUMIF($B$60:$B$64,Q61,$C$60:$C$64) -> 610000 | T61: =+R61-S61 -> -30000
A62: =+A61+1 -> 3 | B62: GALLEGO ARIAS MIRIAM DEL SOCORRO | C62: =SUMIF('Consolidado Cobros'!$B$10:$B$314,B62,'Consolidado Cobros'!$F$10:$F$314) -> 1410000 | D62: =SUMIF('Consolidado Cobros'!$B$10:$B$314,B62,'Consolidado Cobros'!$G$10:$G$314) -> 267900 | E62: =SUMIF('Consolidado Cobros'!$B$10:$B$314,B62,'Consolidado Cobros'!$H$10:$H$314) -> -155100 | F62: =SUMIF('Consolidado Cobros'!$B$10:$B$314,B62,'Consolidado Cobros'!$I$10:$I$314) -> 1677900 | G62: =SUMIF('Consolidado Cobros'!$B$10:$B$314,B62,'Consolidado Cobros'!$J$10:$J$314) -> 1522800 | H62: =SUMIF('Consolidado Cobros'!$B$10:$B$314,B62,'Consolidado Cobros'!$L$10:$L$314) -> 0 | I62: =+G62+H62 -> 1522800 | J62: GTFF-175 | Q62: GALLEGO ARIAS MIRIAM DEL SOCORRO | R62: 1340000 | S62: =+SUMIF($B$60:$B$64,Q62,$C$60:$C$64) -> 1410000 | T62: =+R62-S62 -> -70000
A63: =A62+1 -> 4 | B63: CADAVID GALLEGO JULIA CRISTINA | C63: =SUMIF('Consolidado Cobros'!$B$10:$B$314,B63,'Consolidado Cobros'!$F$10:$F$314) -> 610000 | D63: =SUMIF('Consolidado Cobros'!$B$10:$B$314,B63,'Consolidado Cobros'!$G$10:$G$314) -> 115900 | E63: =SUMIF('Consolidado Cobros'!$B$10:$B$314,B63,'Consolidado Cobros'!$H$10:$H$314) -> -67100 | F63: =SUMIF('Consolidado Cobros'!$B$10:$B$314,B63,'Consolidado Cobros'!$I$10:$I$314) -> 725900 | G63: =SUMIF('Consolidado Cobros'!$B$10:$B$314,B63,'Consolidado Cobros'!$J$10:$J$314) -> 658800 | H63: =SUMIF('Consolidado Cobros'!$B$10:$B$314,B63,'Consolidado Cobros'!$L$10:$L$314) -> 0 | I63: =+G63+H63 -> 658800 | J63: GTFF-175 | Q63: RESTREPO POSADA EMILIO ANTONIO | R63: 2240000 | S63: =+SUMIF($B$60:$B$64,Q63,$C$60:$C$64) -> 2430000 | T63: =+R63-S63 -> -190000
A64: =A63+1 -> 5 | B64: SAN ANTONIO DE LA ALMERÍA S A S | C64: =SUMIF('Consolidado Cobros'!$B$10:$B$314,B64,'Consolidado Cobros'!$F$10:$F$314) -> 3873000 | D64: =SUMIF('Consolidado Cobros'!$B$10:$B$314,B64,'Consolidado Cobros'!$G$10:$G$314) -> 735870 | E64: =SUMIF('Consolidado Cobros'!$B$10:$B$314,B64,'Consolidado Cobros'!$H$10:$H$314) -> -426030 | F64: =SUMIF('Consolidado Cobros'!$B$10:$B$314,B64,'Consolidado Cobros'!$I$10:$I$314) -> 4608870 | G64: =SUMIF('Consolidado Cobros'!$B$10:$B$314,B64,'Consolidado Cobros'!$J$10:$J$314) -> 4182840 | H64: =SUMIF('Consolidado Cobros'!$B$10:$B$314,B64,'Consolidado Cobros'!$L$10:$L$314) -> 0 | I64: =+G64+H64 -> 4182840 | J64: GTFF-175 | Q64: SAN ANTONIO DE LA ALMERÍA S A S | R64: 3690000 | S64: =+SUMIF($B$60:$B$64,Q64,$C$60:$C$64) -> 3873000 | T64: =+R64-S64 -> -183000
A65: SUB TOTAL | B65: SAN ANTONIO DE LA ALMERÍA SAS | C65: =SUM(C59:C64) -> 8933000 | D65: =SUM(D59:D64) -> 1697270 | E65: =SUM(E60:E64) -> -982630 | F65: =SUM(F60:F64) -> 10630270 | G65: =SUM(G59:G64) -> 9647640 | H65: =SUM(H59:H64) -> 0 | I65: =SUM(I59:I64) -> 9647640 | L65: =+C65*$L$7 -> 2545905 | M65: =+C65-L65*0 -> 8933000 | N65: S | O65: =IF(N65="S",M65*$O$5,"NO RETENCIÓN") -> 982630 | P65: =+M65/$P$5 -> 179.38111 | R65: =SUM(R60:R64) -> 8430000 | S65: =SUM(S60:S64) -> 8933000 | T65: =+R65-S65 -> -503000 | U65: =+R65*5.2% -> 438360 | V65: =+T65/R65 -> -0.059667853
B68: INVERSIONES DON EME S A S | I68: Doña MIRIAM y Don EMILIO
A69: =+A64+1 -> 6 | B69: INVERSIONES DON EME S A S | C69: =SUMIF('Consolidado Cobros'!$B$10:$B$314,B69,'Consolidado Cobros'!$F$10:$F$314) -> 0 | D69: =SUMIF('Consolidado Cobros'!$B$10:$B$314,B69,'Consolidado Cobros'!$G$10:$G$314) -> 0 | E69: =SUMIF('Consolidado Cobros'!$B$10:$B$314,B69,'Consolidado Cobros'!$H$10:$H$314) -> 0 | F69: =SUMIF('Consolidado Cobros'!$B$10:$B$314,B69,'Consolidado Cobros'!$I$10:$I$314) -> 0 | G69: =SUMIF('Consolidado Cobros'!$B$10:$B$314,B69,'Consolidado Cobros'!$J$10:$J$314) -> 0 | H69: =SUMIF('Consolidado Cobros'!$B$10:$B$314,B69,'Consolidado Cobros'!$L$10:$L$314) -> 0 | I69: =+G69+H69 -> 0
A70: SUB TOTAL | B70: INVERSIONES DON EME S A S | C70: =SUM(C69:C69) -> 0 | D70: =SUM(D69:D69) -> 0 | E70: =SUM(E69) -> 0 | F70: =SUM(F69:F69) -> 0 | G70: =SUM(G69:G69) -> 0 | H70: =SUM(H69:H69) -> 0 | I70: =SUM(I68:I69) -> 0 | L70: =+C70*$L$7 -> 0 | M70: =+C70-L70*0 -> 0 | N70: S | O70: =IF(N70="S",M70*$O$5,"NO RETENCIÓN") -> 0 | P70: =+M70/$P$5 -> 0
B72: INVERSIONES LA CONGA S A S | I72: Doña MIRIAM y Don EMILIO
A73: =+A69+1 -> 7 | B73: INVERSIONES LA CONGA S A S | C73: =SUMIF('Consolidado Cobros'!$B$10:$B$314,B73,'Consolidado Cobros'!$F$10:$F$314) -> 3007000 | D73: =SUMIF('Consolidado Cobros'!$B$10:$B$314,B73,'Consolidado Cobros'!$G$10:$G$314) -> 571330 | E73: =SUMIF('Consolidado Cobros'!$B$10:$B$314,B73,'Consolidado Cobros'!$H$10:$H$314) -> -330770 | F73: =SUMIF('Consolidado Cobros'!$B$10:$B$314,B73,'Consolidado Cobros'!$I$10:$I$314) -> 3578330 | G73: =SUMIF('Consolidado Cobros'!$B$10:$B$314,B73,'Consolidado Cobros'!$J$10:$J$314) -> 3247560 | H73: =SUMIF('Consolidado Cobros'!$B$10:$B$314,B73,'Consolidado Cobros'!$L$10:$L$314) -> 0 | I73: =+G73+H73 -> 3247560 | J73: GTFF-176 | Q73: INVERSIONES LA CONGA S A S | R73: 2820000 | S73: =+C73 -> 3007000 | T73: =+R73-S73 -> -187000 | U73: =+T73/R73 -> -0.066312057
A74: SUB TOTAL | B74: INVERSIONES LA CONGA S A S | C74: =SUM(C73:C73) -> 3007000 | D74: =SUM(D73:D73) -> 571330 | E74: =SUM(E73) -> -330770 | F74: =SUM(F73:F73) -> 3578330 | G74: =SUM(G73:G73) -> 3247560 | H74: =SUM(H73:H73) -> 0 | I74: =SUM(I72:I73) -> 3247560 | L74: =+C74*$L$7 -> 856995 | M74: =+C74-L74*0 -> 3007000 | N74: S | O74: =IF(N74="S",M74*$O$5,"NO RETENCIÓN") -> 330770 | P74: =+M74/$P$5 -> 60.382739
B76: PERSONAS JURÍDICAS
A77: 1 | B77: CAÑO PALMA S A S | C77: =SUMIF('Consolidado Cobros'!$B$10:$B$314,B77,'Consolidado Cobros'!$F$10:$F$314) -> 3004000 | D77: =SUMIF('Consolidado Cobros'!$B$10:$B$314,B77,'Consolidado Cobros'!$G$10:$G$314) -> 570760 | E77: =SUMIF('Consolidado Cobros'!$B$10:$B$314,B77,'Consolidado Cobros'!$H$10:$H$314) -> -330440 | F77: =SUMIF('Consolidado Cobros'!$B$10:$B$314,B77,'Consolidado Cobros'!$I$10:$I$314) -> 3574760 | G77: =SUMIF('Consolidado Cobros'!$B$10:$B$314,B77,'Consolidado Cobros'!$J$10:$J$314) -> 3244320 | H77: =SUMIF('Consolidado Cobros'!$B$10:$B$314,B77,'Consolidado Cobros'!$L$10:$L$314) -> 0 | I77: =+G77+H77 -> 3244320 | J77: GTFF-177 | L77: =+C77*$L$7 -> 856140 | M77: =+C77-L77*0 -> 3004000 | N77: S | O77: =IF(N77="S",M77*$O$5,"NO RETENCIÓN") -> 330440 | P77: =+M77/$P$5 -> 60.322496
A78: =A77+1 -> 2 | B78: INMOBILIARIA EL CARMELO S A S EN LIQUIDACIÓN | C78: =SUMIF('Consolidado Cobros'!$B$10:$B$314,B78,'Consolidado Cobros'!$F$10:$F$314) -> 1508000 | D78: =SUMIF('Consolidado Cobros'!$B$10:$B$314,B78,'Consolidado Cobros'!$G$10:$G$314) -> 286520 | E78: =SUMIF('Consolidado Cobros'!$B$10:$B$314,B78,'Consolidado Cobros'!$H$10:$H$314) -> -165880 | F78: =SUMIF('Consolidado Cobros'!$B$10:$B$314,B78,'Consolidado Cobros'!$I$10:$I$314) -> 1794520 | G78: =SUMIF('Consolidado Cobros'!$B$10:$B$314,B78,'Consolidado Cobros'!$J$10:$J$314) -> 1628640 | H78: =SUMIF('Consolidado Cobros'!$B$10:$B$314,B78,'Consolidado Cobros'!$L$10:$L$314) -> 0 | I78: =+G78+H78 -> 1628640 | J78: GTFF-178 | L78: =+C78*$L$7 -> 429780 | M78: =+C78-L78*0 -> 1508000 | N78: S | O78: =IF(N78="S",M78*$O$5,"NO RETENCIÓN") -> 165880 | P78: =+M78/$P$5 -> 30.281733
A79: =A78+1 -> 3 | B79: INVERSIONES BARILOCHE DE LA POSADA Y CÍA S C A EN LIQUIDACIÓN | C79: =SUMIF('Consolidado Cobros'!$B$10:$B$314,B79,'Consolidado Cobros'!$F$10:$F$314) -> 0 | D79: =SUMIF('Consolidado Cobros'!$B$10:$B$314,B79,'Consolidado Cobros'!$G$10:$G$314) -> 0 | E79: =SUMIF('Consolidado Cobros'!$B$10:$B$314,B79,'Consolidado Cobros'!$H$10:$H$314) -> 0 | F79: =SUMIF('Consolidado Cobros'!$B$10:$B$314,B79,'Consolidado Cobros'!$I$10:$I$314) -> 0 | G79: =SUMIF('Consolidado Cobros'!$B$10:$B$314,B79,'Consolidado Cobros'!$J$10:$J$314) -> 0 | H79: =SUMIF('Consolidado Cobros'!$B$10:$B$314,B79,'Consolidado Cobros'!$L$10:$L$314) -> 1850000 | I79: =+G79+H79 -> 1850000
A80: =A79+1 -> 4 | B80: INMOBILIARIA NATIVA S A S | C80: =SUMIF('Consolidado Cobros'!$B$10:$B$314,B80,'Consolidado Cobros'!$F$10:$F$314) -> 3700000 | D80: =SUMIF('Consolidado Cobros'!$B$10:$B$314,B80,'Consolidado Cobros'!$G$10:$G$314) -> 703000 | E80: =SUMIF('Consolidado Cobros'!$B$10:$B$314,B80,'Consolidado Cobros'!$H$10:$H$314) -> -407000 | F80: =SUMIF('Consolidado Cobros'!$B$10:$B$314,B80,'Consolidado Cobros'!$I$10:$I$314) -> 4403000 | G80: =SUMIF('Consolidado Cobros'!$B$10:$B$314,B80,'Consolidado Cobros'!$J$10:$J$314) -> 3996000 | H80: =SUMIF('Consolidado Cobros'!$B$10:$B$314,B80,'Consolidado Cobros'!$L$10:$L$314) -> 0 | I80: =+G80+H80 -> 3996000 | J80: GTFF-179 | L80: =+C80*$L$7 -> 1054500 | M80: =+C80-L80*0 -> 3700000 | N80: S | O80: =IF(N80="S",M80*$O$5,"NO RETENCIÓN") -> 407000 | P80: =+M80/$P$5 -> 74.298681 | R80: =+'Facturas año anterior'!F60 -> 2330000 | S80: =+C80 -> 3700000 | T80: =+R80-S80 -> -1370000 | U80: =+T80/R80 -> -0.58798283
A81: =A80+1 -> 5 | B81: INVERSIONES EL MANGLE S A S | C81: =SUMIF('Consolidado Cobros'!$B$10:$B$314,B81,'Consolidado Cobros'!$F$10:$F$314) -> 2637000 | D81: =SUMIF('Consolidado Cobros'!$B$10:$B$314,B81,'Consolidado Cobros'!$G$10:$G$314) -> 501030 | E81: =SUMIF('Consolidado Cobros'!$B$10:$B$314,B81,'Consolidado Cobros'!$H$10:$H$314) -> -290070 | F81: =SUMIF('Consolidado Cobros'!$B$10:$B$314,B81,'Consolidado Cobros'!$I$10:$I$314) -> 3138030 | G81: =SUMIF('Consolidado Cobros'!$B$10:$B$314,B81,'Consolidado Cobros'!$J$10:$J$314) -> 2847960 | H81: =SUMIF('Consolidado Cobros'!$B$10:$B$314,B81,'Consolidado Cobros'!$L$10:$L$314) -> 0 | I81: =+G81+H81 -> 2847960 | J81: GTFF-180 | L81: =+C81*$L$7 -> 751545 | M81: =+C81-L81*0 -> 2637000 | N81: S | O81: =IF(N81="S",M81*$O$5,"NO RETENCIÓN") -> 290070 | P81: =+M81/$P$5 -> 52.952871
A82: =A81+1 -> 6 | B82: INVERSIONES EL OYETO S A S | C82: =SUMIF('Consolidado Cobros'!$B$10:$B$314,B82,'Consolidado Cobros'!$F$10:$F$314) -> 3929000 | D82: =SUMIF('Consolidado Cobros'!$B$10:$B$314,B82,'Consolidado Cobros'!$G$10:$G$314) -> 746510 | E82: =SUMIF('Consolidado Cobros'!$B$10:$B$314,B82,'Consolidado Cobros'!$H$10:$H$314) -> -432190 | F82: =SUMIF('Consolidado Cobros'!$B$10:$B$314,B82,'Consolidado Cobros'!$I$10:$I$314) -> 4675510 | G82: =SUMIF('Consolidado Cobros'!$B$10:$B$314,B82,'Consolidado Cobros'!$J$10:$J$314) -> 4243320 | H82: =SUMIF('Consolidado Cobros'!$B$10:$B$314,B82,'Consolidado Cobros'!$L$10:$L$314) -> 0 | I82: =+G82+H82 -> 4243320 | J82: GTFF-181 | L82: =+C82*$L$7 -> 1119765 | M82: =+C82-L82*0 -> 3929000 | N82: S | O82: =IF(N82="S",M82*$O$5,"NO RETENCIÓN") -> 432190 | P82: =+M82/$P$5 -> 78.897167 | R82: =+'Facturas año anterior'!F65 -> 3690000 | S82: =+Facturas!F65 -> 3929000 | T82: =+R82-S82 -> -239000 | U82: =+T82/R82 -> -0.064769648
A83: SUB TOTAL PERSONAS JURÍDICAS | C83: =SUM(C77:C82) -> 14778000 | D83: =SUM(D77:D82) -> 2807820 | E83: =SUM(E77:E82) -> -1625580 | F83: =SUM(F77:F82) -> 17585820 | G83: =SUM(G77:G82) -> 15960240 | H83: =SUM(H77:H82) -> 1850000 | I83: =SUM(I77:I82) -> 17810240 | L83: =+C83*$L$7 -> 4211730 | M83: =+C83-L83*0 -> 14778000 | O83: =SUM(O77:O82) -> 1625580
A86: LINABI SAS | B86: LINA MARÍA MEJÍA DUQUE | I86: MEJÍA DUQUE LINA MARÍA
A87: 1 | B87: MEJÍA DUQUE LINA MARÍA | C87: =SUMIF('Consolidado Cobros'!$B$10:$B$314,B87,'Consolidado Cobros'!$F$10:$F$314) -> 1480000 | D87: =SUMIF('Consolidado Cobros'!$B$10:$B$314,B87,'Consolidado Cobros'!$G$10:$G$314) -> 281200 | E87: =SUMIF('Consolidado Cobros'!$B$10:$B$314,B87,'Consolidado Cobros'!$H$10:$H$314) -> -162800 | F87: =SUMIF('Consolidado Cobros'!$B$10:$B$314,B87,'Consolidado Cobros'!$I$10:$I$314) -> 1761200 | G87: =SUMIF('Consolidado Cobros'!$B$10:$B$314,B87,'Consolidado Cobros'!$J$10:$J$314) -> 1598400 | H87: =SUMIF('Consolidado Cobros'!$B$10:$B$314,B87,'Consolidado Cobros'!$L$10:$L$314) -> 0 | I87: =+G87+H87 -> 1598400 | J87: GTFF-182
A88: SUB TOTAL | B88: LINABI SAS | C88: =SUM(C86:C87) -> 1480000 | D88: =SUM(D86:D87) -> 281200 | E88: =SUM(E87) -> -162800 | F88: =SUM(F86:F87) -> 1761200 | G88: =SUM(G86:G87) -> 1598400 | H88: =SUM(H86:H87) -> 0 | I88: =SUM(I86:I87) -> 1598400 | L88: =+C88*$L$7 -> 421800 | M88: =+C88-L88*0 -> 1480000 | N88: S | O88: =IF(N88="S",M88*$O$5,"NO RETENCIÓN") -> 162800 | P88: =+M88/$P$5 -> 29.719472
A91: TOTAL ACUMULADO FAMILIA RESTREPO POSADA | C91: =+C12+C17+C39+C45+C49+C57+C33+C65+C70+C74+C83+C88 -> 62360000 | D91: =+D12+D17+D39+D45+D49+D57+D33+D65+D70+D74+D83+D88 -> 11848400 | E91: =+E12+E17+E39+E45+E49+E57+E33+E65+E70+E74+E83+E88 -> -5971900 | F91: =+F12+F17+F39+F45+F49+F57+F33+F65+F70+F74+F83+F88 -> 74208400 | G91: =+G12+G17+G39+G45+G49+G57+G33+G65+G70+G74+G83+G88 -> 68236500 | H91: =+H12+H17+H39+H45+H49+H57+H33+H65+H70+H74+H83+H88 -> 2860000 | I91: =+I12+I17+I39+I45+I49+I57+I33+I65+I70+I74+I83+I88 -> 71096500 | L91: =+L12+L17+L39+L45+L49+L57+L33+L65+L70+L74+L83+L88 -> 14425560 | M91: =+M12+M17+M39+M45+M49+M57+M33+M65+M70+M74+M83+M88 -> 50616000
A95: DR. ESTEBAN ECHAVARRÍA
A96: 1 | B96: VILLEGAS DE ECHAVARRÍA MARÍA CLARA | C96: =SUMIF('Consolidado Cobros'!$B$10:$B$314,B96,'Consolidado Cobros'!$F$10:$F$314) -> 2280000 | D96: =SUMIF('Consolidado Cobros'!$B$10:$B$314,B96,'Consolidado Cobros'!$G$10:$G$314) -> 433200 | E96: =SUMIF('Consolidado Cobros'!$B$10:$B$314,B96,'Consolidado Cobros'!$H$10:$H$314) -> -250800 | F96: =+C96+D96 -> 2713200 | G96: =SUMIF('Consolidado Cobros'!$B$10:$B$314,B96,'Consolidado Cobros'!$J$10:$J$314) -> 2462400 | H96: =SUMIF('Consolidado Cobros'!$B$10:$B$314,B96,'Consolidado Cobros'!$L$10:$L$314) -> 0 | I96: =+G96+H96 -> 2462400 | J96: GTFF-183 | L96: =+'Facturas año anterior'!F34 -> 2500000 | M96: =+L96-C96 -> 220000
A97: SUB TOTAL | C97: =SUM(C95:C96) -> 2280000 | D97: =SUM(D95:D96) -> 433200 | E97: =SUM(E96) -> -250800 | F97: =SUM(F95:F96) -> 2713200 | G97: =SUM(G95:G96) -> 2462400 | H97: =SUM(H95:H96) -> 0 | I97: =SUM(I95:I96) -> 2462400
A99: FAMILIA ECHAVARRÍA
A100: 1 | B100: ECHAVARRÍA Y COMPAÑÍA LTDA EN LIQUIDACIÓN | C100: =SUMIF('Consolidado Cobros'!$B$10:$B$314,B100,'Consolidado Cobros'!$F$10:$F$314) -> 7938000 | D100: =SUMIF('Consolidado Cobros'!$B$10:$B$314,B100,'Consolidado Cobros'!$G$10:$G$314) -> 1508220 | E100: =SUMIF('Consolidado Cobros'!$B$10:$B$314,B100,'Consolidado Cobros'!$H$10:$H$314) -> -873180 | F100: =SUMIF('Consolidado Cobros'!$B$10:$B$314,B100,'Consolidado Cobros'!$I$10:$I$314) -> 9446220 | G100: =SUMIF('Consolidado Cobros'!$B$10:$B$314,B100,'Consolidado Cobros'!$J$10:$J$314) -> 8573040 | H100: =SUMIF('Consolidado Cobros'!$B$10:$B$314,B100,'Consolidado Cobros'!$L$10:$L$314) -> 0 | I100: =+G100+H100 -> 8573040 | J100: GTFF-163 | L100: =+C100*$L$7 -> 2262330 | M100: =+C100-L100*0 -> 7938000 | N100: S | O100: =IF(N100="S",M100*$O$5,"NO RETENCIÓN") -> 873180 | P100: =+M100/$P$5 -> 159.40079
A101: =A100+1 -> 2 | B101: INVERSIONES TALAVERA S A S | C101: =SUMIF('Consolidado Cobros'!$B$10:$B$314,B101,'Consolidado Cobros'!$F$10:$F$314) -> 11587000 | D101: =SUMIF('Consolidado Cobros'!$B$10:$B$314,B101,'Consolidado Cobros'!$G$10:$G$314) -> 2201530 | E101: =SUMIF('Consolidado Cobros'!$B$10:$B$314,B101,'Consolidado Cobros'!$H$10:$H$314) -> -1274570 | F101: =SUMIF('Consolidado Cobros'!$B$10:$B$314,B101,'Consolidado Cobros'!$I$10:$I$314) -> 13788530 | G101: =SUMIF('Consolidado Cobros'!$B$10:$B$314,B101,'Consolidado Cobros'!$J$10:$J$314) -> 12513960 | H101: =SUMIF('Consolidado Cobros'!$B$10:$B$314,B101,'Consolidado Cobros'!$L$10:$L$314) -> 0 | I101: =+G101+H101 -> 12513960 | J101: GTFF-165 | L101: =+C101*$L$7 -> 3302295 | M101: =+C101-L101*0 -> 11587000 | N101: S | O101: =IF(N101="S",M101*$O$5,"NO RETENCIÓN") -> 1274570 | P101: =+M101/$P$5 -> 232.67535
A102: =A101+1 -> 3 | B102: INMOBILIARIA GILINVERSIONES S A S | C102: =SUMIF('Consolidado Cobros'!$B$10:$B$314,B102,'Consolidado Cobros'!$F$10:$F$314) -> 11587000 | D102: =SUMIF('Consolidado Cobros'!$B$10:$B$314,B102,'Consolidado Cobros'!$G$10:$G$314) -> 2201530 | E102: =SUMIF('Consolidado Cobros'!$B$10:$B$314,B102,'Consolidado Cobros'!$H$10:$H$314) -> -1274570 | F102: =SUMIF('Consolidado Cobros'!$B$10:$B$314,B102,'Consolidado Cobros'!$I$10:$I$314) -> 13788530 | G102: =SUMIF('Consolidado Cobros'!$B$10:$B$314,B102,'Consolidado Cobros'!$J$10:$J$314) -> 12513960 | H102: =SUMIF('Consolidado Cobros'!$B$10:$B$314,B102,'Consolidado Cobros'!$L$10:$L$314) -> 0 | I102: =+G102+H102 -> 12513960 | J102: GTFF-164 | L102: =+C102*$L$7 -> 3302295 | M102: =+C102-L102*0 -> 11587000 | N102: S | O102: =IF(N102="S",M102*$O$5,"NO RETENCIÓN") -> 1274570 | P102: =+M102/$P$5 -> 232.67535
A103: SUB TOTAL | C103: =SUM(C99:C102) -> 31112000 | D103: =SUM(D99:D102) -> 5911280 | E103: =SUM(E100:E102) -> -3422320 | F103: =SUM(F99:F102) -> 37023280 | G103: =SUM(G99:G102) -> 33600960 | H103: =SUM(H99:H102) -> 0 | I103: =SUM(I99:I102) -> 33600960 | Q103: =SUM(O100:O102) -> 3422320
Q104: =+E105+Q103 -> -250800
A105: TOTAL ACUMULADO DR ESTEBAN | C105: =+C97+C103 -> 33392000 | D105: =+D97+D103 -> 6344480 | E105: =+E97+E103 -> -3673120 | F105: =+F97+F103 -> 39736480 | G105: =+G97+G103 -> 36063360 | H105: =+H97+H103 -> 0 | I105: =+I97+I103 -> 36063360
A109: JAVIER RÍOS
A110: 1 | B110: JAVIER RÍOS E HIJOS Y CÍA S C A | C110: =SUMIF('Consolidado Cobros'!$B$10:$B$314,B110,'Consolidado Cobros'!$F$10:$F$314) -> 0 | D110: =SUMIF('Consolidado Cobros'!$B$10:$B$314,B110,'Consolidado Cobros'!$G$10:$G$314) -> 0 | E110: =SUMIF('Consolidado Cobros'!$B$10:$B$314,B110,'Consolidado Cobros'!$H$10:$H$314) -> 0 | F110: =SUMIF('Consolidado Cobros'!$B$10:$B$314,B110,'Consolidado Cobros'!$I$10:$I$314) -> 0 | G110: =SUMIF('Consolidado Cobros'!$B$10:$B$314,B110,'Consolidado Cobros'!$J$10:$J$314) -> 0 | H110: =SUMIF('Consolidado Cobros'!$B$10:$B$314,B110,'Consolidado Cobros'!$L$10:$L$314) -> 0 | I110: =+G110+H110 -> 0
A111: =A110+1 -> 2 | B111: CORREA DE RÍOS MIRYAM DEL SOCORRO | C111: =SUMIF('Consolidado Cobros'!$B$10:$B$314,B111,'Consolidado Cobros'!$F$10:$F$314) -> 2240000 | D111: =SUMIF('Consolidado Cobros'!$B$10:$B$314,B111,'Consolidado Cobros'!$G$10:$G$314) -> 425600 | E111: =SUMIF('Consolidado Cobros'!$B$10:$B$314,B111,'Consolidado Cobros'!$H$10:$H$314) -> -246400 | F111: =SUMIF('Consolidado Cobros'!$B$10:$B$314,B111,'Consolidado Cobros'!$I$10:$I$314) -> 2665600 | G111: =SUMIF('Consolidado Cobros'!$B$10:$B$314,B111,'Consolidado Cobros'!$J$10:$J$314) -> 2419200 | H111: =SUMIF('Consolidado Cobros'!$B$10:$B$314,B111,'Consolidado Cobros'!$L$10:$L$314) -> 0 | I111: =+G111+H111 -> 2419200 | J111: DEBE PASAR A CXC
A112: =A111+1 -> 3 | B112: RÍOS FRANCISCO JAVIER | C112: =SUMIF('Consolidado Cobros'!$B$10:$B$314,B112,'Consolidado Cobros'!$F$10:$F$314) -> 990000 | D112: =SUMIF('Consolidado Cobros'!$B$10:$B$314,B112,'Consolidado Cobros'!$G$10:$G$314) -> 188100 | E112: =SUMIF('Consolidado Cobros'!$B$10:$B$314,B112,'Consolidado Cobros'!$H$10:$H$314) -> -108900 | F112: =SUMIF('Consolidado Cobros'!$B$10:$B$314,B112,'Consolidado Cobros'!$I$10:$I$314) -> 1178100 | G112: =SUMIF('Consolidado Cobros'!$B$10:$B$314,B112,'Consolidado Cobros'!$J$10:$J$314) -> 1069200 | H112: =SUMIF('Consolidado Cobros'!$B$10:$B$314,B112,'Consolidado Cobros'!$L$10:$L$314) -> 0 | I112: =+G112+H112 -> 1069200 | J112: DEBE PASAR A CXC
A113: SUB TOTAL | B113: JAVIER RÍOS E HIJOS Y CÍA SCA | C113: =SUM(C110:C112) -> 3230000 | D113: =SUM(D110:D112) -> 613700 | E113: =SUM(E110:E112) -> -355300 | F113: =SUM(F110:F112) -> 3843700 | G113: =SUM(G110:G112) -> 3488400 | H113: =SUM(H110:H112) -> 0 | I113: =SUM(I110:I112) -> 3488400 | L113: =+C113*$L$7 -> 920550 | M113: =+C113-L113*0 -> 3230000 | N113: S | O113: =IF(N113="S",M113*$O$5,"NO RETENCIÓN") -> 355300 | P113: =+M113/$P$5 -> 64.86074
B116: RÍOS CORREA JAVIER ADOLFO
A117: =A112+1 -> 4 | B117: RÍOS CORREA JAVIER ADOLFO | C117: =SUMIF('Consolidado Cobros'!$B$10:$B$314,B117,'Consolidado Cobros'!$F$10:$F$314) -> 0 | D117: =SUMIF('Consolidado Cobros'!$B$10:$B$314,B117,'Consolidado Cobros'!$G$10:$G$314) -> 0 | F117: =SUMIF('Consolidado Cobros'!$B$10:$B$314,B117,'Consolidado Cobros'!$I$10:$I$314) -> 0 | G117: =SUMIF('Consolidado Cobros'!$B$10:$B$314,B117,'Consolidado Cobros'!$J$10:$J$314) -> 0 | H117: =SUMIF('Consolidado Cobros'!$B$10:$B$314,B117,'Consolidado Cobros'!$L$10:$L$314) -> 1500000 | I117: =+G117+H117 -> 1500000
A118: SUB TOTAL | C118: =SUM(C117) -> 0 | D118: =SUM(D117) -> 0 | E118: =SUM(E117) -> 0 | F118: =SUM(F117) -> 0 | G118: =SUM(G117) -> 0 | H118: =SUM(H117) -> 1500000 | I118: =SUM(I117) -> 1500000
A120: TOTAL ACUMULADO FAMILIA RÍOS CORREA | C120: =C113+C118 -> 3230000 | D120: =D113+D118 -> 613700 | E120: =E113+E118 -> -355300 | F120: =F113+F118 -> 3843700 | G120: =G113+G118 -> 3488400 | H120: =H113+H118 -> 1500000 | I120: =I113+I118 -> 4988400
A124: CARLI FLURY
A125: 1 | B125: INDUSTRIAS DE ACEROS DEL CARIBE LTDA EN CAUSAL DE DISOLUCIÓN | C125: =SUMIF('Consolidado Cobros'!$B$10:$B$314,B125,'Consolidado Cobros'!$F$10:$F$314) -> 0 | D125: =SUMIF('Consolidado Cobros'!$B$10:$B$314,B125,'Consolidado Cobros'!$G$10:$G$314) -> 0 | E125: =SUMIF('Consolidado Cobros'!$B$10:$B$314,B125,'Consolidado Cobros'!$H$10:$H$314) -> 0 | F125: =SUMIF('Consolidado Cobros'!$B$10:$B$314,B125,'Consolidado Cobros'!$I$10:$I$314) -> 0 | G125: =SUMIF('Consolidado Cobros'!$B$10:$B$314,B125,'Consolidado Cobros'!$J$10:$J$314) -> 0 | H125: =SUMIF('Consolidado Cobros'!$B$10:$B$314,B125,'Consolidado Cobros'!$L$10:$L$314) -> 860000 | I125: =+G125+H125 -> 860000
A126: =A125+1 -> 2 | B126: FLURY VALENCIA Y CÍA S EN C | C126: =SUMIF('Consolidado Cobros'!$B$10:$B$314,B126,'Consolidado Cobros'!$F$10:$F$314) -> 0 | D126: =SUMIF('Consolidado Cobros'!$B$10:$B$314,B126,'Consolidado Cobros'!$G$10:$G$314) -> 0 | E126: =SUMIF('Consolidado Cobros'!$B$10:$B$314,B126,'Consolidado Cobros'!$H$10:$H$314) -> 0 | F126: =SUMIF('Consolidado Cobros'!$B$10:$B$314,B126,'Consolidado Cobros'!$I$10:$I$314) -> 0 | G126: =SUMIF('Consolidado Cobros'!$B$10:$B$314,B126,'Consolidado Cobros'!$J$10:$J$314) -> 0 | H126: =SUMIF('Consolidado Cobros'!$B$10:$B$314,B126,'Consolidado Cobros'!$L$10:$L$314) -> 860000 | I126: =+G126+H126 -> 860000
A127: =A126+1 -> 3 | B127: FLURY VALENCIA GERALDINE | C127: =SUMIF('Consolidado Cobros'!$B$10:$B$314,B127,'Consolidado Cobros'!$F$10:$F$314) -> 0 | D127: =SUMIF('Consolidado Cobros'!$B$10:$B$314,B127,'Consolidado Cobros'!$G$10:$G$314) -> 0 | E127: =SUMIF('Consolidado Cobros'!$B$10:$B$314,B127,'Consolidado Cobros'!$H$10:$H$314) -> 0 | F127: =SUMIF('Consolidado Cobros'!$B$10:$B$314,B127,'Consolidado Cobros'!$I$10:$I$314) -> 0 | G127: =SUMIF('Consolidado Cobros'!$B$10:$B$314,B127,'Consolidado Cobros'!$J$10:$J$314) -> 0 | H127: =SUMIF('Consolidado Cobros'!$B$10:$B$314,B127,'Consolidado Cobros'!$L$10:$L$314) -> 860000 | I127: =+G127+H127 -> 860000
A128: =A127+1 -> 4 | B128: FLURY CARLI | C128: =SUMIF('Consolidado Cobros'!$B$10:$B$314,B128,'Consolidado Cobros'!$F$10:$F$314) -> 0 | D128: =SUMIF('Consolidado Cobros'!$B$10:$B$314,B128,'Consolidado Cobros'!$G$10:$G$314) -> 0 | E128: =SUMIF('Consolidado Cobros'!$B$10:$B$314,B128,'Consolidado Cobros'!$H$10:$H$314) -> 0 | F128: =SUMIF('Consolidado Cobros'!$B$10:$B$314,B128,'Consolidado Cobros'!$I$10:$I$314) -> 0 | G128: =SUMIF('Consolidado Cobros'!$B$10:$B$314,B128,'Consolidado Cobros'!$J$10:$J$314) -> 0 | H128: =SUMIF('Consolidado Cobros'!$B$10:$B$314,B128,'Consolidado Cobros'!$L$10:$L$314) -> 1120000 | I128: =+G128+H128 -> 1120000
A129: =A128+1 -> 5 | B129: FLURY VALENCIA ERIKA | C129: =SUMIF('Consolidado Cobros'!$B$10:$B$314,B129,'Consolidado Cobros'!$F$10:$F$314) -> 0 | D129: =SUMIF('Consolidado Cobros'!$B$10:$B$314,B129,'Consolidado Cobros'!$G$10:$G$314) -> 0 | E129: =SUMIF('Consolidado Cobros'!$B$10:$B$314,B129,'Consolidado Cobros'!$H$10:$H$314) -> 0 | F129: =SUMIF('Consolidado Cobros'!$B$10:$B$314,B129,'Consolidado Cobros'!$I$10:$I$314) -> 0 | G129: =SUMIF('Consolidado Cobros'!$B$10:$B$314,B129,'Consolidado Cobros'!$J$10:$J$314) -> 0 | H129: =SUMIF('Consolidado Cobros'!$B$10:$B$314,B129,'Consolidado Cobros'!$L$10:$L$314) -> 1340000 | I129: =+G129+H129 -> 1340000
A130: =A129+1 -> 6 | B130: VALENCIA HOYOS BEATRIZ | C130: =SUMIF('Consolidado Cobros'!$B$10:$B$314,B130,'Consolidado Cobros'!$F$10:$F$314) -> 0 | D130: =SUMIF('Consolidado Cobros'!$B$10:$B$314,B130,'Consolidado Cobros'!$G$10:$G$314) -> 0 | E130: =SUMIF('Consolidado Cobros'!$B$10:$B$314,B130,'Consolidado Cobros'!$H$10:$H$314) -> 0 | F130: =SUMIF('Consolidado Cobros'!$B$10:$B$314,B130,'Consolidado Cobros'!$I$10:$I$314) -> 0 | G130: =SUMIF('Consolidado Cobros'!$B$10:$B$314,B130,'Consolidado Cobros'!$J$10:$J$314) -> 0 | H130: =SUMIF('Consolidado Cobros'!$B$10:$B$314,B130,'Consolidado Cobros'!$L$10:$L$314) -> 1600000 | I130: =+G130+H130 -> 1600000
A131: SUB TOTAL | C131: =SUM(C125:C130) -> 0 | D131: =SUM(D125:D130) -> 0 | E131: =SUM(E125:E130) -> 0 | F131: =SUM(F125:F130) -> 0 | G131: =SUM(G125:G130) -> 0 | H131: =SUM(H125:H130) -> 6640000 | I131: =SUM(I125:I130) -> 6640000
A133: =+A130+1 -> 7 | B133: FLURY VALENCIA BREETH | C133: =SUMIF('Consolidado Cobros'!$B$10:$B$314,B133,'Consolidado Cobros'!$F$10:$F$314) -> 0 | D133: =SUMIF('Consolidado Cobros'!$B$10:$B$314,B133,'Consolidado Cobros'!$G$10:$G$314) -> 0 | E133: =SUMIF('Consolidado Cobros'!$B$10:$B$314,B133,'Consolidado Cobros'!$H$10:$H$314) -> 0 | F133: =SUMIF('Consolidado Cobros'!$B$10:$B$314,B133,'Consolidado Cobros'!$I$10:$I$314) -> 0 | G133: =SUMIF('Consolidado Cobros'!$B$10:$B$314,B133,'Consolidado Cobros'!$J$10:$J$314) -> 0 | H133: =SUMIF('Consolidado Cobros'!$B$10:$B$314,B133,'Consolidado Cobros'!$L$10:$L$314) -> 1340000 | I133: =+G133+H133 -> 1340000
A134: SUB TOTAL | C134: =SUM(C133) -> 0 | D134: =SUM(D133) -> 0 | E134: =SUM(E133) -> 0 | F134: =SUM(F133) -> 0 | G134: =SUM(G133) -> 0 | H134: =SUM(H133) -> 1340000 | I134: =SUM(I133) -> 1340000
A136: TOTAL ACUMULADO FAMILIA FLURY VALENCIA | C136: =C131+C134 -> 0 | D136: =D131+D134 -> 0 | E136: =E131+E134 -> 0 | F136: =F131+F134 -> 0 | G136: =G131+G134 -> 0 | H136: =H131+H134 -> 7980000 | I136: =I131+I134 -> 7980000
A140: LUÍS H. VILLEGAS LONDOÑO
...

Sheet Facturas
A1: =+'Grupos Familiares'!$A$1 -> GERMÁN TULIO FERNÁNDEZ FERNÁNDEZ
A2: =+'Grupos Familiares'!$A$3 -> PRESUPUESTO DE COBROS | R2: Mínima Mvto | T2: Mínima 1° Vez | V2: PARA CALCULAR EL VALOR A COBRAR POR EL PRESENTE AÑO | AP2: IPC 2024 | AQ2: Mínima Mvto -año anterior- | AR2: Mínima 1° Vez -Año anterior-
A3: FACTURACIÓN ELECTRÓNICA | R3: =ROUND(AQ3*(100%+$AP$3),-4) -> 230000 | T3: =ROUND(AR3*(100%+$AP$3),-4) -> 370000 | AP3: 0.052 | AQ3: 220000 | AR3: 350000
A4: =+'Grupos Familiares'!$A$4 -> AÑO GRAVABLE 2024 | F4: VALORES A FACTURAR -PRESENTE AÑO- | V4: PRESUPUESTOS DE COBRO: | Z4: =+$A$3 -> FACTURACIÓN ELECTRÓNICA | AP4: Vr Incrementado | AQ4: =(AQ3*(100%+$AP$3)) -> 231440 | AR4: =(AR3*(100%+$AP$3)) -> 368200
A5: PERSONAS NATURALES Y PERSONAS JURÍDICAS | G5: 0.19 | I5: 0.11 | V5: IPC | W5: 0.051 | Y5: 0.5 | AA5: =75%+80%*0 -> 0.75 | AC5: 0.15 | AE5: 0.2 | AG5: 0.1 | AI5: 0.2 | AK5: 0.3
A6: No. | B6: APELLIDOS Y NOMBRES o RAZÓN SOCIAL | C6: CÓDIGO | D6: NIT No. | E6: D. V. | F6: VALOR BRUTO A ELABORAR LA FACTURA | G6: I V A | H6: AGENTE RETENEDOR | I6: RETENCIÓN EN LA FUENTE | J6: VALOR FACTURA antes de RTE FTE | K6: VALOR A PAGAR NETO DE LA FACTURA | L6: VoBo ELABORAR Fra. | M6: FACTURA No. | N6: MEDIO | O6: FECHA | P6: ESTADO | Q6: OBSERVACIONES | R6: VALOR CUENTA DE COBRO -POR PRÉSTAMOS- | S6: CUENTA DE COBRO No. | T6: OBSERVACIONES | V6: SI o NO | W6: VALOR DECLARACIÓN RENTA | X6: SI o NO | Y6: VALOR DECLARACIÓN I AL P 2023 | Z6: SI o NO | AA6: VALOR MEDIOS MAGNÉTICOS | AB6: SI o NO | AC6: EXÓGENA MPIO MEDELLÍN | AD6: SI o NO | AE6: REG ÚNICO de BENEFICIARIOS | AF6: SI o NO | AG6: VALOR FORMATO 2516 CONSERVAR | AH6: SI o NO | AI6: VALOR FORMATO 2516 TRANSMITIR | AJ6: SI o NO | AK6: VALOR DECLARACIÓN ACTIVOS EN EL EXTERIOR | AL6: VALOR OTRAS ASESORÍAS | AM6: PRÉSTAMOS | AN6: TOTAL PRESUPUESTADO | AP6: FACTURAS y C de C
A8: PERSONAS NATURALES
A9: 1 | B9: ARBOLEDA PÉREZ DOLLY | C9: =_xlfn.XLOOKUP(B9,Códigos!$B$8:$B$406,Códigos!$A$8:$A$406,"Verificar",0) -> 52 | D9: =_xlfn.XLOOKUP(B9,'Consolidado Cobros'!$B$10:$B$312,'Consolidado Cobros'!$C$10:$C$312,"Verificar",0) -> 43431768 | E9: =IF((MOD((VALUE(MID(TEXT(D9,"000000000000000"),15,1))*3+VALUE(MID(TEXT(D9,"000000000000000"),14,1))*7+VALUE(MID(TEXT(D9,"000000000000000"),13,1))*13+VALUE(MID(TEXT(D9,"000000000000000"),12,1))*17+VALUE(MID(TEXT(D9,"000000000000000"),11,1))*19+VALUE(MID(TEXT(D9,"000000000000000"),10,1))*23+VALUE(MID(TEXT(D9,"000000000000000"),9,1))*29+VALUE(MID(TEXT(D9,"000000000000000"),8,1))*37+VALUE(MID(TEXT(D9,"000000000000000"),7,1))*41+VALUE(MID(TEXT(D9,"000000000000000"),6,1))*43+VALUE(MID(TEXT(D9,"000000000000000"),5,1))*47+VALUE(MID(TEXT(D9,"000000000000000"),4,1))*53+VALUE(MID(TEXT(D9,"000000000000000"),3,1))*59+VALUE(MID(TEXT(D9,"000000000000000"),2,1))*67+VALUE(MID(TEXT(D9,"000000000000000"),1,1))*71),11))=0,0,IF((MOD((VALUE(MID(TEXT(D9,"000000000000000"),15,1))*3+VALUE(MID(TEXT(D9,"000000000000000"),14,1))*7+VALUE(MID(TEXT(D9,"000000000000000"),13,1))*13+VALUE(MID(TEXT(D9,"000000000000000"),12,1))*17+VALUE(MID(TEXT(D9,"000000000000000"),11,1))*19+VALUE(MID(TEXT(D9,"000000000000000"),10,1))*23+VALUE(MID(TEXT(D9,"000000000000000"),9,1))*29+VALUE(MID(TEXT(D9,"000000000000000"),8,1))*37+VALUE(MID(TEXT(D9,"000000000000000"),7,1))*41+VALUE(MID(TEXT(D9,"000000000000000"),6,1))*43+VALUE(MID(TEXT(D9,"000000000000000"),5,1))*47+VALUE(MID(TEXT(D9,"000000000000000"),4,1))*53+VALUE(MID(TEXT(D9,"000000000000000"),3,1))*59+VALUE(MID(TEXT(D9,"000000000000000"),2,1))*67+VALUE(MID(TEXT(D9,"000000000000000"),1,1))*71),11))=1,1,11-(MOD((VALUE(MID(TEXT(D9,"000000000000000"),15,1))*3+VALUE(MID(TEXT(D9,"000000000000000"),14,1))*7+VALUE(MID(TEXT(D9,"000000000000000"),13,1))*13+VALUE(MID(TEXT(D9,"000000000000000"),12,1))*17+VALUE(MID(TEXT(D9,"000000000000000"),11,1))*19+VALUE(MID(TEXT(D9,"000000000000000"),10,1))*23+VALUE(MID(TEXT(D9,"000000000000000"),9,1))*29+VALUE(MID(TEXT(D9,"000000000000000"),8,1))*37+VALUE(MID(TEXT(D9,"000000000000000"),7,1))*41+VALUE(MID(TEXT(D9,"000000000000000"),6,1))*43+VALUE(MID(TEXT(D9,"000000000000000"),5,1))*47+VALUE(MID(TEXT(D9,"000000000000000"),4,1))*53+VALUE(MID(TEXT(D9,"000000000000000"),3,1))*59+VALUE(MID(TEXT(D9,"000000000000000"),2,1))*67+VALUE(MID(TEXT(D9,"000000000000000"),1,1))*71),11)))) -> 3 | F9: =+AN9 -> 510000 | G9: =+F9*$G$5 -> 96900 | H9: S | I9: =IF(H9="S",-F9*$I$5,"NO RETENCIÓN") -> -56100 | J9: =+F9+G9 -> 606900 | K9: =SUM(F9:I9) -> 550800 | M9: GTFF-187 | N9: Correo | O9: 45987 | R9: =+AM9 -> 0 | T9: Fra con -Ruiz González Álvaro H. | V9: SI | W9: =ROUND(IF(V9="SI",SUMIF('Facturas año anterior'!$B$8:$B$81,B9,'Facturas año anterior'!$V$8:$V$81)*(100%+$W$5),0),-3)+ROUND(IF(V9="SI",SUMIF('C de C año anterior'!$B$8:$B$210,B9,'C de C año anterior'!$Q$8:$Q$210)*(100%+$W$5),0),-3) -> 513000 | Y9: =ROUND(IF(X9="SI",W9*$Y$5,0),-3) -> 0 | AA9: =ROUND(IF(Z9="SI",W9*$AA$5,0),-3) -> 0 | AC9: =ROUND(IF(AB9="SI",W9*$AC$5,0),-3) -> 0 | AE9: =ROUND(IF(AD9="SI",W9*$AE$5,0),-3) -> 0 | AG9: =ROUND(IF(AF9="SI",W9*$AG$5,0),-3) -> 0 | AI9: =ROUND(IF(AH9="SI",W9*$AI$5,0),-3) -> 0 | AK9: =IF(AJ9="SI",W9*$AK$5,0) -> 0 | AL9: =SUMIF('Otras Asesorías y Préstamos'!$B$7:$B$242,B9,'Otras Asesorías y Préstamos'!$F$7:$F$242) -> 0 | AM9: =SUMIF('Otras Asesorías y Préstamos'!$B$7:$B$242,B9,'Otras Asesorías y Préstamos'!$V$7:$V$242) -> 0 | AN9: =ROUND(SUM(W9:AL9),-4) -> 510000
A10: =+A9+1 -> 2 | B10: BETANCUR RESTREPO SARA LUISA | C10: =_xlfn.XLOOKUP(B10,Códigos!$B$8:$B$406,Códigos!$A$8:$A$406,"Verificar",0) -> 56 | D10: =_xlfn.XLOOKUP(B10,'Consolidado Cobros'!$B$10:$B$312,'Consolidado Cobros'!$C$10:$C$312,"Verificar",0) -> 87082052990 | E10: =IF((MOD((VALUE(MID(TEXT(D10,"000000000000000"),15,1))*3+VALUE(MID(TEXT(D10,"000000000000000"),14,1))*7+VALUE(MID(TEXT(D10,"000000000000000"),13,1))*13+VALUE(MID(TEXT(D10,"000000000000000"),12,1))*17+VALUE(MID(TEXT(D10,"000000000000000"),11,1))*19+VALUE(MID(TEXT(D10,"000000000000000"),10,1))*23+VALUE(MID(TEXT(D10,"000000000000000"),9,1))*29+VALUE(MID(TEXT(D10,"000000000000000"),8,1))*37+VALUE(MID(TEXT(D10,"000000000000000"),7,1))*41+VALUE(MID(TEXT(D10,"000000000000000"),6,1))*43+VALUE(MID(TEXT(D10,"000000000000000"),5,1))*47+VALUE(MID(TEXT(D10,"000000000000000"),4,1))*53+VALUE(MID(TEXT(D10,"000000000000000"),3,1))*59+VALUE(MID(TEXT(D10,"000000000000000"),2,1))*67+VALUE(MID(TEXT(D10,"000000000000000"),1,1))*71),11))=0,0,IF((MOD((VALUE(MID(TEXT(D10,"000000000000000"),15,1))*3+VALUE(MID(TEXT(D10,"000000000000000"),14,1))*7+VALUE(MID(TEXT(D10,"000000000000000"),13,1))*13+VALUE(MID(TEXT(D10,"000000000000000"),12,1))*17+VALUE(MID(TEXT(D10,"000000000000000"),11,1))*19+VALUE(MID(TEXT(D10,"000000000000000"),10,1))*23+VALUE(MID(TEXT(D10,"000000000000000"),9,1))*29+VALUE(MID(TEXT(D10,"000000000000000"),8,1))*37+VALUE(MID(TEXT(D10,"000000000000000"),7,1))*41+VALUE(MID(TEXT(D10,"000000000000000"),6,1))*43+VALUE(MID(TEXT(D10,"000000000000000"),5,1))*47+VALUE(MID(TEXT(D10,"000000000000000"),4,1))*53+VALUE(MID(TEXT(D10,"000000000000000"),3,1))*59+VALUE(MID(TEXT(D10,"000000000000000"),2,1))*67+VALUE(MID(TEXT(D10,"000000000000000"),1,1))*71),11))=1,1,11-(MOD((VALUE(MID(TEXT(D10,"000000000000000"),15,1))*3+VALUE(MID(TEXT(D10,"000000000000000"),14,1))*7+VALUE(MID(TEXT(D10,"000000000000000"),13,1))*13+VALUE(MID(TEXT(D10,"000000000000000"),12,1))*17+VALUE(MID(TEXT(D10,"000000000000000"),11,1))*19+VALUE(MID(TEXT(D10,"000000000000000"),10,1))*23+VALUE(MID(TEXT(D10,"000000000000000"),9,1))*29+VALUE(MID(TEXT(D10,"000000000000000"),8,1))*37+VALUE(MID(TEXT(D10,"000000000000000"),7,1))*41+VALUE(MID(TEXT(D10,"000000000000000"),6,1))*43+VALUE(MID(TEXT(D10,"000000000000000"),5,1))*47+VALUE(MID(TEXT(D10,"000000000000000"),4,1))*53+VALUE(MID(TEXT(D10,"000000000000000"),3,1))*59+VALUE(MID(TEXT(D10,"000000000000000"),2,1))*67+VALUE(MID(TEXT(D10,"000000000000000"),1,1))*71),11)))) -> 2 | F10: =+AN10 -> 1950000 | G10: =+F10*$G$5 -> 370500 | H10: NO | I10: =IF(H10="S",-F10*$I$5,"NO RETENCIÓN") -> NO RETENCIÓN | J10: =+F10+G10 -> 2320500 | K10: =SUM(F10:I10) -> 2320500 | M10: GTFF-168 | N10: Correo | O10: 45987 | R10: =+AM10 -> 0 | T10: BETANCUR RESTREPO SARA LUISA | V10: SI | W10: =ROUND(IF(V10="SI",SUMIF('Facturas año anterior'!$B$8:$B$81,B10,'Facturas año anterior'!$V$8:$V$81)*(100%+$W$5),0),-3)+ROUND(IF(V10="SI",SUMIF('C de C año anterior'!$B$8:$B$210,B10,'C de C año anterior'!$Q$8:$Q$210)*(100%+$W$5),0),-3) -> 612000 | Y10: =ROUND(IF(X10="SI",W10*$Y$5,0),-3) -> 0 | Z10: si | AA10: =ROUND(IF(Z10="SI",W10*$AA$5,0),-3) -> 459000 | AC10: =ROUND(IF(AB10="SI",W10*$AC$5,0),-3) -> 0 | AE10: =ROUND(IF(AD10="SI",W10*$AE$5,0),-3) -> 0 | AG10: =ROUND(IF(AF10="SI",W10*$AG$5,0),-3) -> 0 | AI10: =ROUND(IF(AH10="SI",W10*$AI$5,0),-3) -> 0 | AJ10: SI | AK10: =IF(AJ10="SI",W10*$AK$5,0) -> 183600 | AL10: =SUMIF('Otras Asesorías y Préstamos'!$B$7:$B$242,B10,'Otras Asesorías y Préstamos'!$F$7:$F$242) -> 690501.15 | AM10: =SUMIF('Otras Asesorías y Préstamos'!$B$7:$B$242,B10,'Otras Asesorías y Préstamos'!$V$7:$V$242) -> 0 | AN10: =ROUND(SUM(W10:AL10),-4) -> 1950000
A11: =+A10+1 -> 3 | B11: CADAVID GALLEGO JULIA CRISTINA | C11: =_xlfn.XLOOKUP(B11,Códigos!$B$8:$B$406,Códigos!$A$8:$A$406,"Verificar",0) -> 59 | D11: =_xlfn.XLOOKUP(B11,'Consolidado Cobros'!$B$10:$B$312,'Consolidado Cobros'!$C$10:$C$312,"Verificar",0) -> 43255512 | E11: =IF((MOD((VALUE(MID(TEXT(D11,"000000000000000"),15,1))*3+VALUE(MID(TEXT(D11,"000000000000000"),14,1))*7+VALUE(MID(TEXT(D11,"000000000000000"),13,1))*13+VALUE(MID(TEXT(D11,"000000000000000"),12,1))*17+VALUE(MID(TEXT(D11,"000000000000000"),11,1))*19+VALUE(MID(TEXT(D11,"000000000000000"),10,1))*23+VALUE(MID(TEXT(D11,"000000000000000"),9,1))*29+VALUE(MID(TEXT(D11,"000000000000000"),8,1))*37+VALUE(MID(TEXT(D11,"000000000000000"),7,1))*41+VALUE(MID(TEXT(D11,"000000000000000"),6,1))*43+VALUE(MID(TEXT(D11,"000000000000000"),5,1))*47+VALUE(MID(TEXT(D11,"000000000000000"),4,1))*53+VALUE(MID(TEXT(D11,"000000000000000"),3,1))*59+VALUE(MID(TEXT(D11,"000000000000000"),2,1))*67+VALUE(MID(TEXT(D11,"000000000000000"),1,1))*71),11))=0,0,IF((MOD((VALUE(MID(TEXT(D11,"000000000000000"),15,1))*3+VALUE(MID(TEXT(D11,"000000000000000"),14,1))*7+VALUE(MID(TEXT(D11,"000000000000000"),13,1))*13+VALUE(MID(TEXT(D11,"000000000000000"),12,1))*17+VALUE(MID(TEXT(D11,"000000000000000"),11,1))*19+VALUE(MID(TEXT(D11,"000000000000000"),10,1))*23+VALUE(MID(TEXT(D11,"000000000000000"),9,1))*29+VALUE(MID(TEXT(D11,"000000000000000"),8,1))*37+VALUE(MID(TEXT(D11,"000000000000000"),7,1))*41+VALUE(MID(TEXT(D11,"000000000000000"),6,1))*43+VALUE(MID(TEXT(D11,"000000000000000"),5,1))*47+VALUE(MID(TEXT(D11,"000000000000000"),4,1))*53+VALUE(MID(TEXT(D11,"000000000000000"),3,1))*59+VALUE(MID(TEXT(D11,"000000000000000"),2,1))*67+VALUE(MID(TEXT(D11,"000000000000000"),1,1))*71),11))=1,1,11-(MOD((VALUE(MID(TEXT(D11,"000000000000000"),15,1))*3+VALUE(MID(TEXT(D11,"000000000000000"),14,1))*7+VALUE(MID(TEXT(D11,"000000000000000"),13,1))*13+VALUE(MID(TEXT(D11,"000000000000000"),12,1))*17+VALUE(MID(TEXT(D11,"000000000000000"),11,1))*19+VALUE(MID(TEXT(D11,"000000000000000"),10,1))*23+VALUE(MID(TEXT(D11,"000000000000000"),9,1))*29+VALUE(MID(TEXT(D11,"000000000000000"),8,1))*37+VALUE(MID(TEXT(D11,"000000000000000"),7,1))*41+VALUE(MID(TEXT(D11,"000000000000000"),6,1))*43+VALUE(MID(TEXT(D11,"000000000000000"),5,1))*47+VALUE(MID(TEXT(D11,"000000000000000"),4,1))*53+VALUE(MID(TEXT(D11,"000000000000000"),3,1))*59+VALUE(MID(TEXT(D11,"000000000000000"),2,1))*67+VALUE(MID(TEXT(D11,"000000000000000"),1,1))*71),11)))) -> 0 | F11: =+AN11 -> 610000 | G11: =+F11*$G$5 -> 115900 | H11: S | I11: =IF(H11="S",-F11*$I$5,"NO RETENCIÓN") -> -67100 | J11: =+F11+G11 -> 725900 | K11: =SUM(F11:I11) -> 658800 | M11: GTFF-175 | N11: Correo | O11: 45987 | R11: =+AM11 -> 0 | T11: Fra con -San Antonio de la Almería | V11: SI | W11: =ROUND(IF(V11="SI",SUMIF('Facturas año anterior'!$B$8:$B$81,B11,'Facturas año anterior'!$V$8:$V$81)*(100%+$W$5),0),-3)+ROUND(IF(V11="SI",SUMIF('C de C año anterior'!$B$8:$B$210,B11,'C de C año anterior'!$Q$8:$Q$210)*(100%+$W$5),0),-3) -> 612000 | Y11: =ROUND(IF(X11="SI",W11*$Y$5,0),-3) -> 0 | AA11: =ROUND(IF(Z11="SI",W11*$AA$5,0),-3) -> 0 | AC11: =ROUND(IF(AB11="SI",W11*$AC$5,0),-3) -> 0 | AE11: =ROUND(IF(AD11="SI",W11*$AE$5,0),-3) -> 0 | AG11: =ROUND(IF(AF11="SI",W11*$AG$5,0),-3) -> 0 | AI11: =ROUND(IF(AH11="SI",W11*$AI$5,0),-3) -> 0 | AK11: =IF(AJ11="SI",W11*$AK$5,0) -> 0 | AL11: =SUMIF('Otras Asesorías y Préstamos'!$B$7:$B$242,B11,'Otras Asesorías y Préstamos'!$F$7:$F$242) -> 0 | AM11: =SUMIF('Otras Asesorías y Préstamos'!$B$7:$B$242,B11,'Otras Asesorías y Préstamos'!$V$7:$V$242) -> 0 | AN11: =ROUND(SUM(W11:AL11),-4) -> 610000
A12: =+A11+1 -> 4 | B12: CORREA DE RÍOS MIRYAM DEL SOCORRO | C12: =_xlfn.XLOOKUP(B12,Códigos!$B$8:$B$406,Códigos!$A$8:$A$406,"Verificar",0) -> 75 | D12: =_xlfn.XLOOKUP(B12,'Consolidado Cobros'!$B$10:$B$312,'Consolidado Cobros'!$C$10:$C$312,"Verificar",0) -> 21829209 | E12: =IF((MOD((VALUE(MID(TEXT(D12,"000000000000000"),15,1))*3+VALUE(MID(TEXT(D12,"000000000000000"),14,1))*7+VALUE(MID(TEXT(D12,"000000000000000"),13,1))*13+VALUE(MID(TEXT(D12,"000000000000000"),12,1))*17+VALUE(MID(TEXT(D12,"000000000000000"),11,1))*19+VALUE(MID(TEXT(D12,"000000000000000"),10,1))*23+VALUE(MID(TEXT(D12,"000000000000000"),9,1))*29+VALUE(MID(TEXT(D12,"000000000000000"),8,1))*37+VALUE(MID(TEXT(D12,"000000000000000"),7,1))*41+VALUE(MID(TEXT(D12,"000000000000000"),6,1))*43+VALUE(MID(TEXT(D12,"000000000000000"),5,1))*47+VALUE(MID(TEXT(D12,"000000000000000"),4,1))*53+VALUE(MID(TEXT(D12,"000000000000000"),3,1))*59+VALUE(MID(TEXT(D12,"000000000000000"),2,1))*67+VALUE(MID(TEXT(D12,"000000000000000"),1,1))*71),11))=0,0,IF((MOD((VALUE(MID(TEXT(D12,"000000000000000"),15,1))*3+VALUE(MID(TEXT(D12,"000000000000000"),14,1))*7+VALUE(MID(TEXT(D12,"000000000000000"),13,1))*13+VALUE(MID(TEXT(D12,"000000000000000"),12,1))*17+VALUE(MID(TEXT(D12,"000000000000000"),11,1))*19+VALUE(MID(TEXT(D12,"000000000000000"),10,1))*23+VALUE(MID(TEXT(D12,"000000000000000"),9,1))*29+VALUE(MID(TEXT(D12,"000000000000000"),8,1))*37+VALUE(MID(TEXT(D12,"000000000000000"),7,1))*41+VALUE(MID(TEXT(D12,"000000000000000"),6,1))*43+VALUE(MID(TEXT(D12,"000000000000000"),5,1))*47+VALUE(MID(TEXT(D12,"000000000000000"),4,1))*53+VALUE(MID(TEXT(D12,"000000000000000"),3,1))*59+VALUE(MID(TEXT(D12,"000000000000000"),2,1))*67+VALUE(MID(TEXT(D12,"000000000000000"),1,1))*71),11))=1,1,11-(MOD((VALUE(MID(TEXT(D12,"000000000000000"),15,1))*3+VALUE(MID(TEXT(D12,"000000000000000"),14,1))*7+VALUE(MID(TEXT(D12,"000000000000000"),13,1))*13+VALUE(MID(TEXT(D12,"000000000000000"),12,1))*17+VALUE(MID(TEXT(D12,"000000000000000"),11,1))*19+VALUE(MID(TEXT(D12,"000000000000000"),10,1))*23+VALUE(MID(TEXT(D12,"000000000000000"),9,1))*29+VALUE(MID(TEXT(D12,"000000000000000"),8,1))*37+VALUE(MID(TEXT(D12,"000000000000000"),7,1))*41+VALUE(MID(TEXT(D12,"000000000000000"),6,1))*43+VALUE(MID(TEXT(D12,"000000000000000"),5,1))*47+VALUE(MID(TEXT(D12,"000000000000000"),4,1))*53+VALUE(MID(TEXT(D12,"000000000000000"),3,1))*59+VALUE(MID(TEXT(D12,"000000000000000"),2,1))*67+VALUE(MID(TEXT(D12,"000000000000000"),1,1))*71),11)))) -> 8 | F12: =+AN12 -> 2240000 | G12: =+F12*$G$5 -> 425600 | H12: S | I12: =IF(H12="S",-F12*$I$5,"NO RETENCIÓN") -> -246400 | J12: =+F12+G12 -> 2665600 | K12: =SUM(F12:I12) -> 2419200 | N12: ES CXC | R12: =+AM12 -> 0 | T12: Se hace cuenta de cobro | V12: SI | W12: =ROUND(IF(V12="SI",SUMIF('Facturas año anterior'!$B$8:$B$81,B12,'Facturas año anterior'!$V$8:$V$81)*(100%+$W$5),0),-3)+ROUND(IF(V12="SI",SUMIF('C de C año anterior'!$B$8:$B$210,B12,'C de C año anterior'!$Q$8:$Q$210)*(100%+$W$5),0),-3) -> 994000 | X12: SI | Y12: =ROUND(IF(X12="SI",W12*$Y$5,0),-3) -> 497000 | Z12: SI | AA12: =ROUND(IF(Z12="SI",W12*$AA$5,0),-3) -> 746000 | AC12: =ROUND(IF(AB12="SI",W12*$AC$5,0),-3) -> 0 | AE12: =ROUND(IF(AD12="SI",W12*$AE$5,0),-3) -> 0 | AG12: =ROUND(IF(AF12="SI",W12*$AG$5,0),-3) -> 0 | AI12: =ROUND(IF(AH12="SI",W12*$AI$5,0),-3) -> 0 | AK12: =IF(AJ12="SI",W12*$AK$5,0) -> 0 | AL12: =SUMIF('Otras Asesorías y Préstamos'!$B$7:$B$242,B12,'Otras Asesorías y Préstamos'!$F$7:$F$242) -> 0 | AM12: =SUMIF('Otras Asesorías y Préstamos'!$B$7:$B$242,B12,'Otras Asesorías y Préstamos'!$V$7:$V$242) -> 0 | AN12: =ROUND(SUM(W12:AL12),-4) -> 2240000
A13: =+A12+1 -> 5 | B13: ECHAVARRÍA DE VILLEGAS ANA ISABEL | C13: =_xlfn.XLOOKUP(B13,Códigos!$B$8:$B$406,Códigos!$A$8:$A$406,"Verificar",0) -> 81 | D13: =_xlfn.XLOOKUP(B13,'Consolidado Cobros'!$B$10:$B$312,'Consolidado Cobros'!$C$10:$C$312,"Verificar",0) -> 21378780 | E13: =IF((MOD((VALUE(MID(TEXT(D13,"000000000000000"),15,1))*3+VALUE(MID(TEXT(D13,"000000000000000"),14,1))*7+VALUE(MID(TEXT(D13,"000000000000000"),13,1))*13+VALUE(MID(TEXT(D13,"000000000000000"),12,1))*17+VALUE(MID(TEXT(D13,"000000000000000"),11,1))*19+VALUE(MID(TEXT(D13,"000000000000000"),10,1))*23+VALUE(MID(TEXT(D13,"000000000000000"),9,1))*29+VALUE(MID(TEXT(D13,"000000000000000"),8,1))*37+VALUE(MID(TEXT(D13,"000000000000000"),7,1))*41+VALUE(MID(TEXT(D13,"000000000000000"),6,1))*43+VALUE(MID(TEXT(D13,"000000000000000"),5,1))*47+VALUE(MID(TEXT(D13,"000000000000000"),4,1))*53+VALUE(MID(TEXT(D13,"000000000000000"),3,1))*59+VALUE(MID(TEXT(D13,"000000000000000"),2,1))*67+VALUE(MID(TEXT(D13,"000000000000000"),1,1))*71),11))=0,0,IF((MOD((VALUE(MID(TEXT(D13,"000000000000000"),15,1))*3+VALUE(MID(TEXT(D13,"000000000000000"),14,1))*7+VALUE(MID(TEXT(D13,"000000000000000"),13,1))*13+VALUE(MID(TEXT(D13,"000000000000000"),12,1))*17+VALUE(MID(TEXT(D13,"000000000000000"),11,1))*19+VALUE(MID(TEXT(D13,"000000000000000"),10,1))*23+VALUE(MID(TEXT(D13,"000000000000000"),9,1))*29+VALUE(MID(TEXT(D13,"000000000000000"),8,1))*37+VALUE(MID(TEXT(D13,"000000000000000"),7,1))*41+VALUE(MID(TEXT(D13,"000000000000000"),6,1))*43+VALUE(MID(TEXT(D13,"000000000000000"),5,1))*47+VALUE(MID(TEXT(D13,"000000000000000"),4,1))*53+VALUE(MID(TEXT(D13,"000000000000000"),3,1))*59+VALUE(MID(TEXT(D13,"000000000000000"),2,1))*67+VALUE(MID(TEXT(D13,"000000000000000"),1,1))*71),11))=1,1,11-(MOD((VALUE(MID(TEXT(D13,"000000000000000"),15,1))*3+VALUE(MID(TEXT(D13,"000000000000000"),14,1))*7+VALUE(MID(TEXT(D13,"000000000000000"),13,1))*13+VALUE(MID(TEXT(D13,"000000000000000"),12,1))*17+VALUE(MID(TEXT(D13,"000000000000000"),11,1))*19+VALUE(MID(TEXT(D13,"000000000000000"),10,1))*23+VALUE(MID(TEXT(D13,"000000000000000"),9,1))*29+VALUE(MID(TEXT(D13,"000000000000000"),8,1))*37+VALUE(MID(TEXT(D13,"000000000000000"),7,1))*41+VALUE(MID(TEXT(D13,"000000000000000"),6,1))*43+VALUE(MID(TEXT(D13,"000000000000000"),5,1))*47+VALUE(MID(TEXT(D13,"000000000000000"),4,1))*53+VALUE(MID(TEXT(D13,"000000000000000"),3,1))*59+VALUE(MID(TEXT(D13,"000000000000000"),2,1))*67+VALUE(MID(TEXT(D13,"000000000000000"),1,1))*71),11)))) -> 6 | F13: =+AN13 -> 1900000 | G13: =+F13*$G$5 -> 361000 | H13: S | I13: =IF(H13="S",-F13*$I$5,"NO RETENCIÓN") -> -209000 | J13: =+F13+G13 -> 2261000 | K13: =SUM(F13:I13) -> 2052000 | M13: GTFF-184 | N13: Correo | O13: 45987 | R13: =+AM13 -> 0 | T13: Fra con -Truly Nolen | V13: SI | W13: =ROUND(IF(V13="SI",SUMIF('Facturas año anterior'!$B$8:$B$81,B13,'Facturas año anterior'!$V$8:$V$81)*(100%+$W$5),0),-3)+ROUND(IF(V13="SI",SUMIF('C de C año anterior'!$B$8:$B$210,B13,'C de C año anterior'!$Q$8:$Q$210)*(100%+$W$5),0),-3) -> 1904000 | Y13: =ROUND(IF(X13="SI",W13*$Y$5,0),-3) -> 0 | AA13: =ROUND(IF(Z13="SI",W13*$AA$5,0),-3) -> 0 | AC13: =ROUND(IF(AB13="SI",W13*$AC$5,0),-3) -> 0 | AE13: =ROUND(IF(AD13="SI",W13*$AE$5,0),-3) -> 0 | AG13: =ROUND(IF(AF13="SI",W13*$AG$5,0),-3) -> 0 | AI13: =ROUND(IF(AH13="SI",W13*$AI$5,0),-3) -> 0 | AK13: =IF(AJ13="SI",W13*$AK$5,0) -> 0 | AL13: =SUMIF('Otras Asesorías y Préstamos'!$B$7:$B$242,B13,'Otras Asesorías y Préstamos'!$F$7:$F$242) -> 0 | AM13: =SUMIF('Otras Asesorías y Préstamos'!$B$7:$B$242,B13,'Otras Asesorías y Préstamos'!$V$7:$V$242) -> 0 | AN13: =ROUND(SUM(W13:AL13),-4) -> 1900000
A14: =+A13+1 -> 6 | B14: GALLEGO ARIAS GLORIA CRISTINA | C14: =_xlfn.XLOOKUP(B14,Códigos!$B$8:$B$406,Códigos!$A$8:$A$406,"Verificar",0) -> 54 | D14: =_xlfn.XLOOKUP(B14,'Consolidado Cobros'!$B$10:$B$312,'Consolidado Cobros'!$C$10:$C$312,"Verificar",0) -> 43422834 | E14: =IF((MOD((VALUE(MID(TEXT(D14,"000000000000000"),15,1))*3+VALUE(MID(TEXT(D14,"000000000000000"),14,1))*7+VALUE(MID(TEXT(D14,"000000000000000"),13,1))*13+VALUE(MID(TEXT(D14,"000000000000000"),12,1))*17+VALUE(MID(TEXT(D14,"000000000000000"),11,1))*19+VALUE(MID(TEXT(D14,"000000000000000"),10,1))*23+VALUE(MID(TEXT(D14,"000000000000000"),9,1))*29+VALUE(MID(TEXT(D14,"000000000000000"),8,1))*37+VALUE(MID(TEXT(D14,"000000000000000"),7,1))*41+VALUE(MID(TEXT(D14,"000000000000000"),6,1))*43+VALUE(MID(TEXT(D14,"000000000000000"),5,1))*47+VALUE(MID(TEXT(D14,"000000000000000"),4,1))*53+VALUE(MID(TEXT(D14,"000000000000000"),3,1))*59+VALUE(MID(TEXT(D14,"000000000000000"),2,1))*67+VALUE(MID(TEXT(D14,"000000000000000"),1,1))*71),11))=0,0,IF((MOD((VALUE(MID(TEXT(D14,"000000000000000"),15,1))*3+VALUE(MID(TEXT(D14,"000000000000000"),14,1))*7+VALUE(MID(TEXT(D14,"000000000000000"),13,1))*13+VALUE(MID(TEXT(D14,"000000000000000"),12,1))*17+VALUE(MID(TEXT(D14,"000000000000000"),11,1))*19+VALUE(MID(TEXT(D14,"000000000000000"),10,1))*23+VALUE(MID(TEXT(D14,"000000000000000"),9,1))*29+VALUE(MID(TEXT(D14,"000000000000000"),8,1))*37+VALUE(MID(TEXT(D14,"000000000000000"),7,1))*41+VALUE(MID(TEXT(D14,"000000000000000"),6,1))*43+VALUE(MID(TEXT(D14,"000000000000000"),5,1))*47+VALUE(MID(TEXT(D14,"000000000000000"),4,1))*53+VALUE(MID(TEXT(D14,"000000000000000"),3,1))*59+VALUE(MID(TEXT(D14,"000000000000000"),2,1))*67+VALUE(MID(TEXT(D14,"000000000000000"),1,1))*71),11))=1,1,11-(MOD((VALUE(MID(TEXT(D14,"000000000000000"),15,1))*3+VALUE(MID(TEXT(D14,"000000000000000"),14,1))*7+VALUE(MID(TEXT(D14,"000000000000000"),13,1))*13+VALUE(MID(TEXT(D14,"000000000000000"),12,1))*17+VALUE(MID(TEXT(D14,"000000000000000"),11,1))*19+VALUE(MID(TEXT(D14,"000000000000000"),10,1))*23+VALUE(MID(TEXT(D14,"000000000000000"),9,1))*29+VALUE(MID(TEXT(D14,"000000000000000"),8,1))*37+VALUE(MID(TEXT(D14,"000000000000000"),7,1))*41+VALUE(MID(TEXT(D14,"000000000000000"),6,1))*43+VALUE(MID(TEXT(D14,"000000000000000"),5,1))*47+VALUE(MID(TEXT(D14,"000000000000000"),4,1))*53+VALUE(MID(TEXT(D14,"000000000000000"),3,1))*59+VALUE(MID(TEXT(D14,"000000000000000"),2,1))*67+VALUE(MID(TEXT(D14,"000000000000000"),1,1))*71),11)))) -> 3 | F14: =+AN14 -> 610000 | G14: =+F14*$G$5 -> 115900 | H14: S | I14: =IF(H14="S",-F14*$I$5,"NO RETENCIÓN") -> -67100 | J14: =+F14+G14 -> 725900 | K14: =SUM(F14:I14) -> 658800 | M14: GTFF-175 | N14: Correo | O14: 45987 | R14: =+AM14 -> 0 | T14: Fra con -San Antonio de la Almería | V14: SI | W14: =ROUND(IF(V14="SI",SUMIF('Facturas año anterior'!$B$8:$B$81,B14,'Facturas año anterior'!$V$8:$V$81)*(100%+$W$5),0),-3)+ROUND(IF(V14="SI",SUMIF('C de C año anterior'!$B$8:$B$210,B14,'C de C año anterior'!$Q$8:$Q$210)*(100%+$W$5),0),-3) -> 612000 | Y14: =ROUND(IF(X14="SI",W14*$Y$5,0),-3) -> 0 | AA14: =ROUND(IF(Z14="SI",W14*$AA$5,0),-3) -> 0 | AC14: =ROUND(IF(AB14="SI",W14*$AC$5,0),-3) -> 0 | AE14: =ROUND(IF(AD14="SI",W14*$AE$5,0),-3) -> 0 | AG14: =ROUND(IF(AF14="SI",W14*$AG$5,0),-3) -> 0 | AI14: =ROUND(IF(AH14="SI",W14*$AI$5,0),-3) -> 0 | AK14: =IF(AJ14="SI",W14*$AK$5,0) -> 0 | AL14: =SUMIF('Otras Asesorías y Préstamos'!$B$7:$B$242,B14,'Otras Asesorías y Préstamos'!$F$7:$F$242) -> 0 | AM14: =SUMIF('Otras Asesorías y Préstamos'!$B$7:$B$242,B14,'Otras Asesorías y Préstamos'!$V$7:$V$242) -> 0 | AN14: =ROUND(SUM(W14:AL14),-4) -> 610000
A15: =+A14+1 -> 7 | B15: GALLEGO ARIAS MIRIAM DEL SOCORRO | C15: =_xlfn.XLOOKUP(B15,Códigos!$B$8:$B$406,Códigos!$A$8:$A$406,"Verificar",0) -> 99 | D15: =_xlfn.XLOOKUP(B15,'Consolidado Cobros'!$B$10:$B$312,'Consolidado Cobros'!$C$10:$C$312,"Verificar",0) -> 43422711 | E15: =IF((MOD((VALUE(MID(TEXT(D15,"000000000000000"),15,1))*3+VALUE(MID(TEXT(D15,"000000000000000"),14,1))*7+VALUE(MID(TEXT(D15,"000000000000000"),13,1))*13+VALUE(MID(TEXT(D15,"000000000000000"),12,1))*17+VALUE(MID(TEXT(D15,"000000000000000"),11,1))*19+VALUE(MID(TEXT(D15,"000000000000000"),10,1))*23+VALUE(MID(TEXT(D15,"000000000000000"),9,1))*29+VALUE(MID(TEXT(D15,"000000000000000"),8,1))*37+VALUE(MID(TEXT(D15,"000000000000000"),7,1))*41+VALUE(MID(TEXT(D15,"000000000000000"),6,1))*43+VALUE(MID(TEXT(D15,"000000000000000"),5,1))*47+VALUE(MID(TEXT(D15,"000000000000000"),4,1))*53+VALUE(MID(TEXT(D15,"000000000000000"),3,1))*59+VALUE(MID(TEXT(D15,"000000000000000"),2,1))*67+VALUE(MID(TEXT(D15,"000000000000000"),1,1))*71),11))=0,0,IF((MOD((VALUE(MID(TEXT(D15,"000000000000000"),15,1))*3+VALUE(MID(TEXT(D15,"000000000000000"),14,1))*7+VALUE(MID(TEXT(D15,"000000000000000"),13,1))*13+VALUE(MID(TEXT(D15,"000000000000000"),12,1))*17+VALUE(MID(TEXT(D15,"000000000000000"),11,1))*19+VALUE(MID(TEXT(D15,"000000000000000"),10,1))*23+VALUE(MID(TEXT(D15,"000000000000000"),9,1))*29+VALUE(MID(TEXT(D15,"000000000000000"),8,1))*37+VALUE(MID(TEXT(D15,"000000000000000"),7,1))*41+VALUE(MID(TEXT(D15,"000000000000000"),6,1))*43+VALUE(MID(TEXT(D15,"000000000000000"),5,1))*47+VALUE(MID(TEXT(D15,"000000000000000"),4,1))*53+VALUE(MID(TEXT(D15,"000000000000000"),3,1))*59+VALUE(MID(TEXT(D15,"000000000000000"),2,1))*67+VALUE(MID(TEXT(D15,"000000000000000"),1,1))*71),11))=1,1,11-(MOD((VALUE(MID(TEXT(D15,"000000000000000"),15,1))*3+VALUE(MID(TEXT(D15,"000000000000000"),14,1))*7+VALUE(MID(TEXT(D15,"000000000000000"),13,1))*13+VALUE(MID(TEXT(D15,"000000000000000"),12,1))*17+VALUE(MID(TEXT(D15,"000000000000000"),11,1))*19+VALUE(MID(TEXT(D15,"000000000000000"),10,1))*23+VALUE(MID(TEXT(D15,"000000000000000"),9,1))*29+VALUE(MID(TEXT(D15,"000000000000000"),8,1))*37+VALUE(MID(TEXT(D15,"000000000000000"),7,1))*41+VALUE(MID(TEXT(D15,"000000000000000"),6,1))*43+VALUE(MID(TEXT(D15,"000000000000000"),5,1))*47+VALUE(MID(TEXT(D15,"000000000000000"),4,1))*53+VALUE(MID(TEXT(D15,"000000000000000"),3,1))*59+VALUE(MID(TEXT(D15,"000000000000000"),2,1))*67+VALUE(MID(TEXT(D15,"000000000000000"),1,1))*71),11)))) -> 6 | F15: =+AN15 -> 1410000 | G15: =+F15*$G$5 -> 267900 | H15: S | I15: =IF(H15="S",-F15*$I$5,"NO RETENCIÓN") -> -155100 | J15: =+F15+G15 -> 1677900 | K15: =SUM(F15:I15) -> 1522800 | M15: GTFF-175 | N15: Correo | O15: 45987 | R15: =+AM15 -> 0 | T15: Fra con -San Antonio de la Almería | V15: SI | W15: =ROUND(IF(V15="SI",SUMIF('Facturas año anterior'!$B$8:$B$81,B15,'Facturas año anterior'!$V$8:$V$81)*(100%+$W$5),0),-3)+ROUND(IF(V15="SI",SUMIF('C de C año anterior'!$B$8:$B$210,B15,'C de C año anterior'!$Q$8:$Q$210)*(100%+$W$5),0),-3) -> 1410000 | Y15: =ROUND(IF(X15="SI",W15*$Y$5,0),-3) -> 0 | AA15: =ROUND(IF(Z15="SI",W15*$AA$5,0),-3) -> 0 | AC15: =ROUND(IF(AB15="SI",W15*$AC$5,0),-3) -> 0 | AE15: =ROUND(IF(AD15="SI",W15*$AE$5,0),-3) -> 0 | AG15: =ROUND(IF(AF15="SI",W15*$AG$5,0),-3) -> 0 | AI15: =ROUND(IF(AH15="SI",W15*$AI$5,0),-3) -> 0 | AK15: =IF(AJ15="SI",W15*$AK$5,0) -> 0 | AL15: =SUMIF('Otras Asesorías y Préstamos'!$B$7:$B$242,B15,'Otras Asesorías y Préstamos'!$F$7:$F$242) -> 0 | AM15: =SUMIF('Otras Asesorías y Préstamos'!$B$7:$B$242,B15,'Otras Asesorías y Préstamos'!$V$7:$V$242) -> 0 | AN15: =ROUND(SUM(W15:AL15),-4) -> 1410000
A16: =+A15+1 -> 8 | B16: MAYA JIMÉNEZ MARÍA TERESA | C16: =_xlfn.XLOOKUP(B16,Códigos!$B$8:$B$406,Códigos!$A$8:$A$406,"Verificar",0) -> 80 | D16: =_xlfn.XLOOKUP(B16,'Consolidado Cobros'!$B$10:$B$312,'Consolidado Cobros'!$C$10:$C$312,"Verificar",0) -> 1037630601 | E16: =IF((MOD((VALUE(MID(TEXT(D16,"000000000000000"),15,1))*3+VALUE(MID(TEXT(D16,"000000000000000"),14,1))*7+VALUE(MID(TEXT(D16,"000000000000000"),13,1))*13+VALUE(MID(TEXT(D16,"000000000000000"),12,1))*17+VALUE(MID(TEXT(D16,"000000000000000"),11,1))*19+VALUE(MID(TEXT(D16,"000000000000000"),10,1))*23+VALUE(MID(TEXT(D16,"000000000000000"),9,1))*29+VALUE(MID(TEXT(D16,"000000000000000"),8,1))*37+VALUE(MID(TEXT(D16,"000000000000000"),7,1))*41+VALUE(MID(TEXT(D16,"000000000000000"),6,1))*43+VALUE(MID(TEXT(D16,"000000000000000"),5,1))*47+VALUE(MID(TEXT(D16,"000000000000000"),4,1))*53+VALUE(MID(TEXT(D16,"000000000000000"),3,1))*59+VALUE(MID(TEXT(D16,"000000000000000"),2,1))*67+VALUE(MID(TEXT(D16,"000000000000000"),1,1))*71),11))=0,0,IF((MOD((VALUE(MID(TEXT(D16,"000000000000000"),15,1))*3+VALUE(MID(TEXT(D16,"000000000000000"),14,1))*7+VALUE(MID(TEXT(D16,"000000000000000"),13,1))*13+VALUE(MID(TEXT(D16,"000000000000000"),12,1))*17+VALUE(MID(TEXT(D16,"000000000000000"),11,1))*19+VALUE(MID(TEXT(D16,"000000000000000"),10,1))*23+VALUE(MID(TEXT(D16,"000000000000000"),9,1))*29+VALUE(MID(TEXT(D16,"000000000000000"),8,1))*37+VALUE(MID(TEXT(D16,"000000000000000"),7,1))*41+VALUE(MID(TEXT(D16,"000000000000000"),6,1))*43+VALUE(MID(TEXT(D16,"000000000000000"),5,1))*47+VALUE(MID(TEXT(D16,"000000000000000"),4,1))*53+VALUE(MID(TEXT(D16,"000000000000000"),3,1))*59+VALUE(MID(TEXT(D16,"000000000000000"),2,1))*67+VALUE(MID(TEXT(D16,"000000000000000"),1,1))*71),11))=1,1,11-(MOD((VALUE(MID(TEXT(D16,"000000000000000"),15,1))*3+VALUE(MID(TEXT(D16,"000000000000000"),14,1))*7+VALUE(MID(TEXT(D16,"000000000000000"),13,1))*13+VALUE(MID(TEXT(D16,"000000000000000"),12,1))*17+VALUE(MID(TEXT(D16,"000000000000000"),11,1))*19+VALUE(MID(TEXT(D16,"000000000000000"),10,1))*23+VALUE(MID(TEXT(D16,"000000000000000"),9,1))*29+VALUE(MID(TEXT(D16,"000000000000000"),8,1))*37+VALUE(MID(TEXT(D16,"000000000000000"),7,1))*41+VALUE(MID(TEXT(D16,"000000000000000"),6,1))*43+VALUE(MID(TEXT(D16,"000000000000000"),5,1))*47+VALUE(MID(TEXT(D16,"000000000000000"),4,1))*53+VALUE(MID(TEXT(D16,"000000000000000"),3,1))*59+VALUE(MID(TEXT(D16,"000000000000000"),2,1))*67+VALUE(MID(TEXT(D16,"000000000000000"),1,1))*71),11)))) -> 5 | F16: =+AN16 -> 220000 | G16: =+F16*$G$5 -> 41800 | H16: S | I16: =IF(H16="S",-F16*$I$5,"NO RETENCIÓN") -> -24200 | J16: =+F16+G16 -> 261800 | K16: =SUM(F16:I16) -> 237600 | M16: GTFF-187 | N16: Correo | O16: 45987 | R16: =+AM16 -> 0 | T16: Fra con -Ruiz González Álvaro H. | V16: SI | W16: =ROUND(IF(V16="SI",SUMIF('Facturas año anterior'!$B$8:$B$81,B16,'Facturas año anterior'!$V$8:$V$81)*(100%+$W$5),0),-3)+ROUND(IF(V16="SI",SUMIF('C de C año anterior'!$B$8:$B$210,B16,'C de C año anterior'!$Q$8:$Q$210)*(100%+$W$5),0),-3) -> 221000 | Y16: =ROUND(IF(X16="SI",W16*$Y$5,0),-3) -> 0 | AA16: =ROUND(IF(Z16="SI",W16*$AA$5,0),-3) -> 0 | AC16: =ROUND(IF(AB16="SI",W16*$AC$5,0),-3) -> 0 | AE16: =ROUND(IF(AD16="SI",W16*$AE$5,0),-3) -> 0 | AG16: =ROUND(IF(AF16="SI",W16*$AG$5,0),-3) -> 0 | AI16: =ROUND(IF(AH16="SI",W16*$AI$5,0),-3) -> 0 | AK16: =IF(AJ16="SI",W16*$AK$5,0) -> 0 | AL16: =SUMIF('Otras Asesorías y Préstamos'!$B$7:$B$242,B16,'Otras Asesorías y Préstamos'!$F$7:$F$242) -> 0 | AM16: =SUMIF('Otras Asesorías y Préstamos'!$B$7:$B$242,B16,'Otras Asesorías y Préstamos'!$V$7:$V$242) -> 0 | AN16: =ROUND(SUM(W16:AL16),-4) -> 220000
A17: =+A16+1 -> 9 | B17: MEJÍA DUQUE LINA MARÍA | C17: =_xlfn.XLOOKUP(B17,Códigos!$B$8:$B$406,Códigos!$A$8:$A$406,"Verificar",0) -> 216 | D17: =_xlfn.XLOOKUP(B17,'Consolidado Cobros'!$B$10:$B$312,'Consolidado Cobros'!$C$10:$C$312,"Verificar",0) -> 32523581 | E17: =IF((MOD((VALUE(MID(TEXT(D17,"000000000000000"),15,1))*3+VALUE(MID(TEXT(D17,"000000000000000"),14,1))*7+VALUE(MID(TEXT(D17,"000000000000000"),13,1))*13+VALUE(MID(TEXT(D17,"000000000000000"),12,1))*17+VALUE(MID(TEXT(D17,"000000000000000"),11,1))*19+VALUE(MID(TEXT(D17,"000000000000000"),10,1))*23+VALUE(MID(TEXT(D17,"000000000000000"),9,1))*29+VALUE(MID(TEXT(D17,"000000000000000"),8,1))*37+VALUE(MID(TEXT(D17,"000000000000000"),7,1))*41+VALUE(MID(TEXT(D17,"000000000000000"),6,1))*43+VALUE(MID(TEXT(D17,"000000000000000"),5,1))*47+VALUE(MID(TEXT(D17,"000000000000000"),4,1))*53+VALUE(MID(TEXT(D17,"000000000000000"),3,1))*59+VALUE(MID(TEXT(D17,"000000000000000"),2,1))*67+VALUE(MID(TEXT(D17,"000000000000000"),1,1))*71),11))=0,0,IF((MOD((VALUE(MID(TEXT(D17,"000000000000000"),15,1))*3+VALUE(MID(TEXT(D17,"000000000000000"),14,1))*7+VALUE(MID(TEXT(D17,"000000000000000"),13,1))*13+VALUE(MID(TEXT(D17,"000000000000000"),12,1))*17+VALUE(MID(TEXT(D17,"000000000000000"),11,1))*19+VALUE(MID(TEXT(D17,"000000000000000"),10,1))*23+VALUE(MID(TEXT(D17,"000000000000000"),9,1))*29+VALUE(MID(TEXT(D17,"000000000000000"),8,1))*37+VALUE(MID(TEXT(D17,"000000000000000"),7,1))*41+VALUE(MID(TEXT(D17,"000000000000000"),6,1))*43+VALUE(MID(TEXT(D17,"000000000000000"),5,1))*47+VALUE(MID(TEXT(D17,"000000000000000"),4,1))*53+VALUE(MID(TEXT(D17,"000000000000000"),3,1))*59+VALUE(MID(TEXT(D17,"000000000000000"),2,1))*67+VALUE(MID(TEXT(D17,"000000000000000"),1,1))*71),11))=1,1,11-(MOD((VALUE(MID(TEXT(D17,"000000000000000"),15,1))*3+VALUE(MID(TEXT(D17,"000000000000000"),14,1))*7+VALUE(MID(TEXT(D17,"000000000000000"),13,1))*13+VALUE(MID(TEXT(D17,"000000000000000"),12,1))*17+VALUE(MID(TEXT(D17,"000000000000000"),11,1))*19+VALUE(MID(TEXT(D17,"000000000000000"),10,1))*23+VALUE(MID(TEXT(D17,"000000000000000"),9,1))*29+VALUE(MID(TEXT(D17,"000000000000000"),8,1))*37+VALUE(MID(TEXT(D17,"000000000000000"),7,1))*41+VALUE(MID(TEXT(D17,"000000000000000"),6,1))*43+VALUE(MID(TEXT(D17,"000000000000000"),5,1))*47+VALUE(MID(TEXT(D17,"000000000000000"),4,1))*53+VALUE(MID(TEXT(D17,"000000000000000"),3,1))*59+VALUE(MID(TEXT(D17,"000000000000000"),2,1))*67+VALUE(MID(TEXT(D17,"000000000000000"),1,1))*71),11)))) -> 9 | F17: =+AN17 -> 1480000 | G17: =+F17*$G$5 -> 281200 | H17: S | I17: =IF(H17="S",-F17*$I$5,"NO RETENCIÓN") -> -162800 | J17: =+F17+G17 -> 1761200 | K17: =SUM(F17:I17) -> 1598400 | M17: GTFF-182 | N17: Correo | O17: 45987 | R17: =+AM17 -> 0 | T17: Fra con -LINABI | V17: SI | W17: =ROUND(IF(V17="SI",SUMIF('Facturas año anterior'!$B$8:$B$81,B17,'Facturas año anterior'!$V$8:$V$81)*(100%+$W$5),0),-3)+ROUND(IF(V17="SI",SUMIF('C de C año anterior'!$B$8:$B$210,B17,'C de C año anterior'!$Q$8:$Q$210)*(100%+$W$5),0),-3) -> 1483000 | Y17: =ROUND(IF(X17="SI",W17*$Y$5,0),-3) -> 0 | AA17: =ROUND(IF(Z17="SI",W17*$AA$5,0),-3) -> 0 | AC17: =ROUND(IF(AB17="SI",W17*$AC$5,0),-3) -> 0 | AE17: =ROUND(IF(AD17="SI",W17*$AE$5,0),-3) -> 0 | AG17: =ROUND(IF(AF17="SI",W17*$AG$5,0),-3) -> 0 | AI17: =ROUND(IF(AH17="SI",W17*$AI$5,0),-3) -> 0 | AK17: =IF(AJ17="SI",W17*$AK$5,0) -> 0 | AL17: =SUMIF('Otras Asesorías y Préstamos'!$B$7:$B$242,B17,'Otras Asesorías y Préstamos'!$F$7:$F$242) -> 0 | AM17: =SUMIF('Otras Asesorías y Préstamos'!$B$7:$B$242,B17,'Otras Asesorías y Préstamos'!$V$7:$V$242) -> 0 | AN17: =ROUND(SUM(W17:AL17),-4) -> 1480000
A18: =+A17+1 -> 10 | B18: RESTREPO ÁLVAREZ LUÍS EMILIO | C18: =_xlfn.XLOOKUP(B18,Códigos!$B$8:$B$406,Códigos!$A$8:$A$406,"Verificar",0) -> 155 | D18: =_xlfn.XLOOKUP(B18,'Consolidado Cobros'!$B$10:$B$312,'Consolidado Cobros'!$C$10:$C$312,"Verificar",0) -> 92102300043 | E18: =IF((MOD((VALUE(MID(TEXT(D18,"000000000000000"),15,1))*3+VALUE(MID(TEXT(D18,"000000000000000"),14,1))*7+VALUE(MID(TEXT(D18,"000000000000000"),13,1))*13+VALUE(MID(TEXT(D18,"000000000000000"),12,1))*17+VALUE(MID(TEXT(D18,"000000000000000"),11,1))*19+VALUE(MID(TEXT(D18,"000000000000000"),10,1))*23+VALUE(MID(TEXT(D18,"000000000000000"),9,1))*29+VALUE(MID(TEXT(D18,"000000000000000"),8,1))*37+VALUE(MID(TEXT(D18,"000000000000000"),7,1))*41+VALUE(MID(TEXT(D18,"000000000000000"),6,1))*43+VALUE(MID(TEXT(D18,"000000000000000"),5,1))*47+VALUE(MID(TEXT(D18,"000000000000000"),4,1))*53+VALUE(MID(TEXT(D18,"000000000000000"),3,1))*59+VALUE(MID(TEXT(D18,"000000000000000"),2,1))*67+VALUE(MID(TEXT(D18,"000000000000000"),1,1))*71),11))=0,0,IF((MOD((VALUE(MID(TEXT(D18,"000000000000000"),15,1))*3+VALUE(MID(TEXT(D18,"000000000000000"),14,1))*7+VALUE(MID(TEXT(D18,"000000000000000"),13,1))*13+VALUE(MID(TEXT(D18,"000000000000000"),12,1))*17+VALUE(MID(TEXT(D18,"000000000000000"),11,1))*19+VALUE(MID(TEXT(D18,"000000000000000"),10,1))*23+VALUE(MID(TEXT(D18,"000000000000000"),9,1))*29+VALUE(MID(TEXT(D18,"000000000000000"),8,1))*37+VALUE(MID(TEXT(D18,"000000000000000"),7,1))*41+VALUE(MID(TEXT(D18,"000000000000000"),6,1))*43+VALUE(MID(TEXT(D18,"000000000000000"),5,1))*47+VALUE(MID(TEXT(D18,"000000000000000"),4,1))*53+VALUE(MID(TEXT(D18,"000000000000000"),3,1))*59+VALUE(MID(TEXT(D18,"000000000000000"),2,1))*67+VALUE(MID(TEXT(D18,"000000000000000"),1,1))*71),11))=1,1,11-(MOD((VALUE(MID(TEXT(D18,"000000000000000"),15,1))*3+VALUE(MID(TEXT(D18,"000000000000000"),14,1))*7+VALUE(MID(TEXT(D18,"000000000000000"),13,1))*13+VALUE(MID(TEXT(D18,"000000000000000"),12,1))*17+VALUE(MID(TEXT(D18,"000000000000000"),11,1))*19+VALUE(MID(TEXT(D18,"000000000000000"),10,1))*23+VALUE(MID(TEXT(D18,"000000000000000"),9,1))*29+VALUE(MID(TEXT(D18,"000000000000000"),8,1))*37+VALUE(MID(TEXT(D18,"000000000000000"),7,1))*41+VALUE(MID(TEXT(D18,"000000000000000"),6,1))*43+VALUE(MID(TEXT(D18,"000000000000000"),5,1))*47+VALUE(MID(TEXT(D18,"000000000000000"),4,1))*53+VALUE(MID(TEXT(D18,"000000000000000"),3,1))*59+VALUE(MID(TEXT(D18,"000000000000000"),2,1))*67+VALUE(MID(TEXT(D18,"000000000000000"),1,1))*71),11)))) -> 1 | F18: =+AN18 -> 800000 | G18: =+F18*$G$5 -> 152000 | H18: S | I18: =IF(H18="S",-F18*$I$5,"NO RETENCIÓN") -> -88000 | J18: =+F18+G18 -> 952000 | K18: =SUM(F18:I18) -> 864000 | M18: GTFF-172 | N18: Correo | O18: 45987 | R18: =+AM18 -> 0 | T18: Fra con -Invers. Luís Emilio | V18: SI | W18: =ROUND(IF(V18="SI",SUMIF('Facturas año anterior'!$B$8:$B$81,B18,'Facturas año anterior'!$V$8:$V$81)*(100%+$W$5),0),-3)+ROUND(IF(V18="SI",SUMIF('C de C año anterior'!$B$8:$B$210,B18,'C de C año anterior'!$Q$8:$Q$210)*(100%+$W$5),0),-3) -> 612000 | Y18: =ROUND(IF(X18="SI",W18*$Y$5,0),-3) -> 0 | AA18: =ROUND(IF(Z18="SI",W18*$AA$5,0),-3) -> 0 | AC18: =ROUND(IF(AB18="SI",W18*$AC$5,0),-3) -> 0 | AE18: =ROUND(IF(AD18="SI",W18*$AE$5,0),-3) -> 0 | AG18: =ROUND(IF(AF18="SI",W18*$AG$5,0),-3) -> 0 | AI18: =ROUND(IF(AH18="SI",W18*$AI$5,0),-3) -> 0 | AJ18: SI | AK18: =IF(AJ18="SI",W18*$AK$5,0) -> 183600 | AL18: =SUMIF('Otras Asesorías y Préstamos'!$B$7:$B$242,B18,'Otras Asesorías y Préstamos'!$F$7:$F$242) -> 0 | AM18: =SUMIF('Otras Asesorías y Préstamos'!$B$7:$B$242,B18,'Otras Asesorías y Préstamos'!$V$7:$V$242) -> 0 | AN18: =ROUND(SUM(W18:AL18),-4) -> 800000
A19: =+A18+1 -> 11 | B19: RESTREPO DE SÁNCHEZ MARÍA ISABEL | C19: =_xlfn.XLOOKUP(B19,Códigos!$B$8:$B$406,Códigos!$A$8:$A$406,"Verificar",0) -> 158 | D19: =_xlfn.XLOOKUP(B19,'Consolidado Cobros'!$B$10:$B$312,'Consolidado Cobros'!$C$10:$C$312,"Verificar",0) -> 21356663 | E19: =IF((MOD((VALUE(MID(TEXT(D19,"000000000000000"),15,1))*3+VALUE(MID(TEXT(D19,"000000000000000"),14,1))*7+VALUE(MID(TEXT(D19,"000000000000000"),13,1))*13+VALUE(MID(TEXT(D19,"000000000000000"),12,1))*17+VALUE(MID(TEXT(D19,"000000000000000"),11,1))*19+VALUE(MID(TEXT(D19,"000000000000000"),10,1))*23+VALUE(MID(TEXT(D19,"000000000000000"),9,1))*29+VALUE(MID(TEXT(D19,"000000000000000"),8,1))*37+VALUE(MID(TEXT(D19,"000000000000000"),7,1))*41+VALUE(MID(TEXT(D19,"000000000000000"),6,1))*43+VALUE(MID(TEXT(D19,"000000000000000"),5,1))*47+VALUE(MID(TEXT(D19,"000000000000000"),4,1))*53+VALUE(MID(TEXT(D19,"000000000000000"),3,1))*59+VALUE(MID(TEXT(D19,"000000000000000"),2,1))*67+VALUE(MID(TEXT(D19,"000000000000000"),1,1))*71),11))=0,0,IF((MOD((VALUE(MID(TEXT(D19,"000000000000000"),15,1))*3+VALUE(MID(TEXT(D19,"000000000000000"),14,1))*7+VALUE(MID(TEXT(D19,"000000000000000"),13,1))*13+VALUE(MID(TEXT(D19,"000000000000000"),12,1))*17+VALUE(MID(TEXT(D19,"000000000000000"),11,1))*19+VALUE(MID(TEXT(D19,"000000000000000"),10,1))*23+VALUE(MID(TEXT(D19,"000000000000000"),9,1))*29+VALUE(MID(TEXT(D19,"000000000000000"),8,1))*37+VALUE(MID(TEXT(D19,"000000000000000"),7,1))*41+VALUE(MID(TEXT(D19,"000000000000000"),6,1))*43+VALUE(MID(TEXT(D19,"000000000000000"),5,1))*47+VALUE(MID(TEXT(D19,"000000000000000"),4,1))*53+VALUE(MID(TEXT(D19,"000000000000000"),3,1))*59+VALUE(MID(TEXT(D19,"000000000000000"),2,1))*67+VALUE(MID(TEXT(D19,"000000000000000"),1,1))*71),11))=1,1,11-(MOD((VALUE(MID(TEXT(D19,"000000000000000"),15,1))*3+VALUE(MID(TEXT(D19,"000000000000000"),14,1))*7+VALUE(MID(TEXT(D19,"000000000000000"),13,1))*13+VALUE(MID(TEXT(D19,"000000000000000"),12,1))*17+VALUE(MID(TEXT(D19,"000000000000000"),11,1))*19+VALUE(MID(TEXT(D19,"000000000000000"),10,1))*23+VALUE(MID(TEXT(D19,"000000000000000"),9,1))*29+VALUE(MID(TEXT(D19,"000000000000000"),8,1))*37+VALUE(MID(TEXT(D19,"000000000000000"),7,1))*41+VALUE(MID(TEXT(D19,"000000000000000"),6,1))*43+VALUE(MID(TEXT(D19,"000000000000000"),5,1))*47+VALUE(MID(TEXT(D19,"000000000000000"),4,1))*53+VALUE(MID(TEXT(D19,"000000000000000"),3,1))*59+VALUE(MID(TEXT(D19,"000000000000000"),2,1))*67+VALUE(MID(TEXT(D19,"000000000000000"),1,1))*71),11)))) -> 8 | F19: =+AN19 -> 1790000 | G19: =+F19*$G$5 -> 340100 | H19: NO | I19: =IF(H19="S",-F19*$I$5,"NO RETENCIÓN") -> NO RETENCIÓN | J19: =+F19+G19 -> 2130100 | K19: =SUM(F19:I19) -> 2130100 | M19: GTFF-169 | N19: Correo | O19: 45987 | R19: =+AM19 -> 0 | T19: Fra con -Ma Isabel Restrepo de S | V19: SI | W19: =ROUND(IF(V19="SI",SUMIF('Facturas año anterior'!$B$8:$B$81,B19,'Facturas año anterior'!$V$8:$V$81)*(100%+$W$5),0),-3)+ROUND(IF(V19="SI",SUMIF('C de C año anterior'!$B$8:$B$210,B19,'C de C año anterior'!$Q$8:$Q$210)*(100%+$W$5),0),-3) -> 1410000 | Y19: =ROUND(IF(X19="SI",W19*$Y$5,0),-3) -> 0 | AA19: =ROUND(IF(Z19="SI",W19*$AA$5,0),-3) -> 0 | AC19: =ROUND(IF(AB19="SI",W19*$AC$5,0),-3) -> 0 | AE19: =ROUND(IF(AD19="SI",W19*$AE$5,0),-3) -> 0 | AG19: =ROUND(IF(AF19="SI",W19*$AG$5,0),-3) -> 0 | AI19: =ROUND(IF(AH19="SI",W19*$AI$5,0),-3) -> 0 | AK19: =IF(AJ19="SI",W19*$AK$5,0) -> 0 | AL19: =SUMIF('Otras Asesorías y Préstamos'!$B$7:$B$242,B19,'Otras Asesorías y Préstamos'!$F$7:$F$242) -> 384583 | AM19: =SUMIF('Otras Asesorías y Préstamos'!$B$7:$B$242,B19,'Otras Asesorías y Préstamos'!$V$7:$V$242) -> 0 | AN19: =ROUND(SUM(W19:AL19),-4) -> 1790000
A20: =+A19+1 -> 12 | B20: RESTREPO MEJÍA MARÍA LUISA | C20: =_xlfn.XLOOKUP(B20,Códigos!$B$8:$B$406,Códigos!$A$8:$A$406,"Verificar",0) -> 159 | D20: =_xlfn.XLOOKUP(B20,'Consolidado Cobros'!$B$10:$B$312,'Consolidado Cobros'!$C$10:$C$312,"Verificar",0) -> 87101474230 | E20: =IF((MOD((VALUE(MID(TEXT(D20,"000000000000000"),15,1))*3+VALUE(MID(TEXT(D20,"000000000000000"),14,1))*7+VALUE(MID(TEXT(D20,"000000000000000"),13,1))*13+VALUE(MID(TEXT(D20,"000000000000000"),12,1))*17+VALUE(MID(TEXT(D20,"000000000000000"),11,1))*19+VALUE(MID(TEXT(D20,"000000000000000"),10,1))*23+VALUE(MID(TEXT(D20,"000000000000000"),9,1))*29+VALUE(MID(TEXT(D20,"000000000000000"),8,1))*37+VALUE(MID(TEXT(D20,"000000000000000"),7,1))*41+VALUE(MID(TEXT(D20,"000000000000000"),6,1))*43+VALUE(MID(TEXT(D20,"000000000000000"),5,1))*47+VALUE(MID(TEXT(D20,"000000000000000"),4,1))*53+VALUE(MID(TEXT(D20,"000000000000000"),3,1))*59+VALUE(MID(TEXT(D20,"000000000000000"),2,1))*67+VALUE(MID(TEXT(D20,"000000000000000"),1,1))*71),11))=0,0,IF((MOD((VALUE(MID(TEXT(D20,"000000000000000"),15,1))*3+VALUE(MID(TEXT(D20,"000000000000000"),14,1))*7+VALUE(MID(TEXT(D20,"000000000000000"),13,1))*13+VALUE(MID(TEXT(D20,"000000000000000"),12,1))*17+VALUE(MID(TEXT(D20,"000000000000000"),11,1))*19+VALUE(MID(TEXT(D20,"000000000000000"),10,1))*23+VALUE(MID(TEXT(D20,"000000000000000"),9,1))*29+VALUE(MID(TEXT(D20,"000000000000000"),8,1))*37+VALUE(MID(TEXT(D20,"000000000000000"),7,1))*41+VALUE(MID(TEXT(D20,"000000000000000"),6,1))*43+VALUE(MID(TEXT(D20,"000000000000000"),5,1))*47+VALUE(MID(TEXT(D20,"000000000000000"),4,1))*53+VALUE(MID(TEXT(D20,"000000000000000"),3,1))*59+VALUE(MID(TEXT(D20,"000000000000000"),2,1))*67+VALUE(MID(TEXT(D20,"000000000000000"),1,1))*71),11))=1,1,11-(MOD((VALUE(MID(TEXT(D20,"000000000000000"),15,1))*3+VALUE(MID(TEXT(D20,"000000000000000"),14,1))*7+VALUE(MID(TEXT(D20,"000000000000000"),13,1))*13+VALUE(MID(TEXT(D20,"000000000000000"),12,1))*17+VALUE(MID(TEXT(D20,"000000000000000"),11,1))*19+VALUE(MID(TEXT(D20,"000000000000000"),10,1))*23+VALUE(MID(TEXT(D20,"000000000000000"),9,1))*29+VALUE(MID(TEXT(D20,"000000000000000"),8,1))*37+VALUE(MID(TEXT(D20,"000000000000000"),7,1))*41+VALUE(MID(TEXT(D20,"000000000000000"),6,1))*43+VALUE(MID(TEXT(D20,"000000000000000"),5,1))*47+VALUE(MID(TEXT(D20,"000000000000000"),4,1))*53+VALUE(MID(TEXT(D20,"000000000000000"),3,1))*59+VALUE(MID(TEXT(D20,"000000000000000"),2,1))*67+VALUE(MID(TEXT(D20,"000000000000000"),1,1))*71),11)))) -> 2 | F20: =+AN20 -> 610000 | G20: =+F20*$G$5 -> 115900 | H20: S | I20: =IF(H20="S",-F20*$I$5,"NO RETENCIÓN") -> -67100 | J20: =+F20+G20 -> 725900 | K20: =SUM(F20:I20) -> 658800 | M20: GTFF-166 | N20: Correo y Wpp | O20: 45974 | R20: =+AM20 -> 0 | T20: Fra con -Cortijo | V20: SI | W20: =ROUND(IF(V20="SI",SUMIF('Facturas año anterior'!$B$8:$B$81,B20,'Facturas año anterior'!$V$8:$V$81)*(100%+$W$5),0),-3)+ROUND(IF(V20="SI",SUMIF('C de C año anterior'!$B$8:$B$210,B20,'C de C año anterior'!$Q$8:$Q$210)*(100%+$W$5),0),-3) -> 612000 | Y20: =ROUND(IF(X20="SI",W20*$Y$5,0),-3) -> 0 | AA20: =ROUND(IF(Z20="SI",W20*$AA$5,0),-3) -> 0 | AC20: =ROUND(IF(AB20="SI",W20*$AC$5,0),-3) -> 0 | AE20: =ROUND(IF(AD20="SI",W20*$AE$5,0),-3) -> 0 | AG20: =ROUND(IF(AF20="SI",W20*$AG$5,0),-3) -> 0 | AI20: =ROUND(IF(AH20="SI",W20*$AI$5,0),-3) -> 0 | AK20: =IF(AJ20="SI",W20*$AK$5,0) -> 0 | AL20: =SUMIF('Otras Asesorías y Préstamos'!$B$7:$B$242,B20,'Otras Asesorías y Préstamos'!$F$7:$F$242) -> 0 | AM20: =SUMIF('Otras Asesorías y Préstamos'!$B$7:$B$242,B20,'Otras Asesorías y Préstamos'!$V$7:$V$242) -> 0 | AN20: =ROUND(SUM(W20:AL20),-4) -> 610000
A21: =+A20+1 -> 13 | B21: RESTREPO MEJÍA SEBASTIAN | C21: =_xlfn.XLOOKUP(B21,Códigos!$B$8:$B$406,Códigos!$A$8:$A$406,"Verificar",0) -> 160 | D21: =_xlfn.XLOOKUP(B21,'Consolidado Cobros'!$B$10:$B$312,'Consolidado Cobros'!$C$10:$C$312,"Verificar",0) -> 71368472 | E21: =IF((MOD((VALUE(MID(TEXT(D21,"000000000000000"),15,1))*3+VALUE(MID(TEXT(D21,"000000000000000"),14,1))*7+VALUE(MID(TEXT(D21,"000000000000000"),13,1))*13+VALUE(MID(TEXT(D21,"000000000000000"),12,1))*17+VALUE(MID(TEXT(D21,"000000000000000"),11,1))*19+VALUE(MID(TEXT(D21,"000000000000000"),10,1))*23+VALUE(MID(TEXT(D21,"000000000000000"),9,1))*29+VALUE(MID(TEXT(D21,"000000000000000"),8,1))*37+VALUE(MID(TEXT(D21,"000000000000000"),7,1))*41+VALUE(MID(TEXT(D21,"000000000000000"),6,1))*43+VALUE(MID(TEXT(D21,"000000000000000"),5,1))*47+VALUE(MID(TEXT(D21,"000000000000000"),4,1))*53+VALUE(MID(TEXT(D21,"000000000000000"),3,1))*59+VALUE(MID(TEXT(D21,"000000000000000"),2,1))*67+VALUE(MID(TEXT(D21,"000000000000000"),1,1))*71),11))=0,0,IF((MOD((VALUE(MID(TEXT(D21,"000000000000000"),15,1))*3+VALUE(MID(TEXT(D21,"000000000000000"),14,1))*7+VALUE(MID(TEXT(D21,"000000000000000"),13,1))*13+VALUE(MID(TEXT(D21,"000000000000000"),12,1))*17+VALUE(MID(TEXT(D21,"000000000000000"),11,1))*19+VALUE(MID(TEXT(D21,"000000000000000"),10,1))*23+VALUE(MID(TEXT(D21,"000000000000000"),9,1))*29+VALUE(MID(TEXT(D21,"000000000000000"),8,1))*37+VALUE(MID(TEXT(D21,"000000000000000"),7,1))*41+VALUE(MID(TEXT(D21,"000000000000000"),6,1))*43+VALUE(MID(TEXT(D21,"000000000000000"),5,1))*47+VALUE(MID(TEXT(D21,"000000000000000"),4,1))*53+VALUE(MID(TEXT(D21,"000000000000000"),3,1))*59+VALUE(MID(TEXT(D21,"000000000000000"),2,1))*67+VALUE(MID(TEXT(D21,"000000000000000"),1,1))*71),11))=1,1,11-(MOD((VALUE(MID(TEXT(D21,"000000000000000"),15,1))*3+VALUE(MID(TEXT(D21,"000000000000000"),14,1))*7+VALUE(MID(TEXT(D21,"000000000000000"),13,1))*13+VALUE(MID(TEXT(D21,"000000000000000"),12,1))*17+VALUE(MID(TEXT(D21,"000000000000000"),11,1))*19+VALUE(MID(TEXT(D21,"000000000000000"),10,1))*23+VALUE(MID(TEXT(D21,"000000000000000"),9,1))*29+VALUE(MID(TEXT(D21,"000000000000000"),8,1))*37+VALUE(MID(TEXT(D21,"000000000000000"),7,1))*41+VALUE(MID(TEXT(D21,"000000000000000"),6,1))*43+VALUE(MID(TEXT(D21,"000000000000000"),5,1))*47+VALUE(MID(TEXT(D21,"000000000000000"),4,1))*53+VALUE(MID(TEXT(D21,"000000000000000"),3,1))*59+VALUE(MID(TEXT(D21,"000000000000000"),2,1))*67+VALUE(MID(TEXT(D21,"000000000000000"),1,1))*71),11)))) -> 1 | F21: =+AN21 -> 1280000 | G21: =+F21*$G$5 -> 243200 | H21: S | I21: =IF(H21="S",-F21*$I$5,"NO RETENCIÓN") -> -140800 | J21: =+F21+G21 -> 1523200 | K21: =SUM(F21:I21) -> 1382400 | M21: GTFF-166 | N21: Correo y Wpp | O21: 45974 | R21: =+AM21 -> 0 | T21: Fra con -Cortijo | V21: SI | W21: =ROUND(IF(V21="SI",SUMIF('Facturas año anterior'!$B$8:$B$81,B21,'Facturas año anterior'!$V$8:$V$81)*(100%+$W$5),0),-3)+ROUND(IF(V21="SI",SUMIF('C de C año anterior'!$B$8:$B$210,B21,'C de C año anterior'!$Q$8:$Q$210)*(100%+$W$5),0),-3) -> 987000 | Y21: =ROUND(IF(X21="SI",W21*$Y$5,0),-3) -> 0 | AA21: =ROUND(IF(Z21="SI",W21*$AA$5,0),-3) -> 0 | AC21: =ROUND(IF(AB21="SI",W21*$AC$5,0),-3) -> 0 | AE21: =ROUND(IF(AD21="SI",W21*$AE$5,0),-3) -> 0 | AG21: =ROUND(IF(AF21="SI",W21*$AG$5,0),-3) -> 0 | AI21: =ROUND(IF(AH21="SI",W21*$AI$5,0),-3) -> 0 | AJ21: SI | AK21: =IF(AJ21="SI",W21*$AK$5,0) -> 296100 | AL21: =SUMIF('Otras Asesorías y Préstamos'!$B$7:$B$242,B21,'Otras Asesorías y Préstamos'!$F$7:$F$242) -> 0 | AM21: =SUMIF('Otras Asesorías y Préstamos'!$B$7:$B$242,B21,'Otras Asesorías y Préstamos'!$V$7:$V$242) -> 0 | AN21: =ROUND(SUM(W21:AL21),-4) -> 1280000
A22: =+A21+1 -> 14 | B22: RESTREPO POSADA CLARA INÉS | C22: =_xlfn.XLOOKUP(B22,Códigos!$B$8:$B$406,Códigos!$A$8:$A$406,"Verificar",0) -> 165 | D22: =_xlfn.XLOOKUP(B22,'Consolidado Cobros'!$B$10:$B$312,'Consolidado Cobros'!$C$10:$C$312,"Verificar",0) -> 32404117 | E22: =IF((MOD((VALUE(MID(TEXT(D22,"000000000000000"),15,1))*3+VALUE(MID(TEXT(D22,"000000000000000"),14,1))*7+VALUE(MID(TEXT(D22,"000000000000000"),13,1))*13+VALUE(MID(TEXT(D22,"000000000000000"),12,1))*17+VALUE(MID(TEXT(D22,"000000000000000"),11,1))*19+VALUE(MID(TEXT(D22,"000000000000000"),10,1))*23+VALUE(MID(TEXT(D22,"000000000000000"),9,1))*29+VALUE(MID(TEXT(D22,"000000000000000"),8,1))*37+VALUE(MID(TEXT(D22,"000000000000000"),7,1))*41+VALUE(MID(TEXT(D22,"000000000000000"),6,1))*43+VALUE(MID(TEXT(D22,"000000000000000"),5,1))*47+VALUE(MID(TEXT(D22,"000000000000000"),4,1))*53+VALUE(MID(TEXT(D22,"000000000000000"),3,1))*59+VALUE(MID(TEXT(D22,"000000000000000"),2,1))*67+VALUE(MID(TEXT(D22,"000000000000000"),1,1))*71),11))=0,0,IF((MOD((VALUE(MID(TEXT(D22,"000000000000000"),15,1))*3+VALUE(MID(TEXT(D22,"000000000000000"),14,1))*7+VALUE(MID(TEXT(D22,"000000000000000"),13,1))*13+VALUE(MID(TEXT(D22,"000000000000000"),12,1))*17+VALUE(MID(TEXT(D22,"000000000000000"),11,1))*19+VALUE(MID(TEXT(D22,"000000000000000"),10,1))*23+VALUE(MID(TEXT(D22,"000000000000000"),9,1))*29+VALUE(MID(TEXT(D22,"000000000000000"),8,1))*37+VALUE(MID(TEXT(D22,"000000000000000"),7,1))*41+VALUE(MID(TEXT(D22,"000000000000000"),6,1))*43+VALUE(MID(TEXT(D22,"000000000000000"),5,1))*47+VALUE(MID(TEXT(D22,"000000000000000"),4,1))*53+VALUE(MID(TEXT(D22,"000000000000000"),3,1))*59+VALUE(MID(TEXT(D22,"000000000000000"),2,1))*67+VALUE(MID(TEXT(D22,"000000000000000"),1,1))*71),11))=1,1,11-(MOD((VALUE(MID(TEXT(D22,"000000000000000"),15,1))*3+VALUE(MID(TEXT(D22,"000000000000000"),14,1))*7+VALUE(MID(TEXT(D22,"000000000000000"),13,1))*13+VALUE(MID(TEXT(D22,"000000000000000"),12,1))*17+VALUE(MID(TEXT(D22,"000000000000000"),11,1))*19+VALUE(MID(TEXT(D22,"000000000000000"),10,1))*23+VALUE(MID(TEXT(D22,"000000000000000"),9,1))*29+VALUE(MID(TEXT(D22,"000000000000000"),8,1))*37+VALUE(MID(TEXT(D22,"000000000000000"),7,1))*41+VALUE(MID(TEXT(D22,"000000000000000"),6,1))*43+VALUE(MID(TEXT(D22,"000000000000000"),5,1))*47+VALUE(MID(TEXT(D22,"000000000000000"),4,1))*53+VALUE(MID(TEXT(D22,"000000000000000"),3,1))*59+VALUE(MID(TEXT(D22,"000000000000000"),2,1))*67+VALUE(MID(TEXT(D22,"000000000000000"),1,1))*71),11)))) -> 4 | F22: =+AN22 -> 1830000 | G22: =+F22*$G$5 -> 347700 | H22: S | I22: =IF(H22="S",-F22*$I$5,"NO RETENCIÓN") -> -201300 | J22: =+F22+G22 -> 2177700 | K22: =SUM(F22:I22) -> 1976400 | M22: GTFF-174 | N22: Correo | O22: 45987 | R22: =+AM22 -> 0 | T22: Fra con -Cirpul | V22: SI | W22: =ROUND(IF(V22="SI",SUMIF('Facturas año anterior'!$B$8:$B$81,B22,'Facturas año anterior'!$V$8:$V$81)*(100%+$W$5),0),-3)+ROUND(IF(V22="SI",SUMIF('C de C año anterior'!$B$8:$B$210,B22,'C de C año anterior'!$Q$8:$Q$210)*(100%+$W$5),0),-3) -> 1410000 | Y22: =ROUND(IF(X22="SI",W22*$Y$5,0),-3) -> 0 | AA22: =ROUND(IF(Z22="SI",W22*$AA$5,0),-3) -> 0 | AC22: =ROUND(IF(AB22="SI",W22*$AC$5,0),-3) -> 0 | AE22: =ROUND(IF(AD22="SI",W22*$AE$5,0),-3) -> 0 | AG22: =ROUND(IF(AF22="SI",W22*$AG$5,0),-3) -> 0 | AI22: =ROUND(IF(AH22="SI",W22*$AI$5,0),-3) -> 0 | AJ22: SI | AK22: =IF(AJ22="SI",W22*$AK$5,0) -> 423000 | AL22: =SUMIF('Otras Asesorías y Préstamos'!$B$7:$B$242,B22,'Otras Asesorías y Préstamos'!$F$7:$F$242) -> 0 | AM22: =SUMIF('Otras Asesorías y Préstamos'!$B$7:$B$242,B22,'Otras Asesorías y Préstamos'!$V$7:$V$242) -> 0 | AN22: =ROUND(SUM(W22:AL22),-4) -> 1830000
A23: =+A22+1 -> 15 | B23: RESTREPO POSADA EMILIO ANTONIO | C23: =_xlfn.XLOOKUP(B23,Códigos!$B$8:$B$406,Códigos!$A$8:$A$406,"Verificar",0) -> 166 | D23: =_xlfn.XLOOKUP(B23,'Consolidado Cobros'!$B$10:$B$312,'Consolidado Cobros'!$C$10:$C$312,"Verificar",0) -> 8248980 | E23: =IF((MOD((VALUE(MID(TEXT(D23,"000000000000000"),15,1))*3+VALUE(MID(TEXT(D23,"000000000000000"),14,1))*7+VALUE(MID(TEXT(D23,"000000000000000"),13,1))*13+VALUE(MID(TEXT(D23,"000000000000000"),12,1))*17+VALUE(MID(TEXT(D23,"000000000000000"),11,1))*19+VALUE(MID(TEXT(D23,"000000000000000"),10,1))*23+VALUE(MID(TEXT(D23,"000000000000000"),9,1))*29+VALUE(MID(TEXT(D23,"000000000000000"),8,1))*37+VALUE(MID(TEXT(D23,"000000000000000"),7,1))*41+VALUE(MID(TEXT(D23,"000000000000000"),6,1))*43+VALUE(MID(TEXT(D23,"000000000000000"),5,1))*47+VALUE(MID(TEXT(D23,"000000000000000"),4,1))*53+VALUE(MID(TEXT(D23,"000000000000000"),3,1))*59+VALUE(MID(TEXT(D23,"000000000000000"),2,1))*67+VALUE(MID(TEXT(D23,"000000000000000"),1,1))*71),11))=0,0,IF((MOD((VALUE(MID(TEXT(D23,"000000000000000"),15,1))*3+VALUE(MID(TEXT(D23,"000000000000000"),14,1))*7+VALUE(MID(TEXT(D23,"000000000000000"),13,1))*13+VALUE(MID(TEXT(D23,"000000000000000"),12,1))*17+VALUE(MID(TEXT(D23,"000000000000000"),11,1))*19+VALUE(MID(TEXT(D23,"000000000000000"),10,1))*23+VALUE(MID(TEXT(D23,"000000000000000"),9,1))*29+VALUE(MID(TEXT(D23,"000000000000000"),8,1))*37+VALUE(MID(TEXT(D23,"000000000000000"),7,1))*41+VALUE(MID(TEXT(D23,"000000000000000"),6,1))*43+VALUE(MID(TEXT(D23,"000000000000000"),5,1))*47+VALUE(MID(TEXT(D23,"000000000000000"),4,1))*53+VALUE(MID(TEXT(D23,"000000000000000"),3,1))*59+VALUE(MID(TEXT(D23,"000000000000000"),2,1))*67+VALUE(MID(TEXT(D23,"000000000000000"),1,1))*71),11))=1,1,11-(MOD((VALUE(MID(TEXT(D23,"000000000000000"),15,1))*3+VALUE(MID(TEXT(D23,"000000000000000"),14,1))*7+VALUE(MID(TEXT(D23,"000000000000000"),13,1))*13+VALUE(MID(TEXT(D23,"000000000000000"),12,1))*17+VALUE(MID(TEXT(D23,"000000000000000"),11,1))*19+VALUE(MID(TEXT(D23,"000000000000000"),10,1))*23+VALUE(MID(TEXT(D23,"000000000000000"),9,1))*29+VALUE(MID(TEXT(D23,"000000000000000"),8,1))*37+VALUE(MID(TEXT(D23,"000000000000000"),7,1))*41+VALUE(MID(TEXT(D23,"000000000000000"),6,1))*43+VALUE(MID(TEXT(D23,"000000000000000"),5,1))*47+VALUE(MID(TEXT(D23,"000000000000000"),4,1))*53+VALUE(MID(TEXT(D23,"000000000000000"),3,1))*59+VALUE(MID(TEXT(D23,"000000000000000"),2,1))*67+VALUE(MID(TEXT(D23,"000000000000000"),1,1))*71),11)))) -> 8 | F23: =+AN23 -> 2430000 | G23: =+F23*$G$5 -> 461700 | H23: S | I23: =IF(H23="S",-F23*$I$5,"NO RETENCIÓN") -> -267300 | J23: =+F23+G23 -> 2891700 | K23: =SUM(F23:I23) -> 2624400 | M23: GTFF-175 | N23: Correo | O23: 45987 | R23: =+AM23 -> 0 | T23: Fra con -San Antonio de la Almería | V23: SI | W23: =ROUND(IF(V23="SI",SUMIF('Facturas año anterior'!$B$8:$B$81,B23,'Facturas año anterior'!$V$8:$V$81)*(100%+$W$5),0),-3)+ROUND(IF(V23="SI",SUMIF('C de C año anterior'!$B$8:$B$210,B23,'C de C año anterior'!$Q$8:$Q$210)*(100%+$W$5),0),-3) -> 1410000 | Y23: =ROUND(IF(X23="SI",W23*$Y$5,0),-3) -> 0 | AA23: =ROUND(IF(Z23="SI",W23*$AA$5,0),-3) -> 0 | AC23: =ROUND(IF(AB23="SI",W23*$AC$5,0),-3) -> 0 | AE23: =ROUND(IF(AD23="SI",W23*$AE$5,0),-3) -> 0 | AG23: =ROUND(IF(AF23="SI",W23*$AG$5,0),-3) -> 0 | AI23: =ROUND(IF(AH23="SI",W23*$AI$5,0),-3) -> 0 | AJ23: SI | AK23: =IF(AJ23="SI",W23*$AK$5,0) -> 423000 | AL23: =SUMIF('Otras Asesorías y Préstamos'!$B$7:$B$242,B23,'Otras Asesorías y Préstamos'!$F$7:$F$242) -> 600000 | AM23: =SUMIF('Otras Asesorías y Préstamos'!$B$7:$B$242,B23,'Otras Asesorías y Préstamos'!$V$7:$V$242) -> 0 | AN23: =ROUND(SUM(W23:AL23),-4) -> 2430000
A24: =+A23+1 -> 16 | B24: RESTREPO POSADA JUAN JOSÉ | C24: =_xlfn.XLOOKUP(B24,Códigos!$B$8:$B$406,Códigos!$A$8:$A$406,"Verificar",0) -> 167 | D24: =_xlfn.XLOOKUP(B24,'Consolidado Cobros'!$B$10:$B$312,'Consolidado Cobros'!$C$10:$C$312,"Verificar",0) -> 8290656 | E24: =IF((MOD((VALUE(MID(TEXT(D24,"000000000000000"),15,1))*3+VALUE(MID(TEXT(D24,"000000000000000"),14,1))*7+VALUE(MID(TEXT(D24,"000000000000000"),13,1))*13+VALUE(MID(TEXT(D24,"000000000000000"),12,1))*17+VALUE(MID(TEXT(D24,"000000000000000"),11,1))*19+VALUE(MID(TEXT(D24,"000000000000000"),10,1))*23+VALUE(MID(TEXT(D24,"000000000000000"),9,1))*29+VALUE(MID(TEXT(D24,"000000000000000"),8,1))*37+VALUE(MID(TEXT(D24,"000000000000000"),7,1))*41+VALUE(MID(TEXT(D24,"000000000000000"),6,1))*43+VALUE(MID(TEXT(D24,"000000000000000"),5,1))*47+VALUE(MID(TEXT(D24,"000000000000000"),4,1))*53+VALUE(MID(TEXT(D24,"000000000000000"),3,1))*59+VALUE(MID(TEXT(D24,"000000000000000"),2,1))*67+VALUE(MID(TEXT(D24,"000000000000000"),1,1))*71),11))=0,0,IF((MOD((VALUE(MID(TEXT(D24,"000000000000000"),15,1))*3+VALUE(MID(TEXT(D24,"000000000000000"),14,1))*7+VALUE(MID(TEXT(D24,"000000000000000"),13,1))*13+VALUE(MID(TEXT(D24,"000000000000000"),12,1))*17+VALUE(MID(TEXT(D24,"000000000000000"),11,1))*19+VALUE(MID(TEXT(D24,"000000000000000"),10,1))*23+VALUE(MID(TEXT(D24,"000000000000000"),9,1))*29+VALUE(MID(TEXT(D24,"000000000000000"),8,1))*37+VALUE(MID(TEXT(D24,"000000000000000"),7,1))*41+VALUE(MID(TEXT(D24,"000000000000000"),6,1))*43+VALUE(MID(TEXT(D24,"000000000000000"),5,1))*47+VALUE(MID(TEXT(D24,"000000000000000"),4,1))*53+VALUE(MID(TEXT(D24,"000000000000000"),3,1))*59+VALUE(MID(TEXT(D24,"000000000000000"),2,1))*67+VALUE(MID(TEXT(D24,"000000000000000"),1,1))*71),11))=1,1,11-(MOD((VALUE(MID(TEXT(D24,"000000000000000"),15,1))*3+VALUE(MID(TEXT(D24,"000000000000000"),14,1))*7+VALUE(MID(TEXT(D24,"000000000000000"),13,1))*13+VALUE(MID(TEXT(D24,"000000000000000"),12,1))*17+VALUE(MID(TEXT(D24,"000000000000000"),11,1))*19+VALUE(MID(TEXT(D24,"000000000000000"),10,1))*23+VALUE(MID(TEXT(D24,"000000000000000"),9,1))*29+VALUE(MID(TEXT(D24,"000000000000000"),8,1))*37+VALUE(MID(TEXT(D24,"000000000000000"),7,1))*41+VALUE(MID(TEXT(D24,"000000000000000"),6,1))*43+VALUE(MID(TEXT(D24,"000000000000000"),5,1))*47+VALUE(MID(TEXT(D24,"000000000000000"),4,1))*53+VALUE(MID(TEXT(D24,"000000000000000"),3,1))*59+VALUE(MID(TEXT(D24,"000000000000000"),2,1))*67+VALUE(MID(TEXT(D24,"000000000000000"),1,1))*71),11)))) -> 3 | F24: =+AN24 -> 1410000 | G24: =+F24*$G$5 -> 267900 | H24: S | I24: =IF(H24="S",-F24*$I$5,"NO RETENCIÓN") -> -155100 | J24: =+F24+G24 -> 1677900 | K24: =SUM(F24:I24) -> 1522800 | M24: GTFF-166 | N24: Correo y Wpp | O24: 45974 | R24: =+AM24 -> 0 | T24: Fra con -Cortijo | V24: SI | W24: =ROUND(IF(V24="SI",SUMIF('Facturas año anterior'!$B$8:$B$81,B24,'Facturas año anterior'!$V$8:$V$81)*(100%+$W$5),0),-3)+ROUND(IF(V24="SI",SUMIF('C de C año anterior'!$B$8:$B$210,B24,'C de C año anterior'!$Q$8:$Q$210)*(100%+$W$5),0),-3) -> 1410000 | Y24: =ROUND(IF(X24="SI",W24*$Y$5,0),-3) -> 0 | AA24: =ROUND(IF(Z24="SI",W24*$AA$5,0),-3) -> 0 | AC24: =ROUND(IF(AB24="SI",W24*$AC$5,0),-3) -> 0 | AE24: =ROUND(IF(AD24="SI",W24*$AE$5,0),-3) -> 0 | AG24: =ROUND(IF(AF24="SI",W24*$AG$5,0),-3) -> 0 | AI24: =ROUND(IF(AH24="SI",W24*$AI$5,0),-3) -> 0 | AK24: =IF(AJ24="SI",W24*$AK$5,0) -> 0 | AL24: =SUMIF('Otras Asesorías y Préstamos'!$B$7:$B$242,B24,'Otras Asesorías y Préstamos'!$F$7:$F$242) -> 0 | AM24: =SUMIF('Otras Asesorías y Préstamos'!$B$7:$B$242,B24,'Otras Asesorías y Préstamos'!$V$7:$V$242) -> 0 | AN24: =ROUND(SUM(W24:AL24),-4) -> 1410000
A25: =+A24+1 -> 17 | B25: RESTREPO POSADA SILVIA ELENA | C25: =_xlfn.XLOOKUP(B25,Códigos!$B$8:$B$406,Códigos!$A$8:$A$406,"Verificar",0) -> 168 | D25: =_xlfn.XLOOKUP(B25,'Consolidado Cobros'!$B$10:$B$312,'Consolidado Cobros'!$C$10:$C$312,"Verificar",0) -> 32524963 | E25: =IF((MOD((VALUE(MID(TEXT(D25,"000000000000000"),15,1))*3+VALUE(MID(TEXT(D25,"000000000000000"),14,1))*7+VALUE(MID(TEXT(D25,"000000000000000"),13,1))*13+VALUE(MID(TEXT(D25,"000000000000000"),12,1))*17+VALUE(MID(TEXT(D25,"000000000000000"),11,1))*19+VALUE(MID(TEXT(D25,"000000000000000"),10,1))*23+VALUE(MID(TEXT(D25,"000000000000000"),9,1))*29+VALUE(MID(TEXT(D25,"000000000000000"),8,1))*37+VALUE(MID(TEXT(D25,"000000000000000"),7,1))*41+VALUE(MID(TEXT(D25,"000000000000000"),6,1))*43+VALUE(MID(TEXT(D25,"000000000000000"),5,1))*47+VALUE(MID(TEXT(D25,"000000000000000"),4,1))*53+VALUE(MID(TEXT(D25,"000000000000000"),3,1))*59+VALUE(MID(TEXT(D25,"000000000000000"),2,1))*67+VALUE(MID(TEXT(D25,"000000000000000"),1,1))*71),11))=0,0,IF((MOD((VALUE(MID(TEXT(D25,"000000000000000"),15,1))*3+VALUE(MID(TEXT(D25,"000000000000000"),14,1))*7+VALUE(MID(TEXT(D25,"000000000000000"),13,1))*13+VALUE(MID(TEXT(D25,"000000000000000"),12,1))*17+VALUE(MID(TEXT(D25,"000000000000000"),11,1))*19+VALUE(MID(TEXT(D25,"000000000000000"),10,1))*23+VALUE(MID(TEXT(D25,"000000000000000"),9,1))*29+VALUE(MID(TEXT(D25,"000000000000000"),8,1))*37+VALUE(MID(TEXT(D25,"000000000000000"),7,1))*41+VALUE(MID(TEXT(D25,"000000000000000"),6,1))*43+VALUE(MID(TEXT(D25,"000000000000000"),5,1))*47+VALUE(MID(TEXT(D25,"000000000000000"),4,1))*53+VALUE(MID(TEXT(D25,"000000000000000"),3,1))*59+VALUE(MID(TEXT(D25,"000000000000000"),2,1))*67+VALUE(MID(TEXT(D25,"000000000000000"),1,1))*71),11))=1,1,11-(MOD((VALUE(MID(TEXT(D25,"000000000000000"),15,1))*3+VALUE(MID(TEXT(D25,"000000000000000"),14,1))*7+VALUE(MID(TEXT(D25,"000000000000000"),13,1))*13+VALUE(MID(TEXT(D25,"000000000000000"),12,1))*17+VALUE(MID(TEXT(D25,"000000000000000"),11,1))*19+VALUE(MID(TEXT(D25,"000000000000000"),10,1))*23+VALUE(MID(TEXT(D25,"000000000000000"),9,1))*29+VALUE(MID(TEXT(D25,"000000000000000"),8,1))*37+VALUE(MID(TEXT(D25,"000000000000000"),7,1))*41+VALUE(MID(TEXT(D25,"000000000000000"),6,1))*43+VALUE(MID(TEXT(D25,"000000000000000"),5,1))*47+VALUE(MID(TEXT(D25,"000000000000000"),4,1))*53+VALUE(MID(TEXT(D25,"000000000000000"),3,1))*59+VALUE(MID(TEXT(D25,"000000000000000"),2,1))*67+VALUE(MID(TEXT(D25,"000000000000000"),1,1))*71),11)))) -> 3 | F25: =+AN25 -> 2530000 | G25: =+F25*$G$5 -> 480700 | H25: NO | I25: =IF(H25="S",-F25*$I$5,"NO RETENCIÓN") -> NO RETENCIÓN | J25: =+F25+G25 -> 3010700 | K25: =SUM(F25:I25) -> 3010700 | M25: GTFF-171 | N25: Correo | O25: 45987 | R25: =+AM25 -> 0 | T25: RESTREPO POSADA SILVIA ELENA | V25: SI | W25: =ROUND(IF(V25="SI",SUMIF('Facturas año anterior'!$B$8:$B$81,B25,'Facturas año anterior'!$V$8:$V$81)*(100%+$W$5),0),-3)+ROUND(IF(V25="SI",SUMIF('C de C año anterior'!$B$8:$B$210,B25,'C de C año anterior'!$Q$8:$Q$210)*(100%+$W$5),0),-3) -> 1410000 | Y25: =ROUND(IF(X25="SI",W25*$Y$5,0),-3) -> 0 | AA25: =ROUND(IF(Z25="SI",W25*$AA$5,0),-3) -> 0 | AC25: =ROUND(IF(AB25="SI",W25*$AC$5,0),-3) -> 0 | AE25: =ROUND(IF(AD25="SI",W25*$AE$5,0),-3) -> 0 | AG25: =ROUND(IF(AF25="SI",W25*$AG$5,0),-3) -> 0 | AI25: =ROUND(IF(AH25="SI",W25*$AI$5,0),-3) -> 0 | AJ25: SI | AK25: =IF(AJ25="SI",W25*$AK$5,0) -> 423000 | AL25: =SUMIF('Otras Asesorías y Préstamos'!$B$7:$B$242,B25,'Otras Asesorías y Préstamos'!$F$7:$F$242) -> 696501.15 | AM25: =SUMIF('Otras Asesorías y Préstamos'!$B$7:$B$242,B25,'Otras Asesorías y Préstamos'!$V$7:$V$242) -> 0 | AN25: =ROUND(SUM(W25:AL25),-4) -> 2530000
A26: =+A25+1 -> 18 | B26: RÍOS FRANCISCO JAVIER | C26: =_xlfn.XLOOKUP(B26,Códigos!$B$8:$B$406,Códigos!$A$8:$A$406,"Verificar",0) -> 169 | D26: =_xlfn.XLOOKUP(B26,'Consolidado Cobros'!$B$10:$B$312,'Consolidado Cobros'!$C$10:$C$312,"Verificar",0) -> 675024 | E26: =IF((MOD((VALUE(MID(TEXT(D26,"000000000000000"),15,1))*3+VALUE(MID(TEXT(D26,"000000000000000"),14,1))*7+VALUE(MID(TEXT(D26,"000000000000000"),13,1))*13+VALUE(MID(TEXT(D26,"000000000000000"),12,1))*17+VALUE(MID(TEXT(D26,"000000000000000"),11,1))*19+VALUE(MID(TEXT(D26,"000000000000000"),10,1))*23+VALUE(MID(TEXT(D26,"000000000000000"),9,1))*29+VALUE(MID(TEXT(D26,"000000000000000"),8,1))*37+VALUE(MID(TEXT(D26,"000000000000000"),7,1))*41+VALUE(MID(TEXT(D26,"000000000000000"),6,1))*43+VALUE(MID(TEXT(D26,"000000000000000"),5,1))*47+VALUE(MID(TEXT(D26,"000000000000000"),4,1))*53+VALUE(MID(TEXT(D26,"000000000000000"),3,1))*59+VALUE(MID(TEXT(D26,"000000000000000"),2,1))*67+VALUE(MID(TEXT(D26,"000000000000000"),1,1))*71),11))=0,0,IF((MOD((VALUE(MID(TEXT(D26,"000000000000000"),15,1))*3+VALUE(MID(TEXT(D26,"000000000000000"),14,1))*7+VALUE(MID(TEXT(D26,"000000000000000"),13,1))*13+VALUE(MID(TEXT(D26,"000000000000000"),12,1))*17+VALUE(MID(TEXT(D26,"000000000000000"),11,1))*19+VALUE(MID(TEXT(D26,"000000000000000"),10,1))*23+VALUE(MID(TEXT(D26,"000000000000000"),9,1))*29+VALUE(MID(TEXT(D26,"000000000000000"),8,1))*37+VALUE(MID(TEXT(D26,"000000000000000"),7,1))*41+VALUE(MID(TEXT(D26,"000000000000000"),6,1))*43+VALUE(MID(TEXT(D26,"000000000000000"),5,1))*47+VALUE(MID(TEXT(D26,"000000000000000"),4,1))*53+VALUE(MID(TEXT(D26,"000000000000000"),3,1))*59+VALUE(MID(TEXT(D26,"000000000000000"),2,1))*67+VALUE(MID(TEXT(D26,"000000000000000"),1,1))*71),11))=1,1,11-(MOD((VALUE(MID(TEXT(D26,"000000000000000"),15,1))*3+VALUE(MID(TEXT(D26,"000000000000000"),14,1))*7+VALUE(MID(TEXT(D26,"000000000000000"),13,1))*13+VALUE(MID(TEXT(D26,"000000000000000"),12,1))*17+VALUE(MID(TEXT(D26,"000000000000000"),11,1))*19+VALUE(MID(TEXT(D26,"000000000000000"),10,1))*23+VALUE(MID(TEXT(D26,"000000000000000"),9,1))*29+VALUE(MID(TEXT(D26,"000000000000000"),8,1))*37+VALUE(MID(TEXT(D26,"000000000000000"),7,1))*41+VALUE(MID(TEXT(D26,"000000000000000"),6,1))*43+VALUE(MID(TEXT(D26,"000000000000000"),5,1))*47+VALUE(MID(TEXT(D26,"000000000000000"),4,1))*53+VALUE(MID(TEXT(D26,"000000000000000"),3,1))*59+VALUE(MID(TEXT(D26,"000000000000000"),2,1))*67+VALUE(MID(TEXT(D26,"000000000000000"),1,1))*71),11)))) -> 3 | F26: =+AN26 -> 990000 | G26: =+F26*$G$5 -> 188100 | H26: S | I26: =IF(H26="S",-F26*$I$5,"NO RETENCIÓN") -> -108900 | J26: =+F26+G26 -> 1178100 | K26: =SUM(F26:I26) -> 1069200 | N26: ES CXC | R26: =+AM26 -> 0 | T26: Se hace cuenta de cobro | V26: SI | W26: =ROUND(IF(V26="SI",SUMIF('Facturas año anterior'!$B$8:$B$81,B26,'Facturas año anterior'!$V$8:$V$81)*(100%+$W$5),0),-3)+ROUND(IF(V26="SI",SUMIF('C de C año anterior'!$B$8:$B$210,B26,'C de C año anterior'!$Q$8:$Q$210)*(100%+$W$5),0),-3) -> 994000 | Y26: =ROUND(IF(X26="SI",W26*$Y$5,0),-3) -> 0 | AA26: =ROUND(IF(Z26="SI",W26*$AA$5,0),-3) -> 0 | AC26: =ROUND(IF(AB26="SI",W26*$AC$5,0),-3) -> 0 | AE26: =ROUND(IF(AD26="SI",W26*$AE$5,0),-3) -> 0 | AG26: =ROUND(IF(AF26="SI",W26*$AG$5,0),-3) -> 0 | AI26: =ROUND(IF(AH26="SI",W26*$AI$5,0),-3) -> 0 | AK26: =IF(AJ26="SI",W26*$AK$5,0) -> 0 | AL26: =SUMIF('Otras Asesorías y Préstamos'!$B$7:$B$242,B26,'Otras Asesorías y Préstamos'!$F$7:$F$242) -> 0 | AM26: =SUMIF('Otras Asesorías y Préstamos'!$B$7:$B$242,B26,'Otras Asesorías y Préstamos'!$V$7:$V$242) -> 0 | AN26: =ROUND(SUM(W26:AL26),-4) -> 990000
A27: =+A26+1 -> 19 | B27: RUIZ ARBOLEDA ELIZABETH | C27: =_xlfn.XLOOKUP(B27,Códigos!$B$8:$B$406,Códigos!$A$8:$A$406,"Verificar",0) -> 107 | D27: =_xlfn.XLOOKUP(B27,'Consolidado Cobros'!$B$10:$B$312,'Consolidado Cobros'!$C$10:$C$312,"Verificar",0) -> 1152437125 | E27: =IF((MOD((VALUE(MID(TEXT(D27,"000000000000000"),15,1))*3+VALUE(MID(TEXT(D27,"000000000000000"),14,1))*7+VALUE(MID(TEXT(D27,"000000000000000"),13,1))*13+VALUE(MID(TEXT(D27,"000000000000000"),12,1))*17+VALUE(MID(TEXT(D27,"000000000000000"),11,1))*19+VALUE(MID(TEXT(D27,"000000000000000"),10,1))*23+VALUE(MID(TEXT(D27,"000000000000000"),9,1))*29+VALUE(MID(TEXT(D27,"000000000000000"),8,1))*37+VALUE(MID(TEXT(D27,"000000000000000"),7,1))*41+VALUE(MID(TEXT(D27,"000000000000000"),6,1))*43+VALUE(MID(TEXT(D27,"000000000000000"),5,1))*47+VALUE(MID(TEXT(D27,"000000000000000"),4,1))*53+VALUE(MID(TEXT(D27,"000000000000000"),3,1))*59+VALUE(MID(TEXT(D27,"000000000000000"),2,1))*67+VALUE(MID(TEXT(D27,"000000000000000"),1,1))*71),11))=0,0,IF((MOD((VALUE(MID(TEXT(D27,"000000000000000"),15,1))*3+VALUE(MID(TEXT(D27,"000000000000000"),14,1))*7+VALUE(MID(TEXT(D27,"000000000000000"),13,1))*13+VALUE(MID(TEXT(D27,"000000000000000"),12,1))*17+VALUE(MID(TEXT(D27,"000000000000000"),11,1))*19+VALUE(MID(TEXT(D27,"000000000000000"),10,1))*23+VALUE(MID(TEXT(D27,"000000000000000"),9,1))*29+VALUE(MID(TEXT(D27,"000000000000000"),8,1))*37+VALUE(MID(TEXT(D27,"000000000000000"),7,1))*41+VALUE(MID(TEXT(D27,"000000000000000"),6,1))*43+VALUE(MID(TEXT(D27,"000000000000000"),5,1))*47+VALUE(MID(TEXT(D27,"000000000000000"),4,1))*53+VALUE(MID(TEXT(D27,"000000000000000"),3,1))*59+VALUE(MID(TEXT(D27,"000000000000000"),2,1))*67+VALUE(MID(TEXT(D27,"000000000000000"),1,1))*71),11))=1,1,11-(MOD((VALUE(MID(TEXT(D27,"000000000000000"),15,1))*3+VALUE(MID(TEXT(D27,"000000000000000"),14,1))*7+VALUE(MID(TEXT(D27,"000000000000000"),13,1))*13+VALUE(MID(TEXT(D27,"000000000000000"),12,1))*17+VALUE(MID(TEXT(D27,"000000000000000"),11,1))*19+VALUE(MID(TEXT(D27,"000000000000000"),10,1))*23+VALUE(MID(TEXT(D27,"000000000000000"),9,1))*29+VALUE(MID(TEXT(D27,"000000000000000"),8,1))*37+VALUE(MID(TEXT(D27,"000000000000000"),7,1))*41+VALUE(MID(TEXT(D27,"000000000000000"),6,1))*43+VALUE(MID(TEXT(D27,"000000000000000"),5,1))*47+VALUE(MID(TEXT(D27,"000000000000000"),4,1))*53+VALUE(MID(TEXT(D27,"000000000000000"),3,1))*59+VALUE(MID(TEXT(D27,"000000000000000"),2,1))*67+VALUE(MID(TEXT(D27,"000000000000000"),1,1))*71),11)))) -> 1 | F27: =+AN27 -> 220000 | G27: =+F27*$G$5 -> 41800 | H27: S | I27: =IF(H27="S",-F27*$I$5,"NO RETENCIÓN") -> -24200 | J27: =+F27+G27 -> 261800 | K27: =SUM(F27:I27) -> 237600 | M27: GTFF-187 | N27: Correo | O27: 45987 | R27: =+AM27 -> 0 | T27: Fra con -Ruiz González Álvaro H. | V27: SI | W27: =ROUND(IF(V27="SI",SUMIF('Facturas año anterior'!$B$8:$B$81,B27,'Facturas año anterior'!$V$8:$V$81)*(100%+$W$5),0),-3)+ROUND(IF(V27="SI",SUMIF('C de C año anterior'!$B$8:$B$210,B27,'C de C año anterior'!$Q$8:$Q$210)*(100%+$W$5),0),-3) -> 221000 | Y27: =ROUND(IF(X27="SI",W27*$Y$5,0),-3) -> 0 | AA27: =ROUND(IF(Z27="SI",W27*$AA$5,0),-3) -> 0 | AC27: =ROUND(IF(AB27="SI",W27*$AC$5,0),-3) -> 0 | AE27: =ROUND(IF(AD27="SI",W27*$AE$5,0),-3) -> 0 | AG27: =ROUND(IF(AF27="SI",W27*$AG$5,0),-3) -> 0 | AI27: =ROUND(IF(AH27="SI",W27*$AI$5,0),-3) -> 0 | AK27: =IF(AJ27="SI",W27*$AK$5,0) -> 0 | AL27: =SUMIF('Otras Asesorías y Préstamos'!$B$7:$B$242,B27,'Otras Asesorías y Préstamos'!$F$7:$F$242) -> 0 | AM27: =SUMIF('Otras Asesorías y Préstamos'!$B$7:$B$242,B27,'Otras Asesorías y Préstamos'!$V$7:$V$242) -> 0 | AN27: =ROUND(SUM(W27:AL27),-4) -> 220000
A28: =+A27+1 -> 20 | B28: RUIZ ARBOLEDA SEBASTIAN | C28: =_xlfn.XLOOKUP(B28,Códigos!$B$8:$B$406,Códigos!$A$8:$A$406,"Verificar",0) -> 229 | D28: =_xlfn.XLOOKUP(B28,'Consolidado Cobros'!$B$10:$B$312,'Consolidado Cobros'!$C$10:$C$312,"Verificar",0) -> 1037624491 | E28: =IF((MOD((VALUE(MID(TEXT(D28,"000000000000000"),15,1))*3+VALUE(MID(TEXT(D28,"000000000000000"),14,1))*7+VALUE(MID(TEXT(D28,"000000000000000"),13,1))*13+VALUE(MID(TEXT(D28,"000000000000000"),12,1))*17+VALUE(MID(TEXT(D28,"000000000000000"),11,1))*19+VALUE(MID(TEXT(D28,"000000000000000"),10,1))*23+VALUE(MID(TEXT(D28,"000000000000000"),9,1))*29+VALUE(MID(TEXT(D28,"000000000000000"),8,1))*37+VALUE(MID(TEXT(D28,"000000000000000"),7,1))*41+VALUE(MID(TEXT(D28,"000000000000000"),6,1))*43+VALUE(MID(TEXT(D28,"000000000000000"),5,1))*47+VALUE(MID(TEXT(D28,"000000000000000"),4,1))*53+VALUE(MID(TEXT(D28,"000000000000000"),3,1))*59+VALUE(MID(TEXT(D28,"000000000000000"),2,1))*67+VALUE(MID(TEXT(D28,"000000000000000"),1,1))*71),11))=0,0,IF((MOD((VALUE(MID(TEXT(D28,"000000000000000"),15,1))*3+VALUE(MID(TEXT(D28,"000000000000000"),14,1))*7+VALUE(MID(TEXT(D28,"000000000000000"),13,1))*13+VALUE(MID(TEXT(D28,"000000000000000"),12,1))*17+VALUE(MID(TEXT(D28,"000000000000000"),11,1))*19+VALUE(MID(TEXT(D28,"000000000000000"),10,1))*23+VALUE(MID(TEXT(D28,"000000000000000"),9,1))*29+VALUE(MID(TEXT(D28,"000000000000000"),8,1))*37+VALUE(MID(TEXT(D28,"000000000000000"),7,1))*41+VALUE(MID(TEXT(D28,"000000000000000"),6,1))*43+VALUE(MID(TEXT(D28,"000000000000000"),5,1))*47+VALUE(MID(TEXT(D28,"000000000000000"),4,1))*53+VALUE(MID(TEXT(D28,"000000000000000"),3,1))*59+VALUE(MID(TEXT(D28,"000000000000000"),2,1))*67+VALUE(MID(TEXT(D28,"000000000000000"),1,1))*71),11))=1,1,11-(MOD((VALUE(MID(TEXT(D28,"000000000000000"),15,1))*3+VALUE(MID(TEXT(D28,"000000000000000"),14,1))*7+VALUE(MID(TEXT(D28,"000000000000000"),13,1))*13+VALUE(MID(TEXT(D28,"000000000000000"),12,1))*17+VALUE(MID(TEXT(D28,"000000000000000"),11,1))*19+VALUE(MID(TEXT(D28,"000000000000000"),10,1))*23+VALUE(MID(TEXT(D28,"000000000000000"),9,1))*29+VALUE(MID(TEXT(D28,"000000000000000"),8,1))*37+VALUE(MID(TEXT(D28,"000000000000000"),7,1))*41+VALUE(MID(TEXT(D28,"000000000000000"),6,1))*43+VALUE(MID(TEXT(D28,"000000000000000"),5,1))*47+VALUE(MID(TEXT(D28,"000000000000000"),4,1))*53+VALUE(MID(TEXT(D28,"000000000000000"),3,1))*59+VALUE(MID(TEXT(D28,"000000000000000"),2,1))*67+VALUE(MID(TEXT(D28,"000000000000000"),1,1))*71),11)))) -> 7 | F28: =+AN28 -> 220000 | G28: =+F28*$G$5 -> 41800 | H28: S | I28: =IF(H28="S",-F28*$I$5,"NO RETENCIÓN") -> -24200 | J28: =+F28+G28 -> 261800 | K28: =SUM(F28:I28) -> 237600 | M28: GTFF-187 | N28: Correo | O28: 45987 | R28: =+AM28 -> 0 | T28: Fra con -Ruiz González Álvaro H. | V28: SI | W28: =ROUND(IF(V28="SI",SUMIF('Facturas año anterior'!$B$8:$B$81,B28,'Facturas año anterior'!$V$8:$V$81)*(100%+$W$5),0),-3)+ROUND(IF(V28="SI",SUMIF('C de C año anterior'!$B$8:$B$210,B28,'C de C año anterior'!$Q$8:$Q$210)*(100%+$W$5),0),-3) -> 221000 | Y28: =ROUND(IF(X28="SI",W28*$Y$5,0),-3) -> 0 | AA28: =ROUND(IF(Z28="SI",W28*$AA$5,0),-3) -> 0 | AC28: =ROUND(IF(AB28="SI",W28*$AC$5,0),-3) -> 0 | AE28: =ROUND(IF(AD28="SI",W28*$AE$5,0),-3) -> 0 | AG28: =ROUND(IF(AF28="SI",W28*$AG$5,0),-3) -> 0 | AI28: =ROUND(IF(AH28="SI",W28*$AI$5,0),-3) -> 0 | AK28: =IF(AJ28="SI",W28*$AK$5,0) -> 0 | AL28: =SUMIF('Otras Asesorías y Préstamos'!$B$7:$B$242,B28,'Otras Asesorías y Préstamos'!$F$7:$F$242) -> 0 | AM28: =SUMIF('Otras Asesorías y Préstamos'!$B$7:$B$242,B28,'Otras Asesorías y Préstamos'!$V$7:$V$242) -> 0 | AN28: =ROUND(SUM(W28:AL28),-4) -> 220000
A29: =+A28+1 -> 21 | B29: RUIZ GONZÁLEZ ÁLVARO HUMBERTO | C29: =_xlfn.XLOOKUP(B29,Códigos!$B$8:$B$406,Códigos!$A$8:$A$406,"Verificar",0) -> 171 | D29: =_xlfn.XLOOKUP(B29,'Consolidado Cobros'!$B$10:$B$312,'Consolidado Cobros'!$C$10:$C$312,"Verificar",0) -> 71660993 | E29: =IF((MOD((VALUE(MID(TEXT(D29,"000000000000000"),15,1))*3+VALUE(MID(TEXT(D29,"000000000000000"),14,1))*7+VALUE(MID(TEXT(D29,"000000000000000"),13,1))*13+VALUE(MID(TEXT(D29,"000000000000000"),12,1))*17+VALUE(MID(TEXT(D29,"000000000000000"),11,1))*19+VALUE(MID(TEXT(D29,"000000000000000"),10,1))*23+VALUE(MID(TEXT(D29,"000000000000000"),9,1))*29+VALUE(MID(TEXT(D29,"000000000000000"),8,1))*37+VALUE(MID(TEXT(D29,"000000000000000"),7,1))*41+VALUE(MID(TEXT(D29,"000000000000000"),6,1))*43+VALUE(MID(TEXT(D29,"000000000000000"),5,1))*47+VALUE(MID(TEXT(D29,"000000000000000"),4,1))*53+VALUE(MID(TEXT(D29,"000000000000000"),3,1))*59+VALUE(MID(TEXT(D29,"000000000000000"),2,1))*67+VALUE(MID(TEXT(D29,"000000000000000"),1,1))*71),11))=0,0,IF((MOD((VALUE(MID(TEXT(D29,"000000000000000"),15,1))*3+VALUE(MID(TEXT(D29,"000000000000000"),14,1))*7+VALUE(MID(TEXT(D29,"000000000000000"),13,1))*13+VALUE(MID(TEXT(D29,"000000000000000"),12,1))*17+VALUE(MID(TEXT(D29,"000000000000000"),11,1))*19+VALUE(MID(TEXT(D29,"000000000000000"),10,1))*23+VALUE(MID(TEXT(D29,"000000000000000"),9,1))*29+VALUE(MID(TEXT(D29,"000000000000000"),8,1))*37+VALUE(MID(TEXT(D29,"000000000000000"),7,1))*41+VALUE(MID(TEXT(D29,"000000000000000"),6,1))*43+VALUE(MID(TEXT(D29,"000000000000000"),5,1))*47+VALUE(MID(TEXT(D29,"000000000000000"),4,1))*53+VALUE(MID(TEXT(D29,"000000000000000"),3,1))*59+VALUE(MID(TEXT(D29,"000000000000000"),2,1))*67+VALUE(MID(TEXT(D29,"000000000000000"),1,1))*71),11))=1,1,11-(MOD((VALUE(MID(TEXT(D29,"000000000000000"),15,1))*3+VALUE(MID(TEXT(D29,"000000000000000"),14,1))*7+VALUE(MID(TEXT(D29,"000000000000000"),13,1))*13+VALUE(MID(TEXT(D29,"000000000000000"),12,1))*17+VALUE(MID(TEXT(D29,"000000000000000"),11,1))*19+VALUE(MID(TEXT(D29,"000000000000000"),10,1))*23+VALUE(MID(TEXT(D29,"000000000000000"),9,1))*29+VALUE(MID(TEXT(D29,"000000000000000"),8,1))*37+VALUE(MID(TEXT(D29,"000000000000000"),7,1))*41+VALUE(MID(TEXT(D29,"000000000000000"),6,1))*43+VALUE(MID(TEXT(D29,"000000000000000"),5,1))*47+VALUE(MID(TEXT(D29,"000000000000000"),4,1))*53+VALUE(MID(TEXT(D29,"000000000000000"),3,1))*59+VALUE(MID(TEXT(D29,"000000000000000"),2,1))*67+VALUE(MID(TEXT(D29,"000000000000000"),1,1))*71),11)))) -> 8 | F29: =+AN29 -> 2280000 | G29: =+F29*$G$5 -> 433200 | H29: S | I29: =IF(H29="S",-F29*$I$5,"NO RETENCIÓN") -> -250800 | J29: =+F29+G29 -> 2713200 | K29: =SUM(F29:I29) -> 2462400 | M29: GTFF-187 | N29: Correo | O29: 45987 | R29: =+AM29 -> 0 | T29: Fra con -Ruiz González Álvaro H. | V29: SI | W29: =ROUND(IF(V29="SI",SUMIF('Facturas año anterior'!$B$8:$B$81,B29,'Facturas año anterior'!$V$8:$V$81)*(100%+$W$5),0),-3)+ROUND(IF(V29="SI",SUMIF('C de C año anterior'!$B$8:$B$210,B29,'C de C año anterior'!$Q$8:$Q$210)*(100%+$W$5),0),-3) -> 1168000 | Y29: =ROUND(IF(X29="SI",W29*$Y$5,0),-3) -> 0 | Z29: SI | AA29: =ROUND(IF(Z29="SI",W29*$AA$5,0),-3) -> 876000 | AC29: =ROUND(IF(AB29="SI",W29*$AC$5,0),-3) -> 0 | AE29: =ROUND(IF(AD29="SI",W29*$AE$5,0),-3) -> 0 | AG29: =ROUND(IF(AF29="SI",W29*$AG$5,0),-3) -> 0 | AH29: SI | AI29: =ROUND(IF(AH29="SI",W29*$AI$5,0),-3) -> 234000 | AK29: =IF(AJ29="SI",W29*$AK$5,0) -> 0 | AL29: =SUMIF('Otras Asesorías y Préstamos'!$B$7:$B$242,B29,'Otras Asesorías y Préstamos'!$F$7:$F$242) -> 0 | AM29: =SUMIF('Otras Asesorías y Préstamos'!$B$7:$B$242,B29,'Otras Asesorías y Préstamos'!$V$7:$V$242) -> 0 | AN29: =ROUND(SUM(W29:AL29),-4) -> 2280000
A30: =+A29+1 -> 22 | B30: SÁNCHEZ RESTREPO JUAN DAVID | C30: =_xlfn.XLOOKUP(B30,Códigos!$B$8:$B$406,Códigos!$A$8:$A$406,"Verificar",0) -> 175 | D30: =_xlfn.XLOOKUP(B30,'Consolidado Cobros'!$B$10:$B$312,'Consolidado Cobros'!$C$10:$C$312,"Verificar",0) -> 71315509 | E30: =IF((MOD((VALUE(MID(TEXT(D30,"000000000000000"),15,1))*3+VALUE(MID(TEXT(D30,"000000000000000"),14,1))*7+VALUE(MID(TEXT(D30,"000000000000000"),13,1))*13+VALUE(MID(TEXT(D30,"000000000000000"),12,1))*17+VALUE(MID(TEXT(D30,"000000000000000"),11,1))*19+VALUE(MID(TEXT(D30,"000000000000000"),10,1))*23+VALUE(MID(TEXT(D30,"000000000000000"),9,1))*29+VALUE(MID(TEXT(D30,"000000000000000"),8,1))*37+VALUE(MID(TEXT(D30,"000000000000000"),7,1))*41+VALUE(MID(TEXT(D30,"000000000000000"),6,1))*43+VALUE(MID(TEXT(D30,"000000000000000"),5,1))*47+VALUE(MID(TEXT(D30,"000000000000000"),4,1))*53+VALUE(MID(TEXT(D30,"000000000000000"),3,1))*59+VALUE(MID(TEXT(D30,"000000000000000"),2,1))*67+VALUE(MID(TEXT(D30,"000000000000000"),1,1))*71),11))=0,0,IF((MOD((VALUE(MID(TEXT(D30,"000000000000000"),15,1))*3+VALUE(MID(TEXT(D30,"000000000000000"),14,1))*7+VALUE(MID(TEXT(D30,"000000000000000"),13,1))*13+VALUE(MID(TEXT(D30,"000000000000000"),12,1))*17+VALUE(MID(TEXT(D30,"000000000000000"),11,1))*19+VALUE(MID(TEXT(D30,"000000000000000"),10,1))*23+VALUE(MID(TEXT(D30,"000000000000000"),9,1))*29+VALUE(MID(TEXT(D30,"000000000000000"),8,1))*37+VALUE(MID(TEXT(D30,"000000000000000"),7,1))*41+VALUE(MID(TEXT(D30,"000000000000000"),6,1))*43+VALUE(MID(TEXT(D30,"000000000000000"),5,1))*47+VALUE(MID(TEXT(D30,"000000000000000"),4,1))*53+VALUE(MID(TEXT(D30,"000000000000000"),3,1))*59+VALUE(MID(TEXT(D30,"000000000000000"),2,1))*67+VALUE(MID(TEXT(D30,"000000000000000"),1,1))*71),11))=1,1,11-(MOD((VALUE(MID(TEXT(D30,"000000000000000"),15,1))*3+VALUE(MID(TEXT(D30,"000000000000000"),14,1))*7+VALUE(MID(TEXT(D30,"000000000000000"),13,1))*13+VALUE(MID(TEXT(D30,"000000000000000"),12,1))*17+VALUE(MID(TEXT(D30,"000000000000000"),11,1))*19+VALUE(MID(TEXT(D30,"000000000000000"),10,1))*23+VALUE(MID(TEXT(D30,"000000000000000"),9,1))*29+VALUE(MID(TEXT(D30,"000000000000000"),8,1))*37+VALUE(MID(TEXT(D30,"000000000000000"),7,1))*41+VALUE(MID(TEXT(D30,"000000000000000"),6,1))*43+VALUE(MID(TEXT(D30,"000000000000000"),5,1))*47+VALUE(MID(TEXT(D30,"000000000000000"),4,1))*53+VALUE(MID(TEXT(D30,"000000000000000"),3,1))*59+VALUE(MID(TEXT(D30,"000000000000000"),2,1))*67+VALUE(MID(TEXT(D30,"000000000000000"),1,1))*71),11)))) -> 8 | F30: =+AN30 -> 800000 | G30: =+F30*$G$5 -> 152000 | H30: NO | I30: =IF(H30="S",-F30*$I$5,"NO RETENCIÓN") -> NO RETENCIÓN | J30: =+F30+G30 -> 952000 | K30: =SUM(F30:I30) -> 952000 | M30: GTFF-169 | N30: Correo | O30: 45987 | R30: =+AM30 -> 0 | T30: Fra con -Ma Isabel Restrepo de S | V30: SI | W30: =ROUND(IF(V30="SI",SUMIF('Facturas año anterior'!$B$8:$B$81,B30,'Facturas año anterior'!$V$8:$V$81)*(100%+$W$5),0),-3)+ROUND(IF(V30="SI",SUMIF('C de C año anterior'!$B$8:$B$210,B30,'C de C año anterior'!$Q$8:$Q$210)*(100%+$W$5),0),-3) -> 612000 | Y30: =ROUND(IF(X30="SI",W30*$Y$5,0),-3) -> 0 | AA30: =ROUND(IF(Z30="SI",W30*$AA$5,0),-3) -> 0 | AC30: =ROUND(IF(AB30="SI",W30*$AC$5,0),-3) -> 0 | AE30: =ROUND(IF(AD30="SI",W30*$AE$5,0),-3) -> 0 | AG30: =ROUND(IF(AF30="SI",W30*$AG$5,0),-3) -> 0 | AI30: =ROUND(IF(AH30="SI",W30*$AI$5,0),-3) -> 0 | AJ30: SI | AK30: =IF(AJ30="SI",W30*$AK$5,0) -> 183600 | AL30: =SUMIF('Otras Asesorías y Préstamos'!$B$7:$B$242,B30,'Otras Asesorías y Préstamos'!$F$7:$F$242) -> 0 | AM30: =SUMIF('Otras Asesorías y Préstamos'!$B$7:$B$242,B30,'Otras Asesorías y Préstamos'!$V$7:$V$242) -> 0 | AN30: =ROUND(SUM(W30:AL30),-4) -> 800000
A31: =+A30+1 -> 23 | B31: SÁNCHEZ RESTREPO MARGARITA ROSA | C31: =_xlfn.XLOOKUP(B31,Códigos!$B$8:$B$406,Códigos!$A$8:$A$406,"Verificar",0) -> 296 | D31: =_xlfn.XLOOKUP(B31,'Consolidado Cobros'!$B$10:$B$312,'Consolidado Cobros'!$C$10:$C$312,"Verificar",0) -> 43628444 | E31: =IF((MOD((VALUE(MID(TEXT(D31,"000000000000000"),15,1))*3+VALUE(MID(TEXT(D31,"000000000000000"),14,1))*7+VALUE(MID(TEXT(D31,"000000000000000"),13,1))*13+VALUE(MID(TEXT(D31,"000000000000000"),12,1))*17+VALUE(MID(TEXT(D31,"000000000000000"),11,1))*19+VALUE(MID(TEXT(D31,"000000000000000"),10,1))*23+VALUE(MID(TEXT(D31,"000000000000000"),9,1))*29+VALUE(MID(TEXT(D31,"000000000000000"),8,1))*37+VALUE(MID(TEXT(D31,"000000000000000"),7,1))*41+VALUE(MID(TEXT(D31,"000000000000000"),6,1))*43+VALUE(MID(TEXT(D31,"000000000000000"),5,1))*47+VALUE(MID(TEXT(D31,"000000000000000"),4,1))*53+VALUE(MID(TEXT(D31,"000000000000000"),3,1))*59+VALUE(MID(TEXT(D31,"000000000000000"),2,1))*67+VALUE(MID(TEXT(D31,"000000000000000"),1,1))*71),11))=0,0,IF((MOD((VALUE(MID(TEXT(D31,"000000000000000"),15,1))*3+VALUE(MID(TEXT(D31,"000000000000000"),14,1))*7+VALUE(MID(TEXT(D31,"000000000000000"),13,1))*13+VALUE(MID(TEXT(D31,"000000000000000"),12,1))*17+VALUE(MID(TEXT(D31,"000000000000000"),11,1))*19+VALUE(MID(TEXT(D31,"000000000000000"),10,1))*23+VALUE(MID(TEXT(D31,"000000000000000"),9,1))*29+VALUE(MID(TEXT(D31,"000000000000000"),8,1))*37+VALUE(MID(TEXT(D31,"000000000000000"),7,1))*41+VALUE(MID(TEXT(D31,"000000000000000"),6,1))*43+VALUE(MID(TEXT(D31,"000000000000000"),5,1))*47+VALUE(MID(TEXT(D31,"000000000000000"),4,1))*53+VALUE(MID(TEXT(D31,"000000000000000"),3,1))*59+VALUE(MID(TEXT(D31,"000000000000000"),2,1))*67+VALUE(MID(TEXT(D31,"000000000000000"),1,1))*71),11))=1,1,11-(MOD((VALUE(MID(TEXT(D31,"000000000000000"),15,1))*3+VALUE(MID(TEXT(D31,"000000000000000"),14,1))*7+VALUE(MID(TEXT(D31,"000000000000000"),13,1))*13+VALUE(MID(TEXT(D31,"000000000000000"),12,1))*17+VALUE(MID(TEXT(D31,"000000000000000"),11,1))*19+VALUE(MID(TEXT(D31,"000000000000000"),10,1))*23+VALUE(MID(TEXT(D31,"000000000000000"),9,1))*29+VALUE(MID(TEXT(D31,"000000000000000"),8,1))*37+VALUE(MID(TEXT(D31,"000000000000000"),7,1))*41+VALUE(MID(TEXT(D31,"000000000000000"),6,1))*43+VALUE(MID(TEXT(D31,"000000000000000"),5,1))*47+VALUE(MID(TEXT(D31,"000000000000000"),4,1))*53+VALUE(MID(TEXT(D31,"000000000000000"),3,1))*59+VALUE(MID(TEXT(D31,"000000000000000"),2,1))*67+VALUE(MID(TEXT(D31,"000000000000000"),1,1))*71),11)))) -> 1 | F31: =+AN31 -> 1000000 | G31: =+F31*$G$5 -> 190000 | H31: NO | I31: =IF(H31="S",-F31*$I$5,"NO RETENCIÓN") -> NO RETENCIÓN | J31: =+F31+G31 -> 1190000 | K31: =SUM(F31:I31) -> 1190000 | M31: GTFF-170 | N31: Correo | O31: 45987 | R31: =+AM31 -> 0 | T31: SÁNCHEZ RESTREPO MARGARITA ROSA | V31: SI | W31: =ROUND(IF(V31="SI",SUMIF('Facturas año anterior'!$B$8:$B$81,B31,'Facturas año anterior'!$V$8:$V$81)*(100%+$W$5),0),-3)+ROUND(IF(V31="SI",SUMIF('C de C año anterior'!$B$8:$B$210,B31,'C de C año anterior'!$Q$8:$Q$210)*(100%+$W$5),0),-3) -> 612000 | Y31: =ROUND(IF(X31="SI",W31*$Y$5,0),-3) -> 0 | AA31: =ROUND(IF(Z31="SI",W31*$AA$5,0),-3) -> 0 | AC31: =ROUND(IF(AB31="SI",W31*$AC$5,0),-3) -> 0 | AE31: =ROUND(IF(AD31="SI",W31*$AE$5,0),-3) -> 0 | AG31: =ROUND(IF(AF31="SI",W31*$AG$5,0),-3) -> 0 | AI31: =ROUND(IF(AH31="SI",W31*$AI$5,0),-3) -> 0 | AK31: =IF(AJ31="SI",W31*$AK$5,0) -> 0 | AL31: =SUMIF('Otras Asesorías y Préstamos'!$B$7:$B$242,B31,'Otras Asesorías y Préstamos'!$F$7:$F$242) -> 384583 | AM31: =SUMIF('Otras Asesorías y Préstamos'!$B$7:$B$242,B31,'Otras Asesorías y Préstamos'!$V$7:$V$242) -> 0 | AN31: =ROUND(SUM(W31:AL31),-4) -> 1000000
A32: =+A31+1 -> 24 | B32: SÁNCHEZ RUBIO JOSÉ MARDOQUEO | C32: =_xlfn.XLOOKUP(B32,Códigos!$B$8:$B$406,Códigos!$A$8:$A$406,"Verificar",0) -> 176 | D32: =_xlfn.XLOOKUP(B32,'Consolidado Cobros'!$B$10:$B$312,'Consolidado Cobros'!$C$10:$C$312,"Verificar",0) -> 1138258 | E32: =IF((MOD((VALUE(MID(TEXT(D32,"000000000000000"),15,1))*3+VALUE(MID(TEXT(D32,"000000000000000"),14,1))*7+VALUE(MID(TEXT(D32,"000000000000000"),13,1))*13+VALUE(MID(TEXT(D32,"000000000000000"),12,1))*17+VALUE(MID(TEXT(D32,"000000000000000"),11,1))*19+VALUE(MID(TEXT(D32,"000000000000000"),10,1))*23+VALUE(MID(TEXT(D32,"000000000000000"),9,1))*29+VALUE(MID(TEXT(D32,"000000000000000"),8,1))*37+VALUE(MID(TEXT(D32,"000000000000000"),7,1))*41+VALUE(MID(TEXT(D32,"000000000000000"),6,1))*43+VALUE(MID(TEXT(D32,"000000000000000"),5,1))*47+VALUE(MID(TEXT(D32,"000000000000000"),4,1))*53+VALUE(MID(TEXT(D32,"000000000000000"),3,1))*59+VALUE(MID(TEXT(D32,"000000000000000"),2,1))*67+VALUE(MID(TEXT(D32,"000000000000000"),1,1))*71),11))=0,0,IF((MOD((VALUE(MID(TEXT(D32,"000000000000000"),15,1))*3+VALUE(MID(TEXT(D32,"000000000000000"),14,1))*7+VALUE(MID(TEXT(D32,"000000000000000"),13,1))*13+VALUE(MID(TEXT(D32,"000000000000000"),12,1))*17+VALUE(MID(TEXT(D32,"000000000000000"),11,1))*19+VALUE(MID(TEXT(D32,"000000000000000"),10,1))*23+VALUE(MID(TEXT(D32,"000000000000000"),9,1))*29+VALUE(MID(TEXT(D32,"000000000000000"),8,1))*37+VALUE(MID(TEXT(D32,"000000000000000"),7,1))*41+VALUE(MID(TEXT(D32,"000000000000000"),6,1))*43+VALUE(MID(TEXT(D32,"000000000000000"),5,1))*47+VALUE(MID(TEXT(D32,"000000000000000"),4,1))*53+VALUE(MID(TEXT(D32,"000000000000000"),3,1))*59+VALUE(MID(TEXT(D32,"000000000000000"),2,1))*67+VALUE(MID(TEXT(D32,"000000000000000"),1,1))*71),11))=1,1,11-(MOD((VALUE(MID(TEXT(D32,"000000000000000"),15,1))*3+VALUE(MID(TEXT(D32,"000000000000000"),14,1))*7+VALUE(MID(TEXT(D32,"000000000000000"),13,1))*13+VALUE(MID(TEXT(D32,"000000000000000"),12,1))*17+VALUE(MID(TEXT(D32,"000000000000000"),11,1))*19+VALUE(MID(TEXT(D32,"000000000000000"),10,1))*23+VALUE(MID(TEXT(D32,"000000000000000"),9,1))*29+VALUE(MID(TEXT(D32,"000000000000000"),8,1))*37+VALUE(MID(TEXT(D32,"000000000000000"),7,1))*41+VALUE(MID(TEXT(D32,"000000000000000"),6,1))*43+VALUE(MID(TEXT(D32,"000000000000000"),5,1))*47+VALUE(MID(TEXT(D32,"000000000000000"),4,1))*53+VALUE(MID(TEXT(D32,"000000000000000"),3,1))*59+VALUE(MID(TEXT(D32,"000000000000000"),2,1))*67+VALUE(MID(TEXT(D32,"000000000000000"),1,1))*71),11)))) -> 0 | F32: =+AN32 -> 0 | G32: =+F32*$G$5 -> 0 | H32: NO | I32: =IF(H32="S",-F32*$I$5,"NO RETENCIÓN") -> NO RETENCIÓN | J32: =+F32+G32 -> 0 | K32: =SUM(F32:I32) -> 0 | M32: N/A | R32: =+AM32 -> 0 | T32: Fra con -Ma Isabel Restrepo de S | V32: NO | W32: =ROUND(IF(V32="SI",SUMIF('Facturas año anterior'!$B$8:$B$81,B32,'Facturas año anterior'!$V$8:$V$81)*(100%+$W$5),0),-3)+ROUND(IF(V32="SI",SUMIF('C de C año anterior'!$B$8:$B$210,B32,'C de C año anterior'!$Q$8:$Q$210)*(100%+$W$5),0),-3) -> 0 | Y32: =ROUND(IF(X32="SI",W32*$Y$5,0),-3) -> 0 | AA32: =ROUND(IF(Z32="SI",W32*$AA$5,0),-3) -> 0 | AC32: =ROUND(IF(AB32="SI",W32*$AC$5,0),-3) -> 0 | AE32: =ROUND(IF(AD32="SI",W32*$AE$5,0),-3) -> 0 | AG32: =ROUND(IF(AF32="SI",W32*$AG$5,0),-3) -> 0 | AI32: =ROUND(IF(AH32="SI",W32*$AI$5,0),-3) -> 0 | AK32: =IF(AJ32="SI",W32*$AK$5,0) -> 0 | AL32: =SUMIF('Otras Asesorías y Préstamos'!$B$7:$B$242,B32,'Otras Asesorías y Préstamos'!$F$7:$F$242) -> 0 | AM32: =SUMIF('Otras Asesorías y Préstamos'!$B$7:$B$242,B32,'Otras Asesorías y Préstamos'!$V$7:$V$242) -> 0 | AN32: =ROUND(SUM(W32:AL32),-4) -> 0
A33: =+A32+1 -> 25 | B33: TORRES SÁNCHEZ OMAR WINSTON | C33: =_xlfn.XLOOKUP(B33,Códigos!$B$8:$B$406,Códigos!$A$8:$A$406,"Verificar",0) -> 187 | D33: =_xlfn.XLOOKUP(B33,'Consolidado Cobros'!$B$10:$B$312,'Consolidado Cobros'!$C$10:$C$312,"Verificar",0) -> 71595523 | E33: =IF((MOD((VALUE(MID(TEXT(D33,"000000000000000"),15,1))*3+VALUE(MID(TEXT(D33,"000000000000000"),14,1))*7+VALUE(MID(TEXT(D33,"000000000000000"),13,1))*13+VALUE(MID(TEXT(D33,"000000000000000"),12,1))*17+VALUE(MID(TEXT(D33,"000000000000000"),11,1))*19+VALUE(MID(TEXT(D33,"000000000000000"),10,1))*23+VALUE(MID(TEXT(D33,"000000000000000"),9,1))*29+VALUE(MID(TEXT(D33,"000000000000000"),8,1))*37+VALUE(MID(TEXT(D33,"000000000000000"),7,1))*41+VALUE(MID(TEXT(D33,"000000000000000"),6,1))*43+VALUE(MID(TEXT(D33,"000000000000000"),5,1))*47+VALUE(MID(TEXT(D33,"000000000000000"),4,1))*53+VALUE(MID(TEXT(D33,"000000000000000"),3,1))*59+VALUE(MID(TEXT(D33,"000000000000000"),2,1))*67+VALUE(MID(TEXT(D33,"000000000000000"),1,1))*71),11))=0,0,IF((MOD((VALUE(MID(TEXT(D33,"000000000000000"),15,1))*3+VALUE(MID(TEXT(D33,"000000000000000"),14,1))*7+VALUE(MID(TEXT(D33,"000000000000000"),13,1))*13+VALUE(MID(TEXT(D33,"000000000000000"),12,1))*17+VALUE(MID(TEXT(D33,"000000000000000"),11,1))*19+VALUE(MID(TEXT(D33,"000000000000000"),10,1))*23+VALUE(MID(TEXT(D33,"000000000000000"),9,1))*29+VALUE(MID(TEXT(D33,"000000000000000"),8,1))*37+VALUE(MID(TEXT(D33,"000000000000000"),7,1))*41+VALUE(MID(TEXT(D33,"000000000000000"),6,1))*43+VALUE(MID(TEXT(D33,"000000000000000"),5,1))*47+VALUE(MID(TEXT(D33,"000000000000000"),4,1))*53+VALUE(MID(TEXT(D33,"000000000000000"),3,1))*59+VALUE(MID(TEXT(D33,"000000000000000"),2,1))*67+VALUE(MID(TEXT(D33,"000000000000000"),1,1))*71),11))=1,1,11-(MOD((VALUE(MID(TEXT(D33,"000000000000000"),15,1))*3+VALUE(MID(TEXT(D33,"000000000000000"),14,1))*7+VALUE(MID(TEXT(D33,"000000000000000"),13,1))*13+VALUE(MID(TEXT(D33,"000000000000000"),12,1))*17+VALUE(MID(TEXT(D33,"000000000000000"),11,1))*19+VALUE(MID(TEXT(D33,"000000000000000"),10,1))*23+VALUE(MID(TEXT(D33,"000000000000000"),9,1))*29+VALUE(MID(TEXT(D33,"000000000000000"),8,1))*37+VALUE(MID(TEXT(D33,"000000000000000"),7,1))*41+VALUE(MID(TEXT(D33,"000000000000000"),6,1))*43+VALUE(MID(TEXT(D33,"000000000000000"),5,1))*47+VALUE(MID(TEXT(D33,"000000000000000"),4,1))*53+VALUE(MID(TEXT(D33,"000000000000000"),3,1))*59+VALUE(MID(TEXT(D33,"000000000000000"),2,1))*67+VALUE(MID(TEXT(D33,"000000000000000"),1,1))*71),11)))) -> 1 | F33: =+AN33 -> 500000 | G33: =+F33*$G$5 -> 95000 | H33: S | I33: =IF(H33="S",-F33*$I$5,"NO RETENCIÓN") -> -55000 | J33: =+F33+G33 -> 595000 | K33: =SUM(F33:I33) -> 540000 | M33: GTFF-167 | N33: Correo y Wpp | O33: 45986 | R33: =+AM33 -> 0 | T33: Fra con -Arrtos El Campestre | V33: SI | W33: =ROUND(IF(V33="SI",SUMIF('Facturas año anterior'!$B$8:$B$81,B33,'Facturas año anterior'!$V$8:$V$81)*(100%+$W$5),0),-3)+ROUND(IF(V33="SI",SUMIF('C de C año anterior'!$B$8:$B$210,B33,'C de C año anterior'!$Q$8:$Q$210)*(100%+$W$5),0),-3) -> 497000 | Y33: =ROUND(IF(X33="SI",W33*$Y$5,0),-3) -> 0 | AA33: =ROUND(IF(Z33="SI",W33*$AA$5,0),-3) -> 0 | AC33: =ROUND(IF(AB33="SI",W33*$AC$5,0),-3) -> 0 | AE33: =ROUND(IF(AD33="SI",W33*$AE$5,0),-3) -> 0 | AG33: =ROUND(IF(AF33="SI",W33*$AG$5,0),-3) -> 0 | AI33: =ROUND(IF(AH33="SI",W33*$AI$5,0),-3) -> 0 | AK33: =IF(AJ33="SI",W33*$AK$5,0) -> 0 | AL33: =SUMIF('Otras Asesorías y Préstamos'!$B$7:$B$242,B33,'Otras Asesorías y Préstamos'!$F$7:$F$242) -> 0 | AM33: =SUMIF('Otras Asesorías y Préstamos'!$B$7:$B$242,B33,'Otras Asesorías y Préstamos'!$V$7:$V$242) -> 0 | AN33: =ROUND(SUM(W33:AL33),-4) -> 500000
A34: =+A33+1 -> 26 | B34: VILLEGAS DE ECHAVARRÍA MARÍA CLARA | C34: 206 | D34: =_xlfn.XLOOKUP(B34,'Consolidado Cobros'!$B$10:$B$312,'Consolidado Cobros'!$C$10:$C$312,"Verificar",0) -> 32469463 | E34: =IF((MOD((VALUE(MID(TEXT(D34,"000000000000000"),15,1))*3+VALUE(MID(TEXT(D34,"000000000000000"),14,1))*7+VALUE(MID(TEXT(D34,"000000000000000"),13,1))*13+VALUE(MID(TEXT(D34,"000000000000000"),12,1))*17+VALUE(MID(TEXT(D34,"000000000000000"),11,1))*19+VALUE(MID(TEXT(D34,"000000000000000"),10,1))*23+VALUE(MID(TEXT(D34,"000000000000000"),9,1))*29+VALUE(MID(TEXT(D34,"000000000000000"),8,1))*37+VALUE(MID(TEXT(D34,"000000000000000"),7,1))*41+VALUE(MID(TEXT(D34,"000000000000000"),6,1))*43+VALUE(MID(TEXT(D34,"000000000000000"),5,1))*47+VALUE(MID(TEXT(D34,"000000000000000"),4,1))*53+VALUE(MID(TEXT(D34,"000000000000000"),3,1))*59+VALUE(MID(TEXT(D34,"000000000000000"),2,1))*67+VALUE(MID(TEXT(D34,"000000000000000"),1,1))*71),11))=0,0,IF((MOD((VALUE(MID(TEXT(D34,"000000000000000"),15,1))*3+VALUE(MID(TEXT(D34,"000000000000000"),14,1))*7+VALUE(MID(TEXT(D34,"000000000000000"),13,1))*13+VALUE(MID(TEXT(D34,"000000000000000"),12,1))*17+VALUE(MID(TEXT(D34,"000000000000000"),11,1))*19+VALUE(MID(TEXT(D34,"000000000000000"),10,1))*23+VALUE(MID(TEXT(D34,"000000000000000"),9,1))*29+VALUE(MID(TEXT(D34,"000000000000000"),8,1))*37+VALUE(MID(TEXT(D34,"000000000000000"),7,1))*41+VALUE(MID(TEXT(D34,"000000000000000"),6,1))*43+VALUE(MID(TEXT(D34,"000000000000000"),5,1))*47+VALUE(MID(TEXT(D34,"000000000000000"),4,1))*53+VALUE(MID(TEXT(D34,"000000000000000"),3,1))*59+VALUE(MID(TEXT(D34,"000000000000000"),2,1))*67+VALUE(MID(TEXT(D34,"000000000000000"),1,1))*71),11))=1,1,11-(MOD((VALUE(MID(TEXT(D34,"000000000000000"),15,1))*3+VALUE(MID(TEXT(D34,"000000000000000"),14,1))*7+VALUE(MID(TEXT(D34,"000000000000000"),13,1))*13+VALUE(MID(TEXT(D34,"000000000000000"),12,1))*17+VALUE(MID(TEXT(D34,"000000000000000"),11,1))*19+VALUE(MID(TEXT(D34,"000000000000000"),10,1))*23+VALUE(MID(TEXT(D34,"000000000000000"),9,1))*29+VALUE(MID(TEXT(D34,"000000000000000"),8,1))*37+VALUE(MID(TEXT(D34,"000000000000000"),7,1))*41+VALUE(MID(TEXT(D34,"000000000000000"),6,1))*43+VALUE(MID(TEXT(D34,"000000000000000"),5,1))*47+VALUE(MID(TEXT(D34,"000000000000000"),4,1))*53+VALUE(MID(TEXT(D34,"000000000000000"),3,1))*59+VALUE(MID(TEXT(D34,"000000000000000"),2,1))*67+VALUE(MID(TEXT(D34,"000000000000000"),1,1))*71),11)))) -> 7 | F34: =+AN34 -> 2280000 | G34: =+F34*$G$5 -> 433200 | H34: S | I34: =IF(H34="S",-F34*$I$5,"NO RETENCIÓN") -> -250800 | J34: =+F34+G34 -> 2713200 | K34: =SUM(F34:I34) -> 2462400 | M34: GTFF-183 | N34: Correo | O34: 45987 | T34: Fra con -ECHAVARRÍA ABOGADOS SAS | V34: SI | W34: =ROUND(IF(V34="SI",SUMIF('Facturas año anterior'!$B$8:$B$81,B34,'Facturas año anterior'!$V$8:$V$81)*(100%+$W$5),0),-3)+ROUND(IF(V34="SI",SUMIF('C de C año anterior'!$B$8:$B$210,B34,'C de C año anterior'!$Q$8:$Q$210)*(100%+$W$5),0),-3) -> 1753000 | Y34: =ROUND(IF(X34="SI",W34*$Y$5,0),-3) -> 0 | AA34: =ROUND(IF(Z34="SI",W34*$AA$5,0),-3) -> 0 | AC34: =ROUND(IF(AB34="SI",W34*$AC$5,0),-3) -> 0 | AE34: =ROUND(IF(AD34="SI",W34*$AE$5,0),-3) -> 0 | AG34: =ROUND(IF(AF34="SI",W34*$AG$5,0),-3) -> 0 | AI34: =ROUND(IF(AH34="SI",W34*$AI$5,0),-3) -> 0 | AJ34: SI | AK34: =IF(AJ34="SI",W34*$AK$5,0) -> 525900 | AL34: =SUMIF('Otras Asesorías y Préstamos'!$B$7:$B$242,B34,'Otras Asesorías y Préstamos'!$F$7:$F$242) -> 0 | AM34: =SUMIF('Otras Asesorías y Préstamos'!$B$7:$B$242,B34,'Otras Asesorías y Préstamos'!$V$7:$V$242) -> 0 | AN34: =ROUND(SUM(W34:AL34),-4) -> 2280000
A35: =+A34+1 -> 27 | B35: VILLEGAS ECHAVARRÍA ANDRÉS | C35: =_xlfn.XLOOKUP(B35,Códigos!$B$8:$B$406,Códigos!$A$8:$A$406,"Verificar",0) -> 207 | D35: =_xlfn.XLOOKUP(B35,'Consolidado Cobros'!$B$10:$B$312,'Consolidado Cobros'!$C$10:$C$312,"Verificar",0) -> 71720224 | E35: =IF((MOD((VALUE(MID(TEXT(D35,"000000000000000"),15,1))*3+VALUE(MID(TEXT(D35,"000000000000000"),14,1))*7+VALUE(MID(TEXT(D35,"000000000000000"),13,1))*13+VALUE(MID(TEXT(D35,"000000000000000"),12,1))*17+VALUE(MID(TEXT(D35,"000000000000000"),11,1))*19+VALUE(MID(TEXT(D35,"000000000000000"),10,1))*23+VALUE(MID(TEXT(D35,"000000000000000"),9,1))*29+VALUE(MID(TEXT(D35,"000000000000000"),8,1))*37+VALUE(MID(TEXT(D35,"000000000000000"),7,1))*41+VALUE(MID(TEXT(D35,"000000000000000"),6,1))*43+VALUE(MID(TEXT(D35,"000000000000000"),5,1))*47+VALUE(MID(TEXT(D35,"000000000000000"),4,1))*53+VALUE(MID(TEXT(D35,"000000000000000"),3,1))*59+VALUE(MID(TEXT(D35,"000000000000000"),2,1))*67+VALUE(MID(TEXT(D35,"000000000000000"),1,1))*71),11))=0,0,IF((MOD((VALUE(MID(TEXT(D35,"000000000000000"),15,1))*3+VALUE(MID(TEXT(D35,"000000000000000"),14,1))*7+VALUE(MID(TEXT(D35,"000000000000000"),13,1))*13+VALUE(MID(TEXT(D35,"000000000000000"),12,1))*17+VALUE(MID(TEXT(D35,"000000000000000"),11,1))*19+VALUE(MID(TEXT(D35,"000000000000000"),10,1))*23+VALUE(MID(TEXT(D35,"000000000000000"),9,1))*29+VALUE(MID(TEXT(D35,"000000000000000"),8,1))*37+VALUE(MID(TEXT(D35,"000000000000000"),7,1))*41+VALUE(MID(TEXT(D35,"000000000000000"),6,1))*43+VALUE(MID(TEXT(D35,"000000000000000"),5,1))*47+VALUE(MID(TEXT(D35,"000000000000000"),4,1))*53+VALUE(MID(TEXT(D35,"000000000000000"),3,1))*59+VALUE(MID(TEXT(D35,"000000000000000"),2,1))*67+VALUE(MID(TEXT(D35,"000000000000000"),1,1))*71),11))=1,1,11-(MOD((VALUE(MID(TEXT(D35,"000000000000000"),15,1))*3+VALUE(MID(TEXT(D35,"000000000000000"),14,1))*7+VALUE(MID(TEXT(D35,"000000000000000"),13,1))*13+VALUE(MID(TEXT(D35,"000000000000000"),12,1))*17+VALUE(MID(TEXT(D35,"000000000000000"),11,1))*19+VALUE(MID(TEXT(D35,"000000000000000"),10,1))*23+VALUE(MID(TEXT(D35,"000000000000000"),9,1))*29+VALUE(MID(TEXT(D35,"000000000000000"),8,1))*37+VALUE(MID(TEXT(D35,"000000000000000"),7,1))*41+VALUE(MID(TEXT(D35,"000000000000000"),6,1))*43+VALUE(MID(TEXT(D35,"000000000000000"),5,1))*47+VALUE(MID(TEXT(D35,"000000000000000"),4,1))*53+VALUE(MID(TEXT(D35,"000000000000000"),3,1))*59+VALUE(MID(TEXT(D35,"000000000000000"),2,1))*67+VALUE(MID(TEXT(D35,"000000000000000"),1,1))*71),11)))) -> 0 | F35: =+AN35 -> 1900000 | G35: =+F35*$G$5 -> 361000 | H35: S | I35: =IF(H35="S",-F35*$I$5,"NO RETENCIÓN") -> -209000 | J35: =+F35+G35 -> 2261000 | K35: =SUM(F35:I35) -> 2052000 | M35: GTFF-184 | N35: Correo | O35: 45987 | R35: =+AM35 -> 0 | T35: Fra con -Truly Nolen | V35: SI | W35: =ROUND(IF(V35="SI",SUMIF('Facturas año anterior'!$B$8:$B$81,B35,'Facturas año anterior'!$V$8:$V$81)*(100%+$W$5),0),-3)+ROUND(IF(V35="SI",SUMIF('C de C año anterior'!$B$8:$B$210,B35,'C de C año anterior'!$Q$8:$Q$210)*(100%+$W$5),0),-3) -> 1904000 | Y35: =ROUND(IF(X35="SI",W35*$Y$5,0),-3) -> 0 | AA35: =ROUND(IF(Z35="SI",W35*$AA$5,0),-3) -> 0 | AC35: =ROUND(IF(AB35="SI",W35*$AC$5,0),-3) -> 0 | AE35: =ROUND(IF(AD35="SI",W35*$AE$5,0),-3) -> 0 | AG35: =ROUND(IF(AF35="SI",W35*$AG$5,0),-3) -> 0 | AI35: =ROUND(IF(AH35="SI",W35*$AI$5,0),-3) -> 0 | AK35: =IF(AJ35="SI",W35*$AK$5,0) -> 0 | AL35: =SUMIF('Otras Asesorías y Préstamos'!$B$7:$B$242,B35,'Otras Asesorías y Préstamos'!$F$7:$F$242) -> 0 | AM35: =SUMIF('Otras Asesorías y Préstamos'!$B$7:$B$242,B35,'Otras Asesorías y Préstamos'!$V$7:$V$242) -> 0 | AN35: =ROUND(SUM(W35:AL35),-4) -> 1900000
A36: =+A35+1 -> 28 | B36: VILLEGAS ECHAVARRÍA LUÍS CARLOS GILBERTO | C36: =_xlfn.XLOOKUP(B36,Códigos!$B$8:$B$406,Códigos!$A$8:$A$406,"Verificar",0) -> 208 | D36: =_xlfn.XLOOKUP(B36,'Consolidado Cobros'!$B$10:$B$312,'Consolidado Cobros'!$C$10:$C$312,"Verificar",0) -> 70569069 | E36: =IF((MOD((VALUE(MID(TEXT(D36,"000000000000000"),15,1))*3+VALUE(MID(TEXT(D36,"000000000000000"),14,1))*7+VALUE(MID(TEXT(D36,"000000000000000"),13,1))*13+VALUE(MID(TEXT(D36,"000000000000000"),12,1))*17+VALUE(MID(TEXT(D36,"000000000000000"),11,1))*19+VALUE(MID(TEXT(D36,"000000000000000"),10,1))*23+VALUE(MID(TEXT(D36,"000000000000000"),9,1))*29+VALUE(MID(TEXT(D36,"000000000000000"),8,1))*37+VALUE(MID(TEXT(D36,"000000000000000"),7,1))*41+VALUE(MID(TEXT(D36,"000000000000000"),6,1))*43+VALUE(MID(TEXT(D36,"000000000000000"),5,1))*47+VALUE(MID(TEXT(D36,"000000000000000"),4,1))*53+VALUE(MID(TEXT(D36,"000000000000000"),3,1))*59+VALUE(MID(TEXT(D36,"000000000000000"),2,1))*67+VALUE(MID(TEXT(D36,"000000000000000"),1,1))*71),11))=0,0,IF((MOD((VALUE(MID(TEXT(D36,"000000000000000"),15,1))*3+VALUE(MID(TEXT(D36,"000000000000000"),14,1))*7+VALUE(MID(TEXT(D36,"000000000000000"),13,1))*13+VALUE(MID(TEXT(D36,"000000000000000"),12,1))*17+VALUE(MID(TEXT(D36,"000000000000000"),11,1))*19+VALUE(MID(TEXT(D36,"000000000000000"),10,1))*23+VALUE(MID(TEXT(D36,"000000000000000"),9,1))*29+VALUE(MID(TEXT(D36,"000000000000000"),8,1))*37+VALUE(MID(TEXT(D36,"000000000000000"),7,1))*41+VALUE(MID(TEXT(D36,"000000000000000"),6,1))*43+VALUE(MID(TEXT(D36,"000000000000000"),5,1))*47+VALUE(MID(TEXT(D36,"000000000000000"),4,1))*53+VALUE(MID(TEXT(D36,"000000000000000"),3,1))*59+VALUE(MID(TEXT(D36,"000000000000000"),2,1))*67+VALUE(MID(TEXT(D36,"000000000000000"),1,1))*71),11))=1,1,11-(MOD((VALUE(MID(TEXT(D36,"000000000000000"),15,1))*3+VALUE(MID(TEXT(D36,"000000000000000"),14,1))*7+VALUE(MID(TEXT(D36,"000000000000000"),13,1))*13+VALUE(MID(TEXT(D36,"000000000000000"),12,1))*17+VALUE(MID(TEXT(D36,"000000000000000"),11,1))*19+VALUE(MID(TEXT(D36,"000000000000000"),10,1))*23+VALUE(MID(TEXT(D36,"000000000000000"),9,1))*29+VALUE(MID(TEXT(D36,"000000000000000"),8,1))*37+VALUE(MID(TEXT(D36,"000000000000000"),7,1))*41+VALUE(MID(TEXT(D36,"000000000000000"),6,1))*43+VALUE(MID(TEXT(D36,"000000000000000"),5,1))*47+VALUE(MID(TEXT(D36,"000000000000000"),4,1))*53+VALUE(MID(TEXT(D36,"000000000000000"),3,1))*59+VALUE(MID(TEXT(D36,"000000000000000"),2,1))*67+VALUE(MID(TEXT(D36,"000000000000000"),1,1))*71),11)))) -> 5 | F36: =+AN36 -> 1900000 | G36: =+F36*$G$5 -> 361000 | H36: S | I36: =IF(H36="S",-F36*$I$5,"NO RETENCIÓN") -> -209000 | J36: =+F36+G36 -> 2261000 | K36: =SUM(F36:I36) -> 2052000 | M36: GTFF-184 | N36: Correo | O36: 45987 | R36: =+AM36 -> 0 | T36: Fra con -Truly Nolen | V36: SI | W36: =ROUND(IF(V36="SI",SUMIF('Facturas año anterior'!$B$8:$B$81,B36,'Facturas año anterior'!$V$8:$V$81)*(100%+$W$5),0),-3)+ROUND(IF(V36="SI",SUMIF('C de C año anterior'!$B$8:$B$210,B36,'C de C año anterior'!$Q$8:$Q$210)*(100%+$W$5),0),-3) -> 1904000 | Y36: =ROUND(IF(X36="SI",W36*$Y$5,0),-3) -> 0 | AA36: =ROUND(IF(Z36="SI",W36*$AA$5,0),-3) -> 0 | AC36: =ROUND(IF(AB36="SI",W36*$AC$5,0),-3) -> 0 | AE36: =ROUND(IF(AD36="SI",W36*$AE$5,0),-3) -> 0 | AG36: =ROUND(IF(AF36="SI",W36*$AG$5,0),-3) -> 0 | AI36: =ROUND(IF(AH36="SI",W36*$AI$5,0),-3) -> 0 | AK36: =IF(AJ36="SI",W36*$AK$5,0) -> 0 | AL36: =SUMIF('Otras Asesorías y Préstamos'!$B$7:$B$242,B36,'Otras Asesorías y Préstamos'!$F$7:$F$242) -> 0 | AM36: =SUMIF('Otras Asesorías y Préstamos'!$B$7:$B$242,B36,'Otras Asesorías y Préstamos'!$V$7:$V$242) -> 0 | AN36: =ROUND(SUM(W36:AL36),-4) -> 1900000
A37: =+A36+1 -> 29 | B37: VILLEGAS LONDOÑO LUÍS HERNANDO | C37: =_xlfn.XLOOKUP(B37,Códigos!$B$8:$B$406,Códigos!$A$8:$A$406,"Verificar",0) -> 211 | D37: =_xlfn.XLOOKUP(B37,'Consolidado Cobros'!$B$10:$B$312,'Consolidado Cobros'!$C$10:$C$312,"Verificar",0) -> 8252575 | E37: =IF((MOD((VALUE(MID(TEXT(D37,"000000000000000"),15,1))*3+VALUE(MID(TEXT(D37,"000000000000000"),14,1))*7+VALUE(MID(TEXT(D37,"000000000000000"),13,1))*13+VALUE(MID(TEXT(D37,"000000000000000"),12,1))*17+VALUE(MID(TEXT(D37,"000000000000000"),11,1))*19+VALUE(MID(TEXT(D37,"000000000000000"),10,1))*23+VALUE(MID(TEXT(D37,"000000000000000"),9,1))*29+VALUE(MID(TEXT(D37,"000000000000000"),8,1))*37+VALUE(MID(TEXT(D37,"000000000000000"),7,1))*41+VALUE(MID(TEXT(D37,"000000000000000"),6,1))*43+VALUE(MID(TEXT(D37,"000000000000000"),5,1))*47+VALUE(MID(TEXT(D37,"000000000000000"),4,1))*53+VALUE(MID(TEXT(D37,"000000000000000"),3,1))*59+VALUE(MID(TEXT(D37,"000000000000000"),2,1))*67+VALUE(MID(TEXT(D37,"000000000000000"),1,1))*71),11))=0,0,IF((MOD((VALUE(MID(TEXT(D37,"000000000000000"),15,1))*3+VALUE(MID(TEXT(D37,"000000000000000"),14,1))*7+VALUE(MID(TEXT(D37,"000000000000000"),13,1))*13+VALUE(MID(TEXT(D37,"000000000000000"),12,1))*17+VALUE(MID(TEXT(D37,"000000000000000"),11,1))*19+VALUE(MID(TEXT(D37,"000000000000000"),10,1))*23+VALUE(MID(TEXT(D37,"000000000000000"),9,1))*29+VALUE(MID(TEXT(D37,"000000000000000"),8,1))*37+VALUE(MID(TEXT(D37,"000000000000000"),7,1))*41+VALUE(MID(TEXT(D37,"000000000000000"),6,1))*43+VALUE(MID(TEXT(D37,"000000000000000"),5,1))*47+VALUE(MID(TEXT(D37,"000000000000000"),4,1))*53+VALUE(MID(TEXT(D37,"000000000000000"),3,1))*59+VALUE(MID(TEXT(D37,"000000000000000"),2,1))*67+VALUE(MID(TEXT(D37,"000000000000000"),1,1))*71),11))=1,1,11-(MOD((VALUE(MID(TEXT(D37,"000000000000000"),15,1))*3+VALUE(MID(TEXT(D37,"000000000000000"),14,1))*7+VALUE(MID(TEXT(D37,"000000000000000"),13,1))*13+VALUE(MID(TEXT(D37,"000000000000000"),12,1))*17+VALUE(MID(TEXT(D37,"000000000000000"),11,1))*19+VALUE(MID(TEXT(D37,"000000000000000"),10,1))*23+VALUE(MID(TEXT(D37,"000000000000000"),9,1))*29+VALUE(MID(TEXT(D37,"000000000000000"),8,1))*37+VALUE(MID(TEXT(D37,"000000000000000"),7,1))*41+VALUE(MID(TEXT(D37,"000000000000000"),6,1))*43+VALUE(MID(TEXT(D37,"000000000000000"),5,1))*47+VALUE(MID(TEXT(D37,"000000000000000"),4,1))*53+VALUE(MID(TEXT(D37,"000000000000000"),3,1))*59+VALUE(MID(TEXT(D37,"000000000000000"),2,1))*67+VALUE(MID(TEXT(D37,"000000000000000"),1,1))*71),11)))) -> 3 | F37: =+AN37 -> 1900000 | G37: =+F37*$G$5 -> 361000 | H37: S | I37: =IF(H37="S",-F37*$I$5,"NO RETENCIÓN") -> -209000 | J37: =+F37+G37 -> 2261000 | K37: =SUM(F37:I37) -> 2052000 | M37: GTFF-184 | N37: Correo | O37: 45987 | R37: =+AM37 -> 0 | T37: Fra con -Truly Nolen | V37: SI | W37: =ROUND(IF(V37="SI",SUMIF('Facturas año anterior'!$B$8:$B$81,B37,'Facturas año anterior'!$V$8:$V$81)*(100%+$W$5),0),-3)+ROUND(IF(V37="SI",SUMIF('C de C año anterior'!$B$8:$B$210,B37,'C de C año anterior'!$Q$8:$Q$210)*(100%+$W$5),0),-3) -> 1904000 | Y37: =ROUND(IF(X37="SI",W37*$Y$5,0),-3) -> 0 | AA37: =ROUND(IF(Z37="SI",W37*$AA$5,0),-3) -> 0 | AC37: =ROUND(IF(AB37="SI",W37*$AC$5,0),-3) -> 0 | AE37: =ROUND(IF(AD37="SI",W37*$AE$5,0),-3) -> 0 | AG37: =ROUND(IF(AF37="SI",W37*$AG$5,0),-3) -> 0 | AI37: =ROUND(IF(AH37="SI",W37*$AI$5,0),-3) -> 0 | AK37: =IF(AJ37="SI",W37*$AK$5,0) -> 0 | AL37: =SUMIF('Otras Asesorías y Préstamos'!$B$7:$B$242,B37,'Otras Asesorías y Préstamos'!$F$7:$F$242) -> 0 | AM37: =SUMIF('Otras Asesorías y Préstamos'!$B$7:$B$242,B37,'Otras Asesorías y Préstamos'!$V$7:$V$242) -> 0 | AN37: =ROUND(SUM(W37:AL37),-4) -> 1900000
W38: =ROUND(IF(V38="SI",SUMIF('Facturas año anterior'!$B$8:$B$81,B38,'Facturas año anterior'!$V$8:$V$81)*(100%+$W$5),0),-3)+ROUND(IF(V38="SI",SUMIF('C de C año anterior'!$B$8:$B$210,B38,'C de C año anterior'!$F$8:$F$210)*(100%+$W$5),0),-3) -> 0 | Y38: =ROUND(IF(X38="SI",W38*$Y$5,0),-3) -> 0 | AA38: =ROUND(IF(Z38="SI",W38*$AA$5,0),-3) -> 0 | AC38: =ROUND(IF(AB38="SI",W38*$AC$5,0),-3) -> 0 | AE38: =ROUND(IF(AD38="SI",W38*$AE$5,0),-3) -> 0 | AG38: =ROUND(IF(AF38="SI",W38*$AG$5,0),-3) -> 0 | AI38: =ROUND(IF(AH38="SI",W38*$AI$5,0),-3) -> 0 | AK38: =IF(AJ38="SI",W38*$AK$5,0) -> 0 | AL38: =SUMIF('Otras Asesorías y Préstamos'!$B$7:$B$242,B38,'Otras Asesorías y Préstamos'!$F$7:$F$242) -> 0 | AM38: =SUMIF('Otras Asesorías y Préstamos'!$B$7:$B$242,B38,'Otras Asesorías y Préstamos'!$V$7:$V$242) -> 0 | AN38: =ROUND(SUM(W38:AL38),-4) -> 0
W39: =ROUND(IF(V39="SI",SUMIF('Facturas año anterior'!$B$8:$B$81,B39,'Facturas año anterior'!$V$8:$V$81)*(100%+$W$5),0),-3)+ROUND(IF(V39="SI",SUMIF('C de C año anterior'!$B$8:$B$210,B39,'C de C año anterior'!$F$8:$F$210)*(100%+$W$5),0),-3) -> 0 | Y39: =ROUND(IF(X39="SI",W39*$Y$5,0),-3) -> 0 | AA39: =ROUND(IF(Z39="SI",W39*$AA$5,0),-3) -> 0 | AC39: =ROUND(IF(AB39="SI",W39*$AC$5,0),-3) -> 0 | AE39: =ROUND(IF(AD39="SI",W39*$AE$5,0),-3) -> 0 | AG39: =ROUND(IF(AF39="SI",W39*$AG$5,0),-3) -> 0 | AI39: =ROUND(IF(AH39="SI",W39*$AI$5,0),-3) -> 0 | AK39: =IF(AJ39="SI",W39*$AK$5,0) -> 0 | AL39: =SUMIF('Otras Asesorías y Préstamos'!$B$7:$B$242,B39,'Otras Asesorías y Préstamos'!$F$7:$F$242) -> 0 | AM39: =SUMIF('Otras Asesorías y Préstamos'!$B$7:$B$242,B39,'Otras Asesorías y Préstamos'!$V$7:$V$242) -> 0 | AN39: =ROUND(SUM(W39:AL39),-4) -> 0
W40: =ROUND(IF(V40="SI",SUMIF('Facturas año anterior'!$B$8:$B$81,B40,'Facturas año anterior'!$V$8:$V$81)*(100%+$W$5),0),-3)+ROUND(IF(V40="SI",SUMIF('C de C año anterior'!$B$8:$B$210,B40,'C de C año anterior'!$F$8:$F$210)*(100%+$W$5),0),-3) -> 0 | Y40: =ROUND(IF(X40="SI",W40*$Y$5,0),-3) -> 0 | AA40: =ROUND(IF(Z40="SI",W40*$AA$5,0),-3) -> 0 | AC40: =ROUND(IF(AB40="SI",W40*$AC$5,0),-3) -> 0 | AE40: =ROUND(IF(AD40="SI",W40*$AE$5,0),-3) -> 0 | AG40: =ROUND(IF(AF40="SI",W40*$AG$5,0),-3) -> 0 | AI40: =ROUND(IF(AH40="SI",W40*$AI$5,0),-3) -> 0 | AK40: =IF(AJ40="SI",W40*$AK$5,0) -> 0 | AL40: =SUMIF('Otras Asesorías y Préstamos'!$B$7:$B$242,B40,'Otras Asesorías y Préstamos'!$F$7:$F$242) -> 0 | AM40: =SUMIF('Otras Asesorías y Préstamos'!$B$7:$B$242,B40,'Otras Asesorías y Préstamos'!$V$7:$V$242) -> 0 | AN40: =ROUND(SUM(W40:AL40),-4) -> 0
W41: =ROUND(IF(V41="SI",SUMIF('Facturas año anterior'!$B$8:$B$81,B41,'Facturas año anterior'!$V$8:$V$81)*(100%+$W$5),0),-3)+ROUND(IF(V41="SI",SUMIF('C de C año anterior'!$B$8:$B$210,B41,'C de C año anterior'!$F$8:$F$210)*(100%+$W$5),0),-3) -> 0 | Y41: =ROUND(IF(X41="SI",W41*$Y$5,0),-3) -> 0 | AA41: =ROUND(IF(Z41="SI",W41*$AA$5,0),-3) -> 0 | AC41: =ROUND(IF(AB41="SI",W41*$AC$5,0),-3) -> 0 | AE41: =ROUND(IF(AD41="SI",W41*$AE$5,0),-3) -> 0 | AG41: =ROUND(IF(AF41="SI",W41*$AG$5,0),-3) -> 0 | AI41: =ROUND(IF(AH41="SI",W41*$AI$5,0),-3) -> 0 | AK41: =IF(AJ41="SI",W41*$AK$5,0) -> 0 | AL41: =SUMIF('Otras Asesorías y Préstamos'!$B$7:$B$242,B41,'Otras Asesorías y Préstamos'!$F$7:$F$242) -> 0 | AM41: =SUMIF('Otras Asesorías y Préstamos'!$B$7:$B$242,B41,'Otras Asesorías y Préstamos'!$V$7:$V$242) -> 0 | AN41: =ROUND(SUM(W41:AL41),-4) -> 0
W42: =ROUND(IF(V42="SI",SUMIF('Facturas año anterior'!$B$8:$B$81,B42,'Facturas año anterior'!$V$8:$V$81)*(100%+$W$5),0),-3)+ROUND(IF(V42="SI",SUMIF('C de C año anterior'!$B$8:$B$210,B42,'C de C año anterior'!$F$8:$F$210)*(100%+$W$5),0),-3) -> 0 | Y42: =ROUND(IF(X42="SI",W42*$Y$5,0),-3) -> 0 | AA42: =ROUND(IF(Z42="SI",W42*$AA$5,0),-3) -> 0 | AC42: =ROUND(IF(AB42="SI",W42*$AC$5,0),-3) -> 0 | AE42: =ROUND(IF(AD42="SI",W42*$AE$5,0),-3) -> 0 | AG42: =ROUND(IF(AF42="SI",W42*$AG$5,0),-3) -> 0 | AI42: =ROUND(IF(AH42="SI",W42*$AI$5,0),-3) -> 0 | AK42: =IF(AJ42="SI",W42*$AK$5,0) -> 0 | AL42: =SUMIF('Otras Asesorías y Préstamos'!$B$7:$B$242,B42,'Otras Asesorías y Préstamos'!$F$7:$F$242) -> 0 | AM42: =SUMIF('Otras Asesorías y Préstamos'!$B$7:$B$242,B42,'Otras Asesorías y Préstamos'!$V$7:$V$242) -> 0 | AN42: =ROUND(SUM(W42:AL42),-4) -> 0
W43: =ROUND(IF(V43="SI",SUMIF('Facturas año anterior'!$B$8:$B$81,B43,'Facturas año anterior'!$V$8:$V$81)*(100%+$W$5),0),-3)+ROUND(IF(V43="SI",SUMIF('C de C año anterior'!$B$8:$B$210,B43,'C de C año anterior'!$F$8:$F$210)*(100%+$W$5),0),-3) -> 0 | Y43: =ROUND(IF(X43="SI",W43*$Y$5,0),-3) -> 0 | AA43: =ROUND(IF(Z43="SI",W43*$AA$5,0),-3) -> 0 | AC43: =ROUND(IF(AB43="SI",W43*$AC$5,0),-3) -> 0 | AE43: =ROUND(IF(AD43="SI",W43*$AE$5,0),-3) -> 0 | AG43: =ROUND(IF(AF43="SI",W43*$AG$5,0),-3) -> 0 | AI43: =ROUND(IF(AH43="SI",W43*$AI$5,0),-3) -> 0 | AK43: =IF(AJ43="SI",W43*$AK$5,0) -> 0 | AL43: =SUMIF('Otras Asesorías y Préstamos'!$B$7:$B$242,B43,'Otras Asesorías y Préstamos'!$F$7:$F$242) -> 0 | AM43: =SUMIF('Otras Asesorías y Préstamos'!$B$7:$B$242,B43,'Otras Asesorías y Préstamos'!$V$7:$V$242) -> 0 | AN43: =ROUND(SUM(W43:AL43),-4) -> 0
W44: =ROUND(IF(V44="SI",SUMIF('Facturas año anterior'!$B$8:$B$81,B44,'Facturas año anterior'!$V$8:$V$81)*(100%+$W$5),0),-3)+ROUND(IF(V44="SI",SUMIF('C de C año anterior'!$B$8:$B$210,B44,'C de C año anterior'!$F$8:$F$210)*(100%+$W$5),0),-3) -> 0 | Y44: =ROUND(IF(X44="SI",W44*$Y$5,0),-3) -> 0 | AA44: =ROUND(IF(Z44="SI",W44*$AA$5,0),-3) -> 0 | AC44: =ROUND(IF(AB44="SI",W44*$AC$5,0),-3) -> 0 | AE44: =ROUND(IF(AD44="SI",W44*$AE$5,0),-3) -> 0 | AG44: =ROUND(IF(AF44="SI",W44*$AG$5,0),-3) -> 0 | AI44: =ROUND(IF(AH44="SI",W44*$AI$5,0),-3) -> 0 | AK44: =IF(AJ44="SI",W44*$AK$5,0) -> 0 | AL44: =SUMIF('Otras Asesorías y Préstamos'!$B$7:$B$242,B44,'Otras Asesorías y Préstamos'!$F$7:$F$242) -> 0 | AM44: =SUMIF('Otras Asesorías y Préstamos'!$B$7:$B$242,B44,'Otras Asesorías y Préstamos'!$V$7:$V$242) -> 0 | AN44: =ROUND(SUM(W44:AL44),-4) -> 0
W45: =ROUND(IF(V45="SI",SUMIF('Facturas año anterior'!$B$8:$B$81,B45,'Facturas año anterior'!$V$8:$V$81)*(100%+$W$5),0),-3)+ROUND(IF(V45="SI",SUMIF('C de C año anterior'!$B$8:$B$210,B45,'C de C año anterior'!$F$8:$F$210)*(100%+$W$5),0),-3) -> 0 | Y45: =ROUND(IF(X45="SI",W45*$Y$5,0),-3) -> 0 | AA45: =ROUND(IF(Z45="SI",W45*$AA$5,0),-3) -> 0 | AC45: =ROUND(IF(AB45="SI",W45*$AC$5,0),-3) -> 0 | AE45: =ROUND(IF(AD45="SI",W45*$AE$5,0),-3) -> 0 | AG45: =ROUND(IF(AF45="SI",W45*$AG$5,0),-3) -> 0 | AI45: =ROUND(IF(AH45="SI",W45*$AI$5,0),-3) -> 0 | AK45: =IF(AJ45="SI",W45*$AK$5,0) -> 0 | AL45: =SUMIF('Otras Asesorías y Préstamos'!$B$7:$B$242,B45,'Otras Asesorías y Préstamos'!$F$7:$F$242) -> 0 | AM45: =SUMIF('Otras Asesorías y Préstamos'!$B$7:$B$242,B45,'Otras Asesorías y Préstamos'!$V$7:$V$242) -> 0 | AN45: =ROUND(SUM(W45:AL45),-4) -> 0
W46: =ROUND(IF(V46="SI",SUMIF('Facturas año anterior'!$B$8:$B$81,B46,'Facturas año anterior'!$V$8:$V$81)*(100%+$W$5),0),-3)+ROUND(IF(V46="SI",SUMIF('C de C año anterior'!$B$8:$B$210,B46,'C de C año anterior'!$F$8:$F$210)*(100%+$W$5),0),-3) -> 0 | Y46: =ROUND(IF(X46="SI",W46*$Y$5,0),-3) -> 0 | AA46: =ROUND(IF(Z46="SI",W46*$AA$5,0),-3) -> 0 | AC46: =ROUND(IF(AB46="SI",W46*$AC$5,0),-3) -> 0 | AE46: =ROUND(IF(AD46="SI",W46*$AE$5,0),-3) -> 0 | AG46: =ROUND(IF(AF46="SI",W46*$AG$5,0),-3) -> 0 | AI46: =ROUND(IF(AH46="SI",W46*$AI$5,0),-3) -> 0 | AK46: =IF(AJ46="SI",W46*$AK$5,0) -> 0 | AL46: =SUMIF('Otras Asesorías y Préstamos'!$B$7:$B$242,B46,'Otras Asesorías y Préstamos'!$F$7:$F$242) -> 0 | AM46: =SUMIF('Otras Asesorías y Préstamos'!$B$7:$B$242,B46,'Otras Asesorías y Préstamos'!$V$7:$V$242) -> 0 | AN46: =ROUND(SUM(W46:AL46),-4) -> 0
A49: TOTAL PERSONAS NATURALES | F49: =SUM(F9:F47) -> 37600000 | G49: =SUM(G9:G47) -> 7144000 | I49: =SUM(I9:I47) -> -3248300 | J49: =SUM(J9:J47) -> 44744000 | K49: =SUM(K9:K47) -> 41495700 | W49: =SUM(W9:W47) -> 29412000 | Y49: =SUM(Y9:Y47) -> 497000 | AA49: =SUM(AA9:AA47) -> 2081000 | AC49: =SUM(AC9:AC47) -> 0 | AE49: =SUM(AE9:AE47) -> 0 | AG49: =SUM(AG9:AG47) -> 0 | AI49: =SUM(AI9:AI47) -> 234000 | AK49: =SUM(AK9:AK47) -> 2641800 | AL49: =SUM(AL9:AL47) -> 2756168.3 | AM49: =SUM(AM9:AM47) -> 0 | AN49: =SUM(AN9:AN47) -> 37600000
C51: =+A37 -> 29
A53: PERSONAS JURÍDICAS
A54: 1 | B54: ARRENDAMIENTOS EL CAMPESTRE S A S | C54: =_xlfn.XLOOKUP(B54,Códigos!$B$8:$B$406,Códigos!$A$8:$A$406,"Verificar",0) -> 1 | D54: =_xlfn.XLOOKUP(B54,'Consolidado Cobros'!$B$10:$B$312,'Consolidado Cobros'!$C$10:$C$312,"Verificar",0) -> 811032632 | E54: =IF((MOD((VALUE(MID(TEXT(D54,"000000000000000"),15,1))*3+VALUE(MID(TEXT(D54,"000000000000000"),14,1))*7+VALUE(MID(TEXT(D54,"000000000000000"),13,1))*13+VALUE(MID(TEXT(D54,"000000000000000"),12,1))*17+VALUE(MID(TEXT(D54,"000000000000000"),11,1))*19+VALUE(MID(TEXT(D54,"000000000000000"),10,1))*23+VALUE(MID(TEXT(D54,"000000000000000"),9,1))*29+VALUE(MID(TEXT(D54,"000000000000000"),8,1))*37+VALUE(MID(TEXT(D54,"000000000000000"),7,1))*41+VALUE(MID(TEXT(D54,"000000000000000"),6,1))*43+VALUE(MID(TEXT(D54,"000000000000000"),5,1))*47+VALUE(MID(TEXT(D54,"000000000000000"),4,1))*53+VALUE(MID(TEXT(D54,"000000000000000"),3,1))*59+VALUE(MID(TEXT(D54,"000000000000000"),2,1))*67+VALUE(MID(TEXT(D54,"000000000000000"),1,1))*71),11))=0,0,IF((MOD((VALUE(MID(TEXT(D54,"000000000000000"),15,1))*3+VALUE(MID(TEXT(D54,"000000000000000"),14,1))*7+VALUE(MID(TEXT(D54,"000000000000000"),13,1))*13+VALUE(MID(TEXT(D54,"000000000000000"),12,1))*17+VALUE(MID(TEXT(D54,"000000000000000"),11,1))*19+VALUE(MID(TEXT(D54,"000000000000000"),10,1))*23+VALUE(MID(TEXT(D54,"000000000000000"),9,1))*29+VALUE(MID(TEXT(D54,"000000000000000"),8,1))*37+VALUE(MID(TEXT(D54,"000000000000000"),7,1))*41+VALUE(MID(TEXT(D54,"000000000000000"),6,1))*43+VALUE(MID(TEXT(D54,"000000000000000"),5,1))*47+VALUE(MID(TEXT(D54,"000000000000000"),4,1))*53+VALUE(MID(TEXT(D54,"000000000000000"),3,1))*59+VALUE(MID(TEXT(D54,"000000000000000"),2,1))*67+VALUE(MID(TEXT(D54,"000000000000000"),1,1))*71),11))=1,1,11-(MOD((VALUE(MID(TEXT(D54,"000000000000000"),15,1))*3+VALUE(MID(TEXT(D54,"000000000000000"),14,1))*7+VALUE(MID(TEXT(D54,"000000000000000"),13,1))*13+VALUE(MID(TEXT(D54,"000000000000000"),12,1))*17+VALUE(MID(TEXT(D54,"000000000000000"),11,1))*19+VALUE(MID(TEXT(D54,"000000000000000"),10,1))*23+VALUE(MID(TEXT(D54,"000000000000000"),9,1))*29+VALUE(MID(TEXT(D54,"000000000000000"),8,1))*37+VALUE(MID(TEXT(D54,"000000000000000"),7,1))*41+VALUE(MID(TEXT(D54,"000000000000000"),6,1))*43+VALUE(MID(TEXT(D54,"000000000000000"),5,1))*47+VALUE(MID(TEXT(D54,"000000000000000"),4,1))*53+VALUE(MID(TEXT(D54,"000000000000000"),3,1))*59+VALUE(MID(TEXT(D54,"000000000000000"),2,1))*67+VALUE(MID(TEXT(D54,"000000000000000"),1,1))*71),11)))) -> 4 | F54: =+AN54 -> 2241000 | G54: =+F54*$G$5 -> 425790 | H54: S | I54: =IF(H54="S",-F54*$I$5,"NO RETENCIÓN") -> -246510 | J54: =+F54+G54 -> 2666790 | K54: =SUM(F54:I54) -> 2420280 | M54: GTFF-167 | N54: Correo y Wpp | O54: 45986 | P54: PENDIENTE | Q54: OBSERVACIONES | R54: =+AM54 -> 0 | T54: Fra más -TORRES SÁNCHEZ OMAR WINSTON -Ver Grupos Familiares- | V54: SI | W54: =ROUND(IF(V54="SI",SUMIF('Facturas año anterior'!$B$8:$B$81,B54,'Facturas año anterior'!$V$8:$V$81)*(100%+$W$5),0),-3)+ROUND(IF(V54="SI",SUMIF('C de C año anterior'!$B$8:$B$210,B54,'C de C año anterior'!$Q$8:$Q$210)*(100%+$W$5),0),-3) -> 1168000 | Y54: =ROUND(IF(X54="SI",W54*$Y$5,0),-3) -> 0 | Z54: SI | AA54: =ROUND(IF(Z54="SI",W54*$AA$5,0),-3) -> 876000 | AC54: =ROUND(IF(AB54="SI",W54*$AC$5,0),-3) -> 0 | AE54: =ROUND(IF(AD54="SI",W54*$AE$5,0),-3) -> 0 | AF54: SI | AG54: =ROUND(IF(AF54="SI",W54*$AG$5,0),-3) -> 117000 | AI54: =ROUND(IF(AH54="SI",W54*$AI$5,0),-3) -> 0 | AK54: =IF(AJ54="SI",W54*$AK$5,0) -> 0 | AL54: =SUMIF('Otras Asesorías y Préstamos'!$B$7:$B$242,B54,'Otras Asesorías y Préstamos'!$F$7:$F$242) -> 80000 | AM54: =SUMIF('Otras Asesorías y Préstamos'!$B$7:$B$242,B54,'Otras Asesorías y Préstamos'!$V$7:$V$242) -> 0 | AN54: =ROUND(SUM(W54:AL54),-3) -> 2241000
A55: =+A54+1 -> 2 | B55: CAÑO PALMA S A S | C55: =_xlfn.XLOOKUP(B55,Códigos!$B$8:$B$406,Códigos!$A$8:$A$406,"Verificar",0) -> 246 | D55: =_xlfn.XLOOKUP(B55,'Consolidado Cobros'!$B$10:$B$312,'Consolidado Cobros'!$C$10:$C$312,"Verificar",0) -> 900650238 | E55: =IF((MOD((VALUE(MID(TEXT(D55,"000000000000000"),15,1))*3+VALUE(MID(TEXT(D55,"000000000000000"),14,1))*7+VALUE(MID(TEXT(D55,"000000000000000"),13,1))*13+VALUE(MID(TEXT(D55,"000000000000000"),12,1))*17+VALUE(MID(TEXT(D55,"000000000000000"),11,1))*19+VALUE(MID(TEXT(D55,"000000000000000"),10,1))*23+VALUE(MID(TEXT(D55,"000000000000000"),9,1))*29+VALUE(MID(TEXT(D55,"000000000000000"),8,1))*37+VALUE(MID(TEXT(D55,"000000000000000"),7,1))*41+VALUE(MID(TEXT(D55,"000000000000000"),6,1))*43+VALUE(MID(TEXT(D55,"000000000000000"),5,1))*47+VALUE(MID(TEXT(D55,"000000000000000"),4,1))*53+VALUE(MID(TEXT(D55,"000000000000000"),3,1))*59+VALUE(MID(TEXT(D55,"000000000000000"),2,1))*67+VALUE(MID(TEXT(D55,"000000000000000"),1,1))*71),11))=0,0,IF((MOD((VALUE(MID(TEXT(D55,"000000000000000"),15,1))*3+VALUE(MID(TEXT(D55,"000000000000000"),14,1))*7+VALUE(MID(TEXT(D55,"000000000000000"),13,1))*13+VALUE(MID(TEXT(D55,"000000000000000"),12,1))*17+VALUE(MID(TEXT(D55,"000000000000000"),11,1))*19+VALUE(MID(TEXT(D55,"000000000000000"),10,1))*23+VALUE(MID(TEXT(D55,"000000000000000"),9,1))*29+VALUE(MID(TEXT(D55,"000000000000000"),8,1))*37+VALUE(MID(TEXT(D55,"000000000000000"),7,1))*41+VALUE(MID(TEXT(D55,"000000000000000"),6,1))*43+VALUE(MID(TEXT(D55,"000000000000000"),5,1))*47+VALUE(MID(TEXT(D55,"000000000000000"),4,1))*53+VALUE(MID(TEXT(D55,"000000000000000"),3,1))*59+VALUE(MID(TEXT(D55,"000000000000000"),2,1))*67+VALUE(MID(TEXT(D55,"000000000000000"),1,1))*71),11))=1,1,11-(MOD((VALUE(MID(TEXT(D55,"000000000000000"),15,1))*3+VALUE(MID(TEXT(D55,"000000000000000"),14,1))*7+VALUE(MID(TEXT(D55,"000000000000000"),13,1))*13+VALUE(MID(TEXT(D55,"000000000000000"),12,1))*17+VALUE(MID(TEXT(D55,"000000000000000"),11,1))*19+VALUE(MID(TEXT(D55,"000000000000000"),10,1))*23+VALUE(MID(TEXT(D55,"000000000000000"),9,1))*29+VALUE(MID(TEXT(D55,"000000000000000"),8,1))*37+VALUE(MID(TEXT(D55,"000000000000000"),7,1))*41+VALUE(MID(TEXT(D55,"000000000000000"),6,1))*43+VALUE(MID(TEXT(D55,"000000000000000"),5,1))*47+VALUE(MID(TEXT(D55,"000000000000000"),4,1))*53+VALUE(MID(TEXT(D55,"000000000000000"),3,1))*59+VALUE(MID(TEXT(D55,"000000000000000"),2,1))*67+VALUE(MID(TEXT(D55,"000000000000000"),1,1))*71),11)))) -> 9 | F55: =+AN55 -> 3004000 | G55: =+F55*$G$5 -> 570760 | H55: S | I55: =IF(H55="S",-F55*$I$5,"NO RETENCIÓN") -> -330440 | J55: =+F55+G55 -> 3574760 | K55: =SUM(F55:I55) -> 3244320 | M55: GTFF-177 | N55: Correo | O55: 45987 | R55: =+AM55 -> 0 | V55: SI | W55: =ROUND(IF(V55="SI",SUMIF('Facturas año anterior'!$B$8:$B$81,B55,'Facturas año anterior'!$V$8:$V$81)*(100%+$W$5),0),-3)+ROUND(IF(V55="SI",SUMIF('C de C año anterior'!$B$8:$B$210,B55,'C de C año anterior'!$Q$8:$Q$210)*(100%+$W$5),0),-3) -> 1424000 | Y55: =ROUND(IF(X55="SI",W55*$Y$5,0),-3) -> 0 | Z55: SI | AA55: =ROUND(IF(Z55="SI",W55*$AA$5,0),-3) -> 1068000 | AC55: =ROUND(IF(AB55="SI",W55*$AC$5,0),-3) -> 0 | AE55: =ROUND(IF(AD55="SI",W55*$AE$5,0),-3) -> 0 | AF55: SI | AG55: =ROUND(IF(AF55="SI",W55*$AG$5,0),-3) -> 142000 | AI55: =ROUND(IF(AH55="SI",W55*$AI$5,0),-3) -> 0 | AK55: =IF(AJ55="SI",W55*$AK$5,0) -> 0 | AL55: =SUMIF('Otras Asesorías y Préstamos'!$B$7:$B$242,B55,'Otras Asesorías y Préstamos'!$F$7:$F$242) -> 370000 | AM55: =SUMIF('Otras Asesorías y Préstamos'!$B$7:$B$242,B55,'Otras Asesorías y Préstamos'!$V$7:$V$242) -> 0 | AN55: =ROUND(SUM(W55:AL55),-3) -> 3004000
A56: =+A55+1 -> 3 | B56: CORRUFORMAS S A S | C56: =_xlfn.XLOOKUP(B56,Códigos!$B$8:$B$406,Códigos!$A$8:$A$406,"Verificar",0) -> 8 | D56: =_xlfn.XLOOKUP(B56,'Consolidado Cobros'!$B$10:$B$312,'Consolidado Cobros'!$C$10:$C$312,"Verificar",0) -> 811028472 | E56: =IF((MOD((VALUE(MID(TEXT(D56,"000000000000000"),15,1))*3+VALUE(MID(TEXT(D56,"000000000000000"),14,1))*7+VALUE(MID(TEXT(D56,"000000000000000"),13,1))*13+VALUE(MID(TEXT(D56,"000000000000000"),12,1))*17+VALUE(MID(TEXT(D56,"000000000000000"),11,1))*19+VALUE(MID(TEXT(D56,"000000000000000"),10,1))*23+VALUE(MID(TEXT(D56,"000000000000000"),9,1))*29+VALUE(MID(TEXT(D56,"000000000000000"),8,1))*37+VALUE(MID(TEXT(D56,"000000000000000"),7,1))*41+VALUE(MID(TEXT(D56,"000000000000000"),6,1))*43+VALUE(MID(TEXT(D56,"000000000000000"),5,1))*47+VALUE(MID(TEXT(D56,"000000000000000"),4,1))*53+VALUE(MID(TEXT(D56,"000000000000000"),3,1))*59+VALUE(MID(TEXT(D56,"000000000000000"),2,1))*67+VALUE(MID(TEXT(D56,"000000000000000"),1,1))*71),11))=0,0,IF((MOD((VALUE(MID(TEXT(D56,"000000000000000"),15,1))*3+VALUE(MID(TEXT(D56,"000000000000000"),14,1))*7+VALUE(MID(TEXT(D56,"000000000000000"),13,1))*13+VALUE(MID(TEXT(D56,"000000000000000"),12,1))*17+VALUE(MID(TEXT(D56,"000000000000000"),11,1))*19+VALUE(MID(TEXT(D56,"000000000000000"),10,1))*23+VALUE(MID(TEXT(D56,"000000000000000"),9,1))*29+VALUE(MID(TEXT(D56,"000000000000000"),8,1))*37+VALUE(MID(TEXT(D56,"000000000000000"),7,1))*41+VALUE(MID(TEXT(D56,"000000000000000"),6,1))*43+VALUE(MID(TEXT(D56,"000000000000000"),5,1))*47+VALUE(MID(TEXT(D56,"000000000000000"),4,1))*53+VALUE(MID(TEXT(D56,"000000000000000"),3,1))*59+VALUE(MID(TEXT(D56,"000000000000000"),2,1))*67+VALUE(MID(TEXT(D56,"000000000000000"),1,1))*71),11))=1,1,11-(MOD((VALUE(MID(TEXT(D56,"000000000000000"),15,1))*3+VALUE(MID(TEXT(D56,"000000000000000"),14,1))*7+VALUE(MID(TEXT(D56,"000000000000000"),13,1))*13+VALUE(MID(TEXT(D56,"000000000000000"),12,1))*17+VALUE(MID(TEXT(D56,"000000000000000"),11,1))*19+VALUE(MID(TEXT(D56,"000000000000000"),10,1))*23+VALUE(MID(TEXT(D56,"000000000000000"),9,1))*29+VALUE(MID(TEXT(D56,"000000000000000"),8,1))*37+VALUE(MID(TEXT(D56,"000000000000000"),7,1))*41+VALUE(MID(TEXT(D56,"000000000000000"),6,1))*43+VALUE(MID(TEXT(D56,"000000000000000"),5,1))*47+VALUE(MID(TEXT(D56,"000000000000000"),4,1))*53+VALUE(MID(TEXT(D56,"000000000000000"),3,1))*59+VALUE(MID(TEXT(D56,"000000000000000"),2,1))*67+VALUE(MID(TEXT(D56,"000000000000000"),1,1))*71),11)))) -> 7 | F56: =+AN56 -> 1707000 | G56: =+F56*$G$5 -> 324330 | H56: S | I56: =IF(H56="S",-F56*$I$5,"NO RETENCIÓN") -> -187770 | J56: =+F56+G56 -> 2031330 | K56: =SUM(F56:I56) -> 1843560 | M56: GTFF-188 | N56: Correo | O56: 45987 | R56: =+AM56 -> 0 | V56: SI | W56: =ROUND(IF(V56="SI",SUMIF('Facturas año anterior'!$B$8:$B$81,B56,'Facturas año anterior'!$V$8:$V$81)*(100%+$W$5),0),-3)+ROUND(IF(V56="SI",SUMIF('C de C año anterior'!$B$8:$B$210,B56,'C de C año anterior'!$Q$8:$Q$210)*(100%+$W$5),0),-3) -> 923000 | Y56: =ROUND(IF(X56="SI",W56*$Y$5,0),-3) -> 0 | Z56: SI | AA56: =ROUND(IF(Z56="SI",W56*$AA$5,0),-3) -> 692000 | AC56: =ROUND(IF(AB56="SI",W56*$AC$5,0),-3) -> 0 | AE56: =ROUND(IF(AD56="SI",W56*$AE$5,0),-3) -> 0 | AF56: SI | AG56: =ROUND(IF(AF56="SI",W56*$AG$5,0),-3) -> 92000 | AI56: =ROUND(IF(AH56="SI",W56*$AI$5,0),-3) -> 0 | AK56: =IF(AJ56="SI",W56*$AK$5,0) -> 0 | AL56: =SUMIF('Otras Asesorías y Préstamos'!$B$7:$B$242,B56,'Otras Asesorías y Préstamos'!$F$7:$F$242) -> 0 | AM56: =SUMIF('Otras Asesorías y Préstamos'!$B$7:$B$242,B56,'Otras Asesorías y Préstamos'!$V$7:$V$242) -> 0 | AN56: =ROUND(SUM(W56:AL56),-3) -> 1707000
A57: =+A56+1 -> 4 | B57: CORTIJO DE RESTREPO S A S | C57: =_xlfn.XLOOKUP(B57,Códigos!$B$8:$B$406,Códigos!$A$8:$A$406,"Verificar",0) -> 9 | D57: =_xlfn.XLOOKUP(B57,'Consolidado Cobros'!$B$10:$B$312,'Consolidado Cobros'!$C$10:$C$312,"Verificar",0) -> 811017889 | E57: =IF((MOD((VALUE(MID(TEXT(D57,"000000000000000"),15,1))*3+VALUE(MID(TEXT(D57,"000000000000000"),14,1))*7+VALUE(MID(TEXT(D57,"000000000000000"),13,1))*13+VALUE(MID(TEXT(D57,"000000000000000"),12,1))*17+VALUE(MID(TEXT(D57,"000000000000000"),11,1))*19+VALUE(MID(TEXT(D57,"000000000000000"),10,1))*23+VALUE(MID(TEXT(D57,"000000000000000"),9,1))*29+VALUE(MID(TEXT(D57,"000000000000000"),8,1))*37+VALUE(MID(TEXT(D57,"000000000000000"),7,1))*41+VALUE(MID(TEXT(D57,"000000000000000"),6,1))*43+VALUE(MID(TEXT(D57,"000000000000000"),5,1))*47+VALUE(MID(TEXT(D57,"000000000000000"),4,1))*53+VALUE(MID(TEXT(D57,"000000000000000"),3,1))*59+VALUE(MID(TEXT(D57,"000000000000000"),2,1))*67+VALUE(MID(TEXT(D57,"000000000000000"),1,1))*71),11))=0,0,IF((MOD((VALUE(MID(TEXT(D57,"000000000000000"),15,1))*3+VALUE(MID(TEXT(D57,"000000000000000"),14,1))*7+VALUE(MID(TEXT(D57,"000000000000000"),13,1))*13+VALUE(MID(TEXT(D57,"000000000000000"),12,1))*17+VALUE(MID(TEXT(D57,"000000000000000"),11,1))*19+VALUE(MID(TEXT(D57,"000000000000000"),10,1))*23+VALUE(MID(TEXT(D57,"000000000000000"),9,1))*29+VALUE(MID(TEXT(D57,"000000000000000"),8,1))*37+VALUE(MID(TEXT(D57,"000000000000000"),7,1))*41+VALUE(MID(TEXT(D57,"000000000000000"),6,1))*43+VALUE(MID(TEXT(D57,"000000000000000"),5,1))*47+VALUE(MID(TEXT(D57,"000000000000000"),4,1))*53+VALUE(MID(TEXT(D57,"000000000000000"),3,1))*59+VALUE(MID(TEXT(D57,"000000000000000"),2,1))*67+VALUE(MID(TEXT(D57,"000000000000000"),1,1))*71),11))=1,1,11-(MOD((VALUE(MID(TEXT(D57,"000000000000000"),15,1))*3+VALUE(MID(TEXT(D57,"000000000000000"),14,1))*7+VALUE(MID(TEXT(D57,"000000000000000"),13,1))*13+VALUE(MID(TEXT(D57,"000000000000000"),12,1))*17+VALUE(MID(TEXT(D57,"000000000000000"),11,1))*19+VALUE(MID(TEXT(D57,"000000000000000"),10,1))*23+VALUE(MID(TEXT(D57,"000000000000000"),9,1))*29+VALUE(MID(TEXT(D57,"000000000000000"),8,1))*37+VALUE(MID(TEXT(D57,"000000000000000"),7,1))*41+VALUE(MID(TEXT(D57,"000000000000000"),6,1))*43+VALUE(MID(TEXT(D57,"000000000000000"),5,1))*47+VALUE(MID(TEXT(D57,"000000000000000"),4,1))*53+VALUE(MID(TEXT(D57,"000000000000000"),3,1))*59+VALUE(MID(TEXT(D57,"000000000000000"),2,1))*67+VALUE(MID(TEXT(D57,"000000000000000"),1,1))*71),11)))) -> 7 | F57: =+AN57 -> 5146000 | G57: =+F57*$G$5 -> 977740 | H57: S | I57: =IF(H57="S",-F57*$I$5,"NO RETENCIÓN") -> -566060 | J57: =+F57+G57 -> 6123740 | K57: =SUM(F57:I57) -> 5557680 | M57: GTFF-166 | N57: Correo y Wpp | O57: 45974 | P57: ABONO | Q57: Abonaron $5.000.000 25/11/2025 | R57: =+AM57 -> 0 | T57: Fra más -JUAN JOSÉ RESTREPO P. Y FAMILIA -Ver Grupos Familiares- | V57: SI | W57: =ROUND(IF(V57="SI",SUMIF('Facturas año anterior'!$B$8:$B$81,B57,'Facturas año anterior'!$V$8:$V$81)*(100%+$W$5),0),-3)+ROUND(IF(V57="SI",SUMIF('C de C año anterior'!$B$8:$B$210,B57,'C de C año anterior'!$Q$8:$Q$210)*(100%+$W$5),0),-3) -> 1823000 | Y57: =ROUND(IF(X57="SI",W57*$Y$5,0),-3) -> 0 | Z57: SI | AA57: =ROUND(IF(Z57="SI",W57*$AA$5,0),-3) -> 1367000 | AC57: =ROUND(IF(AB57="SI",W57*$AC$5,0),-3) -> 0 | AE57: =ROUND(IF(AD57="SI",W57*$AE$5,0),-3) -> 0 | AF57: SI | AG57: =ROUND(IF(AF57="SI",W57*$AG$5,0),-3) -> 182000 | AI57: =ROUND(IF(AH57="SI",W57*$AI$5,0),-3) -> 0 | AK57: =IF(AJ57="SI",W57*$AK$5,0) -> 0 | AL57: =SUMIF('Otras Asesorías y Préstamos'!$B$7:$B$242,B57,'Otras Asesorías y Préstamos'!$F$7:$F$242) -> 1773794.9 | AM57: =SUMIF('Otras Asesorías y Préstamos'!$B$7:$B$242,B57,'Otras Asesorías y Préstamos'!$V$7:$V$242) -> 0 | AN57: =ROUND(SUM(W57:AL57),-3) -> 5146000
A58: =+A57+1 -> 5 | B58: ECHAVARRÍA Y COMPAÑÍA LTDA EN LIQUIDACIÓN | C58: =_xlfn.XLOOKUP(B58,Códigos!$B$8:$B$406,Códigos!$A$8:$A$406,"Verificar",0) -> 10 | D58: =_xlfn.XLOOKUP(B58,'Consolidado Cobros'!$B$10:$B$312,'Consolidado Cobros'!$C$10:$C$312,"Verificar",0) -> 890911921 | E58: =IF((MOD((VALUE(MID(TEXT(D58,"000000000000000"),15,1))*3+VALUE(MID(TEXT(D58,"000000000000000"),14,1))*7+VALUE(MID(TEXT(D58,"000000000000000"),13,1))*13+VALUE(MID(TEXT(D58,"000000000000000"),12,1))*17+VALUE(MID(TEXT(D58,"000000000000000"),11,1))*19+VALUE(MID(TEXT(D58,"000000000000000"),10,1))*23+VALUE(MID(TEXT(D58,"000000000000000"),9,1))*29+VALUE(MID(TEXT(D58,"000000000000000"),8,1))*37+VALUE(MID(TEXT(D58,"000000000000000"),7,1))*41+VALUE(MID(TEXT(D58,"000000000000000"),6,1))*43+VALUE(MID(TEXT(D58,"000000000000000"),5,1))*47+VALUE(MID(TEXT(D58,"000000000000000"),4,1))*53+VALUE(MID(TEXT(D58,"000000000000000"),3,1))*59+VALUE(MID(TEXT(D58,"000000000000000"),2,1))*67+VALUE(MID(TEXT(D58,"000000000000000"),1,1))*71),11))=0,0,IF((MOD((VALUE(MID(TEXT(D58,"000000000000000"),15,1))*3+VALUE(MID(TEXT(D58,"000000000000000"),14,1))*7+VALUE(MID(TEXT(D58,"000000000000000"),13,1))*13+VALUE(MID(TEXT(D58,"000000000000000"),12,1))*17+VALUE(MID(TEXT(D58,"000000000000000"),11,1))*19+VALUE(MID(TEXT(D58,"000000000000000"),10,1))*23+VALUE(MID(TEXT(D58,"000000000000000"),9,1))*29+VALUE(MID(TEXT(D58,"000000000000000"),8,1))*37+VALUE(MID(TEXT(D58,"000000000000000"),7,1))*41+VALUE(MID(TEXT(D58,"000000000000000"),6,1))*43+VALUE(MID(TEXT(D58,"000000000000000"),5,1))*47+VALUE(MID(TEXT(D58,"000000000000000"),4,1))*53+VALUE(MID(TEXT(D58,"000000000000000"),3,1))*59+VALUE(MID(TEXT(D58,"000000000000000"),2,1))*67+VALUE(MID(TEXT(D58,"000000000000000"),1,1))*71),11))=1,1,11-(MOD((VALUE(MID(TEXT(D58,"000000000000000"),15,1))*3+VALUE(MID(TEXT(D58,"000000000000000"),14,1))*7+VALUE(MID(TEXT(D58,"000000000000000"),13,1))*13+VALUE(MID(TEXT(D58,"000000000000000"),12,1))*17+VALUE(MID(TEXT(D58,"000000000000000"),11,1))*19+VALUE(MID(TEXT(D58,"000000000000000"),10,1))*23+VALUE(MID(TEXT(D58,"000000000000000"),9,1))*29+VALUE(MID(TEXT(D58,"000000000000000"),8,1))*37+VALUE(MID(TEXT(D58,"000000000000000"),7,1))*41+VALUE(MID(TEXT(D58,"000000000000000"),6,1))*43+VALUE(MID(TEXT(D58,"000000000000000"),5,1))*47+VALUE(MID(TEXT(D58,"000000000000000"),4,1))*53+VALUE(MID(TEXT(D58,"000000000000000"),3,1))*59+VALUE(MID(TEXT(D58,"000000000000000"),2,1))*67+VALUE(MID(TEXT(D58,"000000000000000"),1,1))*71),11)))) -> 7 | F58: =+AN58 -> 7938000 | G58: =+F58*$G$5 -> 1508220 | H58: S | I58: =IF(H58="S",-F58*$I$5,"NO RETENCIÓN") -> -873180 | J58: =+F58+G58 -> 9446220 | K58: =SUM(F58:I58) -> 8573040 | R58: =+AM58 -> 0 | T58: CH No. 0231402-4 Itaú $31.971.240 | V58: SI | W58: =7553000*(1+$W$5) -> 7938203 | AA58: =ROUND(IF(Z58="SI",W58*$AA$5,0),-3) -> 0 | AN58: =ROUND(SUM(W58:AL58),-3) -> 7938000 | AP58: =+'Facturas año anterior'!F58 -> 7180000 | AQ58: =+AP58*5.2% -> 373360 | AR58: =+AP58+AQ58 -> 7553360
A59: =+A58+1 -> 6 | B59: INMOBILIARIA EL CARMELO S A S EN LIQUIDACIÓN | C59: =_xlfn.XLOOKUP(B59,Códigos!$B$8:$B$406,Códigos!$A$8:$A$406,"Verificar",0) -> 245 | D59: =_xlfn.XLOOKUP(B59,'Consolidado Cobros'!$B$10:$B$312,'Consolidado Cobros'!$C$10:$C$312,"Verificar",0) -> 900666782 | E59: =IF((MOD((VALUE(MID(TEXT(D59,"000000000000000"),15,1))*3+VALUE(MID(TEXT(D59,"000000000000000"),14,1))*7+VALUE(MID(TEXT(D59,"000000000000000"),13,1))*13+VALUE(MID(TEXT(D59,"000000000000000"),12,1))*17+VALUE(MID(TEXT(D59,"000000000000000"),11,1))*19+VALUE(MID(TEXT(D59,"000000000000000"),10,1))*23+VALUE(MID(TEXT(D59,"000000000000000"),9,1))*29+VALUE(MID(TEXT(D59,"000000000000000"),8,1))*37+VALUE(MID(TEXT(D59,"000000000000000"),7,1))*41+VALUE(MID(TEXT(D59,"000000000000000"),6,1))*43+VALUE(MID(TEXT(D59,"000000000000000"),5,1))*47+VALUE(MID(TEXT(D59,"000000000000000"),4,1))*53+VALUE(MID(TEXT(D59,"000000000000000"),3,1))*59+VALUE(MID(TEXT(D59,"000000000000000"),2,1))*67+VALUE(MID(TEXT(D59,"000000000000000"),1,1))*71),11))=0,0,IF((MOD((VALUE(MID(TEXT(D59,"000000000000000"),15,1))*3+VALUE(MID(TEXT(D59,"000000000000000"),14,1))*7+VALUE(MID(TEXT(D59,"000000000000000"),13,1))*13+VALUE(MID(TEXT(D59,"000000000000000"),12,1))*17+VALUE(MID(TEXT(D59,"000000000000000"),11,1))*19+VALUE(MID(TEXT(D59,"000000000000000"),10,1))*23+VALUE(MID(TEXT(D59,"000000000000000"),9,1))*29+VALUE(MID(TEXT(D59,"000000000000000"),8,1))*37+VALUE(MID(TEXT(D59,"000000000000000"),7,1))*41+VALUE(MID(TEXT(D59,"000000000000000"),6,1))*43+VALUE(MID(TEXT(D59,"000000000000000"),5,1))*47+VALUE(MID(TEXT(D59,"000000000000000"),4,1))*53+VALUE(MID(TEXT(D59,"000000000000000"),3,1))*59+VALUE(MID(TEXT(D59,"000000000000000"),2,1))*67+VALUE(MID(TEXT(D59,"000000000000000"),1,1))*71),11))=1,1,11-(MOD((VALUE(MID(TEXT(D59,"000000000000000"),15,1))*3+VALUE(MID(TEXT(D59,"000000000000000"),14,1))*7+VALUE(MID(TEXT(D59,"000000000000000"),13,1))*13+VALUE(MID(TEXT(D59,"000000000000000"),12,1))*17+VALUE(MID(TEXT(D59,"000000000000000"),11,1))*19+VALUE(MID(TEXT(D59,"000000000000000"),10,1))*23+VALUE(MID(TEXT(D59,"000000000000000"),9,1))*29+VALUE(MID(TEXT(D59,"000000000000000"),8,1))*37+VALUE(MID(TEXT(D59,"000000000000000"),7,1))*41+VALUE(MID(TEXT(D59,"000000000000000"),6,1))*43+VALUE(MID(TEXT(D59,"000000000000000"),5,1))*47+VALUE(MID(TEXT(D59,"000000000000000"),4,1))*53+VALUE(MID(TEXT(D59,"000000000000000"),3,1))*59+VALUE(MID(TEXT(D59,"000000000000000"),2,1))*67+VALUE(MID(TEXT(D59,"000000000000000"),1,1))*71),11)))) -> 4 | F59: =+AN59 -> 1508000 | G59: =+F59*$G$5 -> 286520 | H59: S | I59: =IF(H59="S",-F59*$I$5,"NO RETENCIÓN") -> -165880 | J59: =+F59+G59 -> 1794520 | K59: =SUM(F59:I59) -> 1628640 | R59: =+AM59 -> 0 | V59: SI | W59: 815000 | Y59: =ROUND(IF(X59="SI",W59*$Y$5,0),-3) -> 0 | Z59: SI | AA59: =ROUND(IF(Z59="SI",W59*$AA$5,0),-3) -> 611000 | AC59: =ROUND(IF(AB59="SI",W59*$AC$5,0),-3) -> 0 | AE59: =ROUND(IF(AD59="SI",W59*$AE$5,0),-3) -> 0 | AF59: SI | AG59: =ROUND(IF(AF59="SI",W59*$AG$5,0),-3) -> 82000 | AI59: =ROUND(IF(AH59="SI",W59*$AI$5,0),-3) -> 0 | AK59: =IF(AJ59="SI",W59*$AK$5,0) -> 0 | AL59: =SUMIF('Otras Asesorías y Préstamos'!$B$7:$B$242,B59,'Otras Asesorías y Préstamos'!$F$7:$F$242) -> 0 | AM59: =SUMIF('Otras Asesorías y Préstamos'!$B$7:$B$242,B59,'Otras Asesorías y Préstamos'!$V$7:$V$242) -> 0 | AN59: =ROUND(SUM(W59:AL59),-3) -> 1508000
A60: =+A59+1 -> 7 | B60: INMOBILIARIA NATIVA S A S | C60: =_xlfn.XLOOKUP(B60,Códigos!$B$8:$B$406,Códigos!$A$8:$A$406,"Verificar",0) -> 196 | D60: =_xlfn.XLOOKUP(B60,'Consolidado Cobros'!$B$10:$B$312,'Consolidado Cobros'!$C$10:$C$312,"Verificar",0) -> 901445237 | E60: =IF((MOD((VALUE(MID(TEXT(D60,"000000000000000"),15,1))*3+VALUE(MID(TEXT(D60,"000000000000000"),14,1))*7+VALUE(MID(TEXT(D60,"000000000000000"),13,1))*13+VALUE(MID(TEXT(D60,"000000000000000"),12,1))*17+VALUE(MID(TEXT(D60,"000000000000000"),11,1))*19+VALUE(MID(TEXT(D60,"000000000000000"),10,1))*23+VALUE(MID(TEXT(D60,"000000000000000"),9,1))*29+VALUE(MID(TEXT(D60,"000000000000000"),8,1))*37+VALUE(MID(TEXT(D60,"000000000000000"),7,1))*41+VALUE(MID(TEXT(D60,"000000000000000"),6,1))*43+VALUE(MID(TEXT(D60,"000000000000000"),5,1))*47+VALUE(MID(TEXT(D60,"000000000000000"),4,1))*53+VALUE(MID(TEXT(D60,"000000000000000"),3,1))*59+VALUE(MID(TEXT(D60,"000000000000000"),2,1))*67+VALUE(MID(TEXT(D60,"000000000000000"),1,1))*71),11))=0,0,IF((MOD((VALUE(MID(TEXT(D60,"000000000000000"),15,1))*3+VALUE(MID(TEXT(D60,"000000000000000"),14,1))*7+VALUE(MID(TEXT(D60,"000000000000000"),13,1))*13+VALUE(MID(TEXT(D60,"000000000000000"),12,1))*17+VALUE(MID(TEXT(D60,"000000000000000"),11,1))*19+VALUE(MID(TEXT(D60,"000000000000000"),10,1))*23+VALUE(MID(TEXT(D60,"000000000000000"),9,1))*29+VALUE(MID(TEXT(D60,"000000000000000"),8,1))*37+VALUE(MID(TEXT(D60,"000000000000000"),7,1))*41+VALUE(MID(TEXT(D60,"000000000000000"),6,1))*43+VALUE(MID(TEXT(D60,"000000000000000"),5,1))*47+VALUE(MID(TEXT(D60,"000000000000000"),4,1))*53+VALUE(MID(TEXT(D60,"000000000000000"),3,1))*59+VALUE(MID(TEXT(D60,"000000000000000"),2,1))*67+VALUE(MID(TEXT(D60,"000000000000000"),1,1))*71),11))=1,1,11-(MOD((VALUE(MID(TEXT(D60,"000000000000000"),15,1))*3+VALUE(MID(TEXT(D60,"000000000000000"),14,1))*7+VALUE(MID(TEXT(D60,"000000000000000"),13,1))*13+VALUE(MID(TEXT(D60,"000000000000000"),12,1))*17+VALUE(MID(TEXT(D60,"000000000000000"),11,1))*19+VALUE(MID(TEXT(D60,"000000000000000"),10,1))*23+VALUE(MID(TEXT(D60,"000000000000000"),9,1))*29+VALUE(MID(TEXT(D60,"000000000000000"),8,1))*37+VALUE(MID(TEXT(D60,"000000000000000"),7,1))*41+VALUE(MID(TEXT(D60,"000000000000000"),6,1))*43+VALUE(MID(TEXT(D60,"000000000000000"),5,1))*47+VALUE(MID(TEXT(D60,"000000000000000"),4,1))*53+VALUE(MID(TEXT(D60,"000000000000000"),3,1))*59+VALUE(MID(TEXT(D60,"000000000000000"),2,1))*67+VALUE(MID(TEXT(D60,"000000000000000"),1,1))*71),11)))) -> 7 | F60: =+AN60-10000 -> 3700000 | G60: =+F60*$G$5 -> 703000 | H60: S | I60: =IF(H60="S",-F60*$I$5,"NO RETENCIÓN") -> -407000 | J60: =+F60+G60 -> 4403000 | K60: =SUM(F60:I60) -> 3996000 | R60: =+AM60 -> 0 | T60: Se actualiza el valor al minimo aproximadamente- Se iguala al minímo | V60: SI | W60: 1400000 | Y60: =ROUND(IF(X60="SI",W60*$Y$5,0),-3) -> 0 | Z60: SI | AA60: =ROUND(IF(Z60="SI",W60*$AA$5,0),-3)*2 -> 2100000 | AC60: =ROUND(IF(AB60="SI",W60*$AC$5,0),-3) -> 0 | AE60: =ROUND(IF(AD60="SI",W60*$AE$5,0),-3) -> 0 | AF60: SI | AG60: =ROUND(IF(AF60="SI",W60*$AG$5,0),-3) -> 140000 | AI60: =ROUND(IF(AH60="SI",W60*$AI$5,0),-3) -> 0 | AK60: =IF(AJ60="SI",W60*$AK$5,0) -> 0 | AL60: =SUMIF('Otras Asesorías y Préstamos'!$B$7:$B$242,B60,'Otras Asesorías y Préstamos'!$F$7:$F$242) -> 70000 | AM60: =SUMIF('Otras Asesorías y Préstamos'!$B$7:$B$242,B60,'Otras Asesorías y Préstamos'!$V$7:$V$242) -> 0 | AN60: =ROUND(SUM(W60:AL60),-3) -> 3710000
A61: =+A60+1 -> 8 | B61: INMOBILIARIA GILINVERSIONES S A S | C61: =_xlfn.XLOOKUP(B61,Códigos!$B$8:$B$406,Códigos!$A$8:$A$406,"Verificar",0) -> 19 | D61: =_xlfn.XLOOKUP(B61,'Consolidado Cobros'!$B$10:$B$312,'Consolidado Cobros'!$C$10:$C$312,"Verificar",0) -> 900478289 | E61: =IF((MOD((VALUE(MID(TEXT(D61,"000000000000000"),15,1))*3+VALUE(MID(TEXT(D61,"000000000000000"),14,1))*7+VALUE(MID(TEXT(D61,"000000000000000"),13,1))*13+VALUE(MID(TEXT(D61,"000000000000000"),12,1))*17+VALUE(MID(TEXT(D61,"000000000000000"),11,1))*19+VALUE(MID(TEXT(D61,"000000000000000"),10,1))*23+VALUE(MID(TEXT(D61,"000000000000000"),9,1))*29+VALUE(MID(TEXT(D61,"000000000000000"),8,1))*37+VALUE(MID(TEXT(D61,"000000000000000"),7,1))*41+VALUE(MID(TEXT(D61,"000000000000000"),6,1))*43+VALUE(MID(TEXT(D61,"000000000000000"),5,1))*47+VALUE(MID(TEXT(D61,"000000000000000"),4,1))*53+VALUE(MID(TEXT(D61,"000000000000000"),3,1))*59+VALUE(MID(TEXT(D61,"000000000000000"),2,1))*67+VALUE(MID(TEXT(D61,"000000000000000"),1,1))*71),11))=0,0,IF((MOD((VALUE(MID(TEXT(D61,"000000000000000"),15,1))*3+VALUE(MID(TEXT(D61,"000000000000000"),14,1))*7+VALUE(MID(TEXT(D61,"000000000000000"),13,1))*13+VALUE(MID(TEXT(D61,"000000000000000"),12,1))*17+VALUE(MID(TEXT(D61,"000000000000000"),11,1))*19+VALUE(MID(TEXT(D61,"000000000000000"),10,1))*23+VALUE(MID(TEXT(D61,"000000000000000"),9,1))*29+VALUE(MID(TEXT(D61,"000000000000000"),8,1))*37+VALUE(MID(TEXT(D61,"000000000000000"),7,1))*41+VALUE(MID(TEXT(D61,"000000000000000"),6,1))*43+VALUE(MID(TEXT(D61,"000000000000000"),5,1))*47+VALUE(MID(TEXT(D61,"000000000000000"),4,1))*53+VALUE(MID(TEXT(D61,"000000000000000"),3,1))*59+VALUE(MID(TEXT(D61,"000000000000000"),2,1))*67+VALUE(MID(TEXT(D61,"000000000000000"),1,1))*71),11))=1,1,11-(MOD((VALUE(MID(TEXT(D61,"000000000000000"),15,1))*3+VALUE(MID(TEXT(D61,"000000000000000"),14,1))*7+VALUE(MID(TEXT(D61,"000000000000000"),13,1))*13+VALUE(MID(TEXT(D61,"000000000000000"),12,1))*17+VALUE(MID(TEXT(D61,"000000000000000"),11,1))*19+VALUE(MID(TEXT(D61,"000000000000000"),10,1))*23+VALUE(MID(TEXT(D61,"000000000000000"),9,1))*29+VALUE(MID(TEXT(D61,"000000000000000"),8,1))*37+VALUE(MID(TEXT(D61,"000000000000000"),7,1))*41+VALUE(MID(TEXT(D61,"000000000000000"),6,1))*43+VALUE(MID(TEXT(D61,"000000000000000"),5,1))*47+VALUE(MID(TEXT(D61,"000000000000000"),4,1))*53+VALUE(MID(TEXT(D61,"000000000000000"),3,1))*59+VALUE(MID(TEXT(D61,"000000000000000"),2,1))*67+VALUE(MID(TEXT(D61,"000000000000000"),1,1))*71),11)))) -> 8 | F61: =+AN61 -> 11587000 | G61: =+F61*$G$5 -> 2201530 | H61: S | I61: =IF(H61="S",-F61*$I$5,"NO RETENCIÓN") -> -1274570 | J61: =+F61+G61 -> 13788530 | K61: =SUM(F61:I61) -> 12513960 | R61: =+AM61 -> 0 | T61: CH No. 0231402-4 Itaú $31.971.240 | V61: SI | W61: =11025000*(1+$W$5) -> 11587275 | AA61: =ROUND(IF(Z61="SI",W61*$AA$5,0),-3)*2 -> 0 | AN61: =ROUND(SUM(W61:AL61),-3) -> 11587000 | AP61: =+'Facturas año anterior'!V61 -> 10480000 | AQ61: =+AP61*5.2% -> 544960 | AR61: =+AP61+AQ61 -> 11024960
A62: =+A61+1 -> 9 | B62: INVERSIONES CIRPUL S A S | C62: =_xlfn.XLOOKUP(B62,Códigos!$B$8:$B$406,Códigos!$A$8:$A$406,"Verificar",0) -> 290 | D62: =_xlfn.XLOOKUP(B62,'Consolidado Cobros'!$B$10:$B$312,'Consolidado Cobros'!$C$10:$C$312,"Verificar",0) -> 900792746 | E62: =IF((MOD((VALUE(MID(TEXT(D62,"000000000000000"),15,1))*3+VALUE(MID(TEXT(D62,"000000000000000"),14,1))*7+VALUE(MID(TEXT(D62,"000000000000000"),13,1))*13+VALUE(MID(TEXT(D62,"000000000000000"),12,1))*17+VALUE(MID(TEXT(D62,"000000000000000"),11,1))*19+VALUE(MID(TEXT(D62,"000000000000000"),10,1))*23+VALUE(MID(TEXT(D62,"000000000000000"),9,1))*29+VALUE(MID(TEXT(D62,"000000000000000"),8,1))*37+VALUE(MID(TEXT(D62,"000000000000000"),7,1))*41+VALUE(MID(TEXT(D62,"000000000000000"),6,1))*43+VALUE(MID(TEXT(D62,"000000000000000"),5,1))*47+VALUE(MID(TEXT(D62,"000000000000000"),4,1))*53+VALUE(MID(TEXT(D62,"000000000000000"),3,1))*59+VALUE(MID(TEXT(D62,"000000000000000"),2,1))*67+VALUE(MID(TEXT(D62,"000000000000000"),1,1))*71),11))=0,0,IF((MOD((VALUE(MID(TEXT(D62,"000000000000000"),15,1))*3+VALUE(MID(TEXT(D62,"000000000000000"),14,1))*7+VALUE(MID(TEXT(D62,"000000000000000"),13,1))*13+VALUE(MID(TEXT(D62,"000000000000000"),12,1))*17+VALUE(MID(TEXT(D62,"000000000000000"),11,1))*19+VALUE(MID(TEXT(D62,"000000000000000"),10,1))*23+VALUE(MID(TEXT(D62,"000000000000000"),9,1))*29+VALUE(MID(TEXT(D62,"000000000000000"),8,1))*37+VALUE(MID(TEXT(D62,"000000000000000"),7,1))*41+VALUE(MID(TEXT(D62,"000000000000000"),6,1))*43+VALUE(MID(TEXT(D62,"000000000000000"),5,1))*47+VALUE(MID(TEXT(D62,"000000000000000"),4,1))*53+VALUE(MID(TEXT(D62,"000000000000000"),3,1))*59+VALUE(MID(TEXT(D62,"000000000000000"),2,1))*67+VALUE(MID(TEXT(D62,"000000000000000"),1,1))*71),11))=1,1,11-(MOD((VALUE(MID(TEXT(D62,"000000000000000"),15,1))*3+VALUE(MID(TEXT(D62,"000000000000000"),14,1))*7+VALUE(MID(TEXT(D62,"000000000000000"),13,1))*13+VALUE(MID(TEXT(D62,"000000000000000"),12,1))*17+VALUE(MID(TEXT(D62,"000000000000000"),11,1))*19+VALUE(MID(TEXT(D62,"000000000000000"),10,1))*23+VALUE(MID(TEXT(D62,"000000000000000"),9,1))*29+VALUE(MID(TEXT(D62,"000000000000000"),8,1))*37+VALUE(MID(TEXT(D62,"000000000000000"),7,1))*41+VALUE(MID(TEXT(D62,"000000000000000"),6,1))*43+VALUE(MID(TEXT(D62,"000000000000000"),5,1))*47+VALUE(MID(TEXT(D62,"000000000000000"),4,1))*53+VALUE(MID(TEXT(D62,"000000000000000"),3,1))*59+VALUE(MID(TEXT(D62,"000000000000000"),2,1))*67+VALUE(MID(TEXT(D62,"000000000000000"),1,1))*71),11)))) -> 8 | F62: =+AN62 -> 3876000 | G62: =+F62*$G$5 -> 736440 | H62: S | I62: =IF(H62="S",-F62*$I$5,"NO RETENCIÓN") -> -426360 | J62: =+F62+G62 -> 4612440 | K62: =SUM(F62:I62) -> 4186080 | R62: =+AM62 -> 0 | T62: Fra más -CLARA INÉS RESTREPO P. -Ver Grupos Familiares- | V62: SI | W62: 1425000 | Y62: =ROUND(IF(X62="SI",W62*$Y$5,0),-3) -> 0 | Z62: SI | AA62: =ROUND(IF(Z62="SI",W62*$AA$5,0),-3) -> 1069000 | AC62: =ROUND(IF(AB62="SI",W62*$AC$5,0),-3) -> 0 | AE62: =ROUND(IF(AD62="SI",W62*$AE$5,0),-3) -> 0 | AF62: SI | AG62: =ROUND(IF(AF62="SI",W62*$AG$5,0),-3) -> 143000 | AI62: =ROUND(IF(AH62="SI",W62*$AI$5,0),-3) -> 0 | AK62: =IF(AJ62="SI",W62*$AK$5,0) -> 0 | AL62: =SUMIF('Otras Asesorías y Préstamos'!$B$7:$B$242,B62,'Otras Asesorías y Préstamos'!$F$7:$F$242) -> 1239211.9 | AM62: =SUMIF('Otras Asesorías y Préstamos'!$B$7:$B$242,B62,'Otras Asesorías y Préstamos'!$V$7:$V$242) -> 0 | AN62: =ROUND(SUM(W62:AL62),-3) -> 3876000
A63: =+A62+1 -> 10 | B63: INVERSIONES COBALTO S A S | C63: =_xlfn.XLOOKUP(B63,Códigos!$B$8:$B$406,Códigos!$A$8:$A$406,"Verificar",0) -> 33 | D63: =_xlfn.XLOOKUP(B63,'Consolidado Cobros'!$B$10:$B$312,'Consolidado Cobros'!$C$10:$C$312,"Verificar",0) -> 901241763 | E63: =IF((MOD((VALUE(MID(TEXT(D63,"000000000000000"),15,1))*3+VALUE(MID(TEXT(D63,"000000000000000"),14,1))*7+VALUE(MID(TEXT(D63,"000000000000000"),13,1))*13+VALUE(MID(TEXT(D63,"000000000000000"),12,1))*17+VALUE(MID(TEXT(D63,"000000000000000"),11,1))*19+VALUE(MID(TEXT(D63,"000000000000000"),10,1))*23+VALUE(MID(TEXT(D63,"000000000000000"),9,1))*29+VALUE(MID(TEXT(D63,"000000000000000"),8,1))*37+VALUE(MID(TEXT(D63,"000000000000000"),7,1))*41+VALUE(MID(TEXT(D63,"000000000000000"),6,1))*43+VALUE(MID(TEXT(D63,"000000000000000"),5,1))*47+VALUE(MID(TEXT(D63,"000000000000000"),4,1))*53+VALUE(MID(TEXT(D63,"000000000000000"),3,1))*59+VALUE(MID(TEXT(D63,"000000000000000"),2,1))*67+VALUE(MID(TEXT(D63,"000000000000000"),1,1))*71),11))=0,0,IF((MOD((VALUE(MID(TEXT(D63,"000000000000000"),15,1))*3+VALUE(MID(TEXT(D63,"000000000000000"),14,1))*7+VALUE(MID(TEXT(D63,"000000000000000"),13,1))*13+VALUE(MID(TEXT(D63,"000000000000000"),12,1))*17+VALUE(MID(TEXT(D63,"000000000000000"),11,1))*19+VALUE(MID(TEXT(D63,"000000000000000"),10,1))*23+VALUE(MID(TEXT(D63,"000000000000000"),9,1))*29+VALUE(MID(TEXT(D63,"000000000000000"),8,1))*37+VALUE(MID(TEXT(D63,"000000000000000"),7,1))*41+VALUE(MID(TEXT(D63,"000000000000000"),6,1))*43+VALUE(MID(TEXT(D63,"000000000000000"),5,1))*47+VALUE(MID(TEXT(D63,"000000000000000"),4,1))*53+VALUE(MID(TEXT(D63,"000000000000000"),3,1))*59+VALUE(MID(TEXT(D63,"000000000000000"),2,1))*67+VALUE(MID(TEXT(D63,"000000000000000"),1,1))*71),11))=1,1,11-(MOD((VALUE(MID(TEXT(D63,"000000000000000"),15,1))*3+VALUE(MID(TEXT(D63,"000000000000000"),14,1))*7+VALUE(MID(TEXT(D63,"000000000000000"),13,1))*13+VALUE(MID(TEXT(D63,"000000000000000"),12,1))*17+VALUE(MID(TEXT(D63,"000000000000000"),11,1))*19+VALUE(MID(TEXT(D63,"000000000000000"),10,1))*23+VALUE(MID(TEXT(D63,"000000000000000"),9,1))*29+VALUE(MID(TEXT(D63,"000000000000000"),8,1))*37+VALUE(MID(TEXT(D63,"000000000000000"),7,1))*41+VALUE(MID(TEXT(D63,"000000000000000"),6,1))*43+VALUE(MID(TEXT(D63,"000000000000000"),5,1))*47+VALUE(MID(TEXT(D63,"000000000000000"),4,1))*53+VALUE(MID(TEXT(D63,"000000000000000"),3,1))*59+VALUE(MID(TEXT(D63,"000000000000000"),2,1))*67+VALUE(MID(TEXT(D63,"000000000000000"),1,1))*71),11)))) -> 3 | F63: =+AN63 -> 3377000 | G63: =+F63*$G$5 -> 641630 | H63: S | I63: =IF(H63="S",-F63*$I$5,"NO RETENCIÓN") -> -371470 | J63: =+F63+G63 -> 4018630 | K63: =SUM(F63:I63) -> 3647160 | R63: =+AM63 -> 0 | V63: SI | W63: 1825000 | Y63: =ROUND(IF(X63="SI",W63*$Y$5,0),-3) -> 0 | Z63: SI | AA63: =ROUND(IF(Z63="SI",W63*$AA$5,0),-3) -> 1369000 | AC63: =ROUND(IF(AB63="SI",W63*$AC$5,0),-3) -> 0 | AE63: =ROUND(IF(AD63="SI",W63*$AE$5,0),-3) -> 0 | AF63: SI | AG63: =ROUND(IF(AF63="SI",W63*$AG$5,0),-3) -> 183000 | AI63: =ROUND(IF(AH63="SI",W63*$AI$5,0),-3) -> 0 | AK63: =IF(AJ63="SI",W63*$AK$5,0) -> 0 | AL63: =SUMIF('Otras Asesorías y Préstamos'!$B$7:$B$242,B63,'Otras Asesorías y Préstamos'!$F$7:$F$242) -> 0 | AM63: =SUMIF('Otras Asesorías y Préstamos'!$B$7:$B$242,B63,'Otras Asesorías y Préstamos'!$V$7:$V$242) -> 0 | AN63: =ROUND(SUM(W63:AL63),-3) -> 3377000
A64: =+A63+1 -> 11 | B64: INVERSIONES EL MANGLE S A S | C64: =_xlfn.XLOOKUP(B64,Códigos!$B$8:$B$406,Códigos!$A$8:$A$406,"Verificar",0) -> 291 | D64: =_xlfn.XLOOKUP(B64,'Consolidado Cobros'!$B$10:$B$312,'Consolidado Cobros'!$C$10:$C$312,"Verificar",0) -> 900797164 | E64: =IF((MOD((VALUE(MID(TEXT(D64,"000000000000000"),15,1))*3+VALUE(MID(TEXT(D64,"000000000000000"),14,1))*7+VALUE(MID(TEXT(D64,"000000000000000"),13,1))*13+VALUE(MID(TEXT(D64,"000000000000000"),12,1))*17+VALUE(MID(TEXT(D64,"000000000000000"),11,1))*19+VALUE(MID(TEXT(D64,"000000000000000"),10,1))*23+VALUE(MID(TEXT(D64,"000000000000000"),9,1))*29+VALUE(MID(TEXT(D64,"000000000000000"),8,1))*37+VALUE(MID(TEXT(D64,"000000000000000"),7,1))*41+VALUE(MID(TEXT(D64,"000000000000000"),6,1))*43+VALUE(MID(TEXT(D64,"000000000000000"),5,1))*47+VALUE(MID(TEXT(D64,"000000000000000"),4,1))*53+VALUE(MID(TEXT(D64,"000000000000000"),3,1))*59+VALUE(MID(TEXT(D64,"000000000000000"),2,1))*67+VALUE(MID(TEXT(D64,"000000000000000"),1,1))*71),11))=0,0,IF((MOD((VALUE(MID(TEXT(D64,"000000000000000"),15,1))*3+VALUE(MID(TEXT(D64,"000000000000000"),14,1))*7+VALUE(MID(TEXT(D64,"000000000000000"),13,1))*13+VALUE(MID(TEXT(D64,"000000000000000"),12,1))*17+VALUE(MID(TEXT(D64,"000000000000000"),11,1))*19+VALUE(MID(TEXT(D64,"000000000000000"),10,1))*23+VALUE(MID(TEXT(D64,"000000000000000"),9,1))*29+VALUE(MID(TEXT(D64,"000000000000000"),8,1))*37+VALUE(MID(TEXT(D64,"000000000000000"),7,1))*41+VALUE(MID(TEXT(D64,"000000000000000"),6,1))*43+VALUE(MID(TEXT(D64,"000000000000000"),5,1))*47+VALUE(MID(TEXT(D64,"000000000000000"),4,1))*53+VALUE(MID(TEXT(D64,"000000000000000"),3,1))*59+VALUE(MID(TEXT(D64,"000000000000000"),2,1))*67+VALUE(MID(TEXT(D64,"000000000000000"),1,1))*71),11))=1,1,11-(MOD((VALUE(MID(TEXT(D64,"000000000000000"),15,1))*3+VALUE(MID(TEXT(D64,"000000000000000"),14,1))*7+VALUE(MID(TEXT(D64,"000000000000000"),13,1))*13+VALUE(MID(TEXT(D64,"000000000000000"),12,1))*17+VALUE(MID(TEXT(D64,"000000000000000"),11,1))*19+VALUE(MID(TEXT(D64,"000000000000000"),10,1))*23+VALUE(MID(TEXT(D64,"000000000000000"),9,1))*29+VALUE(MID(TEXT(D64,"000000000000000"),8,1))*37+VALUE(MID(TEXT(D64,"000000000000000"),7,1))*41+VALUE(MID(TEXT(D64,"000000000000000"),6,1))*43+VALUE(MID(TEXT(D64,"000000000000000"),5,1))*47+VALUE(MID(TEXT(D64,"000000000000000"),4,1))*53+VALUE(MID(TEXT(D64,"000000000000000"),3,1))*59+VALUE(MID(TEXT(D64,"000000000000000"),2,1))*67+VALUE(MID(TEXT(D64,"000000000000000"),1,1))*71),11)))) -> 4 | F64: =+AN64 -> 2637000 | G64: =+F64*$G$5 -> 501030 | H64: S | I64: =IF(H64="S",-F64*$I$5,"NO RETENCIÓN") -> -290070 | J64: =+F64+G64 -> 3138030 | K64: =SUM(F64:I64) -> 2847960 | R64: =+AM64 -> 0 | V64: SI | W64: 1425000 | Y64: =ROUND(IF(X64="SI",W64*$Y$5,0),-3) -> 0 | Z64: SI | AA64: =ROUND(IF(Z64="SI",W64*$AA$5,0),-3) -> 1069000 | AC64: =ROUND(IF(AB64="SI",W64*$AC$5,0),-3) -> 0 | AE64: =ROUND(IF(AD64="SI",W64*$AE$5,0),-3) -> 0 | AF64: SI | AG64: =ROUND(IF(AF64="SI",W64*$AG$5,0),-3) -> 143000 | AI64: =ROUND(IF(AH64="SI",W64*$AI$5,0),-3) -> 0 | AK64: =IF(AJ64="SI",W64*$AK$5,0) -> 0 | AL64: =SUMIF('Otras Asesorías y Préstamos'!$B$7:$B$242,B64,'Otras Asesorías y Préstamos'!$F$7:$F$242) -> 0 | AM64: =SUMIF('Otras Asesorías y Préstamos'!$B$7:$B$242,B64,'Otras Asesorías y Préstamos'!$V$7:$V$242) -> 0 | AN64: =ROUND(SUM(W64:AL64),-3) -> 2637000
A65: =+A64+1 -> 12 | B65: INVERSIONES EL OYETO S A S | C65: =_xlfn.XLOOKUP(B65,Códigos!$B$8:$B$406,Códigos!$A$8:$A$406,"Verificar",0) -> 292 | D65: =_xlfn.XLOOKUP(B65,'Consolidado Cobros'!$B$10:$B$312,'Consolidado Cobros'!$C$10:$C$312,"Verificar",0) -> 900474585 | E65: =IF((MOD((VALUE(MID(TEXT(D65,"000000000000000"),15,1))*3+VALUE(MID(TEXT(D65,"000000000000000"),14,1))*7+VALUE(MID(TEXT(D65,"000000000000000"),13,1))*13+VALUE(MID(TEXT(D65,"000000000000000"),12,1))*17+VALUE(MID(TEXT(D65,"000000000000000"),11,1))*19+VALUE(MID(TEXT(D65,"000000000000000"),10,1))*23+VALUE(MID(TEXT(D65,"000000000000000"),9,1))*29+VALUE(MID(TEXT(D65,"000000000000000"),8,1))*37+VALUE(MID(TEXT(D65,"000000000000000"),7,1))*41+VALUE(MID(TEXT(D65,"000000000000000"),6,1))*43+VALUE(MID(TEXT(D65,"000000000000000"),5,1))*47+VALUE(MID(TEXT(D65,"000000000000000"),4,1))*53+VALUE(MID(TEXT(D65,"000000000000000"),3,1))*59+VALUE(MID(TEXT(D65,"000000000000000"),2,1))*67+VALUE(MID(TEXT(D65,"000000000000000"),1,1))*71),11))=0,0,IF((MOD((VALUE(MID(TEXT(D65,"000000000000000"),15,1))*3+VALUE(MID(TEXT(D65,"000000000000000"),14,1))*7+VALUE(MID(TEXT(D65,"000000000000000"),13,1))*13+VALUE(MID(TEXT(D65,"000000000000000"),12,1))*17+VALUE(MID(TEXT(D65,"000000000000000"),11,1))*19+VALUE(MID(TEXT(D65,"000000000000000"),10,1))*23+VALUE(MID(TEXT(D65,"000000000000000"),9,1))*29+VALUE(MID(TEXT(D65,"000000000000000"),8,1))*37+VALUE(MID(TEXT(D65,"000000000000000"),7,1))*41+VALUE(MID(TEXT(D65,"000000000000000"),6,1))*43+VALUE(MID(TEXT(D65,"000000000000000"),5,1))*47+VALUE(MID(TEXT(D65,"000000000000000"),4,1))*53+VALUE(MID(TEXT(D65,"000000000000000"),3,1))*59+VALUE(MID(TEXT(D65,"000000000000000"),2,1))*67+VALUE(MID(TEXT(D65,"000000000000000"),1,1))*71),11))=1,1,11-(MOD((VALUE(MID(TEXT(D65,"000000000000000"),15,1))*3+VALUE(MID(TEXT(D65,"000000000000000"),14,1))*7+VALUE(MID(TEXT(D65,"000000000000000"),13,1))*13+VALUE(MID(TEXT(D65,"000000000000000"),12,1))*17+VALUE(MID(TEXT(D65,"000000000000000"),11,1))*19+VALUE(MID(TEXT(D65,"000000000000000"),10,1))*23+VALUE(MID(TEXT(D65,"000000000000000"),9,1))*29+VALUE(MID(TEXT(D65,"000000000000000"),8,1))*37+VALUE(MID(TEXT(D65,"000000000000000"),7,1))*41+VALUE(MID(TEXT(D65,"000000000000000"),6,1))*43+VALUE(MID(TEXT(D65,"000000000000000"),5,1))*47+VALUE(MID(TEXT(D65,"000000000000000"),4,1))*53+VALUE(MID(TEXT(D65,"000000000000000"),3,1))*59+VALUE(MID(TEXT(D65,"000000000000000"),2,1))*67+VALUE(MID(TEXT(D65,"000000000000000"),1,1))*71),11)))) -> 5 | F65: =+AN65 -> 3929000 | G65: =+F65*$G$5 -> 746510 | H65: S | I65: =IF(H65="S",-F65*$I$5,"NO RETENCIÓN") -> -432190 | J65: =+F65+G65 -> 4675510 | K65: =SUM(F65:I65) -> 4243320 | R65: =+AM65 -> 0 | V65: SI | W65: 1825000 | Y65: =ROUND(IF(X65="SI",W65*$Y$5,0),-3) -> 0 | Z65: SI | AA65: =ROUND(IF(Z65="SI",W65*$AA$5,0),-3) -> 1369000 | AC65: =ROUND(IF(AB65="SI",W65*$AC$5,0),-3) -> 0 | AE65: =ROUND(IF(AD65="SI",W65*$AE$5,0),-3) -> 0 | AG65: =ROUND(IF(AF65="SI",W65*$AG$5,0),-3) -> 0 | AH65: SI | AI65: =ROUND(IF(AH65="SI",W65*$AI$5,0),-3) -> 365000 | AK65: =IF(AJ65="SI",W65*$AK$5,0) -> 0 | AL65: =SUMIF('Otras Asesorías y Préstamos'!$B$7:$B$242,B65,'Otras Asesorías y Préstamos'!$F$7:$F$242) -> 370000 | AM65: =SUMIF('Otras Asesorías y Préstamos'!$B$7:$B$242,B65,'Otras Asesorías y Préstamos'!$V$7:$V$242) -> 0 | AN65: =ROUND(SUM(W65:AL65),-3) -> 3929000
